{
  "220774564": {
    "Company": "VECTOR",
    "Job Title": "Entry Level IT Software Developer",
    "Job Details": "DescriptionJob Purpose:Prepares computer programs by translating specifications into software code||||Duties:* Plans program by studying specifications||||* Arranges specifications by developing logical sequence; preparing flowcharts; researching solutions||||* Encodes specifications by converting logical sequence and workflow into program language||||* Verifies encoding by performing trial runs; modifying code||||* Prepares program reference by documenting control language||||* Advances job knowledge to next level by participating in educational opportunities; reading professional publications||||* Accomplishes department and organization mission by completing related results as needed||||Skills/Qualifications:Analyzing Information, Problem Solving, Persistence, Software Performance Tuning, Attention to Detail, Software Development Fundamentals, Software Documentation, Technical Zeal, Independence, ThoroughnessMany different backgrounds are encouraged to apply: Healthcare, Engineering, Finance, IT, Telecommunications, Business Intelligence, Business Analytics, Information Systems, Computer Science, Computer Engineering etc||||Learn more about us at www||||VectorNow||||comCompetitive PayPaid Time Off (PTO)Medical/Dental/Vision/LifeJob DetailsSalary$45000 - $50000 Per YearJob Typefulltime, employeePosted 5 days ago||||",
    "KeyWords": {
      "NOUN": {
        "Purpose": "Purpose",
        "Prepares": "Prepares",
        "computer": "computer",
        "programs": "programs",
        "specifications": "specifications",
        "software": "software",
        "code": "code",
        "Duties": "Duties",
        "Plans": "Plans",
        "program": "program",
        "Arranges": "Arranges",
        "sequence": "sequence",
        "flowcharts": "flowcharts",
        "solutions": "solutions",
        "Encodes": "Encodes",
        "language": "language",
        "Verifies": "Verifies",
        "trial": "trial",
        "runs": "runs",
        "reference": "reference",
        "control": "control",
        "Advances": "Advances",
        "job": "job",
        "knowledge": "knowledge",
        "level": "level",
        "opportunities": "opportunities",
        "publications": "publications",
        "Accomplishes": "Accomplishes",
        "department": "department",
        "organization": "organization",
        "mission": "mission",
        "results": "results",
        "Skills/Qualifications": "Skills/Qualifications",
        "Information": "Information",
        "Problem": "Problem",
        "Solving": "Solving",
        "Persistence": "Persistence",
        "Software": "Software",
        "Performance": "Performance",
        "Tuning": "Tuning",
        "Attention": "Attention",
        "Detail": "Detail",
        "Development": "Development",
        "Fundamentals": "Fundamentals",
        "Documentation": "Documentation",
        "Technical": "Technical",
        "Zeal": "Zeal",
        "Independence": "Independence",
        "ThoroughnessMany": "ThoroughnessMany",
        "backgrounds": "backgrounds",
        "Healthcare": "Healthcare",
        "Engineering": "Engineering",
        "Finance": "Finance",
        "IT": "IT",
        "Telecommunications": "Telecommunications",
        "Business": "Business",
        "Intelligence": "Intelligence",
        "Analytics": "Analytics",
        "Systems": "Systems",
        "Computer": "Computer",
        "Science": "Science",
        "etc": "etc",
        "www": "www",
        "VectorNow": "VectorNow",
        "comCompetitive": "comCompetitive",
        "PayPaid": "PayPaid",
        "Time": "Time",
        "Off": "Off",
        "PTO": "PTO",
        "Medical/Dental/Vision/LifeJob": "Medical/Dental/Vision/LifeJob",
        "DetailsSalary": "DetailsSalary",
        "Per": "Per",
        "YearJob": "YearJob",
        "Typefulltime": "Typefulltime",
        "days": "days"
      },
      "VERB": {
        "studying": "studying",
        "developing": "developing",
        "preparing": "preparing",
        "researching": "researching",
        "converting": "converting",
        "workflow": "workflow",
        "encoding": "encoding",
        "performing": "performing",
        "modifying": "modifying",
        "documenting": "documenting",
        "participating": "participating",
        "reading": "reading",
        "completing": "completing",
        "Analyzing": "Analyzing",
        "are": "are",
        "encouraged": "encouraged",
        "apply": "apply",
        "Learn": "Learn",
        "employeePosted": "employeePosted"
      },
      "ADJ": {
        "logical": "logical",
        "next": "next",
        "educational": "educational",
        "professional": "professional",
        "related": "related",
        "needed": "needed",
        "different": "different",
        "more": "more"
      },
      "PRT": {
        "to": "to"
      },
      "NUM": {
        "50000": "50000"
      }
    }
  },
  "221414451": {
    "Company": "Tata Consultancy Services",
    "Job Title": "Entry Level Software Developer",
    "Job Details": "DescriptionRole: Software DeveloperLocation: Charlotte, NC // TX // GA // CAResponsibilities:    Develop, create, and modify general computer application software or specialized programs Analyze user needs and develop software solutions Design or customize software for client use to optimize operational efficiency Improve existing systems by analyzing areas of modification Analyze and design databases with application areas Coordinate database development with a team or individually Maintain systems by monitoring, identifying, and correcting software defects Create technical specifications and test plans Update knowledge and skills regularly through in-house and external courses, manuals, and new applicationsNote: Interested candidates can share resume to avinash||||aadari2@tcs||||comJob DetailsJob Typefulltime, employeePosted 7 days ago||||",
    "KeyWords": {
      "NOUN": {
        "DeveloperLocation": "DeveloperLocation",
        "Charlotte": "Charlotte",
        "NC": "NC",
        "//": "//",
        "TX": "TX",
        "GA": "GA",
        "CAResponsibilities": "CAResponsibilities",
        "Develop": "Develop",
        "create": "create",
        "computer": "computer",
        "application": "application",
        "software": "software",
        "programs": "programs",
        "Analyze": "Analyze",
        "user": "user",
        "needs": "needs",
        "solutions": "solutions",
        "Design": "Design",
        "client": "client",
        "use": "use",
        "efficiency": "efficiency",
        "Improve": "Improve",
        "systems": "systems",
        "areas": "areas",
        "modification": "modification",
        "design": "design",
        "databases": "databases",
        "Coordinate": "Coordinate",
        "database": "database",
        "development": "development",
        "team": "team",
        "Maintain": "Maintain",
        "monitoring": "monitoring",
        "identifying": "identifying",
        "defects": "defects",
        "Create": "Create",
        "specifications": "specifications",
        "test": "test",
        "plans": "plans",
        "Update": "Update",
        "knowledge": "knowledge",
        "skills": "skills",
        "in-house": "in-house",
        "courses": "courses",
        "manuals": "manuals",
        "applicationsNote": "applicationsNote",
        "candidates": "candidates",
        "share": "share",
        "tcs": "tcs",
        "DetailsJob": "DetailsJob",
        "Typefulltime": "Typefulltime",
        "days": "days"
      },
      "ADJ": {
        "general": "general",
        "specialized": "specialized",
        "operational": "operational",
        "technical": "technical",
        "external": "external",
        "new": "new",
        "Interested": "Interested",
        "comJob": "comJob"
      },
      "VERB": {
        "develop": "develop",
        "customize": "customize",
        "optimize": "optimize",
        "existing": "existing",
        "analyzing": "analyzing",
        "correcting": "correcting",
        "can": "can",
        "resume": "resume",
        "avinash": "avinash",
        "aadari2": "aadari2",
        "employeePosted": "employeePosted"
      },
      "PRT": {
        "to": "to"
      }
    }
  },
  "222046234": {
    "Company": "Ekman Associates, Inc.",
    "Job Title": "Digital Backend Developer",
    "Job Details": "",
    "KeyWords": {}
  },
  "222162289": {
    "Company": "Responsive Search",
    "Job Title": "Software Architect Service Now",
    "Job Details": "DescriptionServiceNow Architect:5-7 years of working on NOW platformExperience with developing apps, integrations and general management on the NOW platformSpecific experience with CMDB,Service Catalog requiredExperience w/ ITBM, ITSM, APM preferredExperience with the GLIDE framework especially around pushing large amounts of data back and forthExperience architecting solutions/apps on the NOW platformExperience with Workflow mgmt, UI dev on the NOW platformEntrepreneurial mindsetJob DetailsSalary$120000 - $140000 Per YearJob Typefulltime, employeePosted 1 Day ago||||",
    "KeyWords": {
      "NOUN": {
        "Architect:5-7": "Architect:5-7",
        "years": "years",
        "NOW": "NOW",
        "platformExperience": "platformExperience",
        "apps": "apps",
        "integrations": "integrations",
        "management": "management",
        "experience": "experience",
        "CMDB": "CMDB",
        "Service": "Service",
        "Catalog": "Catalog",
        "requiredExperience": "requiredExperience",
        "w/": "w/",
        "ITBM": "ITBM",
        "ITSM": "ITSM",
        "APM": "APM",
        "preferredExperience": "preferredExperience",
        "GLIDE": "GLIDE",
        "framework": "framework",
        "amounts": "amounts",
        "data": "data",
        "forthExperience": "forthExperience",
        "solutions/apps": "solutions/apps",
        "Workflow": "Workflow",
        "mgmt": "mgmt",
        "UI": "UI",
        "dev": "dev",
        "mindsetJob": "mindsetJob",
        "DetailsSalary": "DetailsSalary",
        "Per": "Per",
        "YearJob": "YearJob",
        "Typefulltime": "Typefulltime",
        "Day": "Day"
      },
      "VERB": {
        "developing": "developing",
        "platformSpecific": "platformSpecific",
        "pushing": "pushing",
        "architecting": "architecting",
        "employeePosted": "employeePosted"
      },
      "ADJ": {
        "large": "large",
        "platformEntrepreneurial": "platformEntrepreneurial"
      },
      "NUM": {
        "140000": "140000"
      }
    }
  },
  "222274794": {
    "Company": "Avery Partners",
    "Job Title": "Software Developer",
    "Job Details": "DescriptionWe are seeking a Software Developer with Full Stack Development experience to become an integral part of our team! You will be responsible for creating and modifying computer application software or specialized utility programs||||Qualified candidates must be US Citizens or Green Card holders|||| No work or student visas can be sponsored||||Responsibilities:Analyze user needs and develop software solutionsWork with project manager or product owner to meet specification needsRecommend software upgrades to optimize operational efficiencyCollaborate with other developers to design and optimize codeCreate flowcharts and user guides for new and existing programsDocument all programming tasks and proceduresPerform routine software maintenanceQualifications:Minimum of 3 years of experienceBachelor degree or related experiencePrevious experience in software development, computer engineering, or other related fieldsSolid experience with C#, MVC, JavaScript, VB||||NET, HTML, T-SQL, MS SQL Server,  and ||||NET Knowledge of Visual Studio, Telerik, DevExpress ControlsFamiliarity with relational databases such as MySQL, Oracle, and SQL ServerDeadline and detail-orientedStrong analytical and critical thinking skillsExcellent benefits package||||  Remote capabilites 80% - 100%Send resume with current contact information to nancy||||daves@averypartners||||com Job DetailsSalary$55000 - $65000 Per YearJob Typefulltime, employeePosted 5 days ago||||",
    "KeyWords": {
      "NOUN": {
        "Software": "Software",
        "Developer": "Developer",
        "Full": "Full",
        "Stack": "Stack",
        "Development": "Development",
        "experience": "experience",
        "part": "part",
        "team": "team",
        "computer": "computer",
        "application": "application",
        "software": "software",
        "utility": "utility",
        "programs": "programs",
        "candidates": "candidates",
        "Citizens": "Citizens",
        "Card": "Card",
        "holders": "holders",
        "work": "work",
        "student": "student",
        "visas": "visas",
        "Responsibilities": "Responsibilities",
        "Analyze": "Analyze",
        "user": "user",
        "needs": "needs",
        "solutionsWork": "solutionsWork",
        "project": "project",
        "manager": "manager",
        "product": "product",
        "owner": "owner",
        "upgrades": "upgrades",
        "efficiencyCollaborate": "efficiencyCollaborate",
        "developers": "developers",
        "codeCreate": "codeCreate",
        "flowcharts": "flowcharts",
        "guides": "guides",
        "programsDocument": "programsDocument",
        "programming": "programming",
        "tasks": "tasks",
        "maintenanceQualifications": "maintenanceQualifications",
        "Minimum": "Minimum",
        "years": "years",
        "experienceBachelor": "experienceBachelor",
        "degree": "degree",
        "development": "development",
        "engineering": "engineering",
        "MVC": "MVC",
        "JavaScript": "JavaScript",
        "VB": "VB",
        "NET": "NET",
        "HTML": "HTML",
        "T-SQL": "T-SQL",
        "MS": "MS",
        "SQL": "SQL",
        "Server": "Server",
        "Knowledge": "Knowledge",
        "Visual": "Visual",
        "Studio": "Studio",
        "Telerik": "Telerik",
        "DevExpress": "DevExpress",
        "ControlsFamiliarity": "ControlsFamiliarity",
        "databases": "databases",
        "MySQL": "MySQL",
        "Oracle": "Oracle",
        "ServerDeadline": "ServerDeadline",
        "thinking": "thinking",
        "skillsExcellent": "skillsExcellent",
        "benefits": "benefits",
        "package": "package",
        "Send": "Send",
        "resume": "resume",
        "contact": "contact",
        "information": "information",
        "nancy": "nancy",
        "daves": "daves",
        "averypartners": "averypartners",
        "Job": "Job",
        "DetailsSalary": "DetailsSalary",
        "Per": "Per",
        "YearJob": "YearJob",
        "Typefulltime": "Typefulltime",
        "days": "days"
      },
      "VERB": {
        "seeking": "seeking",
        "become": "become",
        "will": "will",
        "be": "be",
        "creating": "creating",
        "modifying": "modifying",
        "specialized": "specialized",
        "Qualified": "Qualified",
        "must": "must",
        "can": "can",
        "sponsored": "sponsored",
        "develop": "develop",
        "meet": "meet",
        "optimize": "optimize",
        "design": "design",
        "existing": "existing",
        "proceduresPerform": "proceduresPerform",
        "related": "related",
        "Remote": "Remote",
        "capabilites": "capabilites",
        "com": "com",
        "employeePosted": "employeePosted"
      },
      "PRT": {
        "to": "to"
      },
      "ADJ": {
        "responsible": "responsible",
        "US": "US",
        "Green": "Green",
        "specification": "specification",
        "operational": "operational",
        "other": "other",
        "new": "new",
        "routine": "routine",
        "experiencePrevious": "experiencePrevious",
        "related": "related",
        "fieldsSolid": "fieldsSolid",
        "relational": "relational",
        "such": "such",
        "detail-orientedStrong": "detail-orientedStrong",
        "analytical": "analytical",
        "critical": "critical",
        "current": "current"
      },
      "X": {},
      "NUM": {
        "100": "100",
        "55000": "55000",
        "65000": "65000"
      }
    }
  },
  "222405034": {
    "Company": "Stellar Software",
    "Job Title": "React JS Developer",
    "Job Details": "DescriptionWho We Are? Stellar Software provides innovative Marina Management software solutions to marinas across the United States|||| We recently secured funding to expand upon our product, and are currently looking for developers to grow our current team|||| This role will focus on growing our current product offering to serve a growing market|||| Our goal is to provide modern revenue producing software solutions to the marina industry||||What Are We Looking For? We are seeking Front-end Developers with 2+ years of professional experience||||Professional experience in software developmentIn depth documentation experience with complex projectsProven ability to learn new skills and demonstrate curiosityExcellent communication skillsStrategic thinking, problem-solving, and decision-making capabilitiesStrong desire to grow with the company and deliver valuable resultsWho We Are? Stellar Software provides Innovative Marina Management Software Solutions to Marina’s all across the United States||||What Are We Looking For? We’re seeking Front-end Developers with a minimum of 2-3 years experience in the field|||| Candidates will help develop industry specific Software as a Service Products||||What Are We Up To? We are greatly expanding our product offering|||| Therefore we are we are looking for developers to expand our current team|||| This role will focus on the build out of enhancements and extensions to our product offering|||| Details: Full Time or Part Time Remote, or in our office at the Atlanta Tech Village/Flexible ScheduleRequirements:CSSHTMLJavaScriptReact JSA familiarity with object-oriented software design and frameworksSherlock-style analytical and problem solving skillsExperience with design work is a significant plus, but is not required||||MUST BE AUTHORIZED TO WORK IN THE U||||S|||| (WE DO NOT SPONSOR)||||Our Website: https://boatrentalmanagement||||com/3423 Piedmont Rd NE, Suite 597 Atlanta, GA 30305Job DetailsSalary$70000 - $125000 Per YearJob Typefulltime, employeePosted 1 Day ago||||",
    "KeyWords": {
      "VERB": {
        "provides": "provides",
        "marinas": "marinas",
        "secured": "secured",
        "expand": "expand",
        "are": "are",
        "looking": "looking",
        "grow": "grow",
        "will": "will",
        "focus": "focus",
        "growing": "growing",
        "serve": "serve",
        "is": "is",
        "provide": "provide",
        "producing": "producing",
        "Are": "Are",
        "Looking": "Looking",
        "seeking": "seeking",
        "learn": "learn",
        "demonstrate": "demonstrate",
        "help": "help",
        "develop": "develop",
        "expanding": "expanding",
        "solving": "solving",
        "required": "required",
        "employeePosted": "employeePosted"
      },
      "ADJ": {
        "innovative": "innovative",
        "current": "current",
        "modern": "modern",
        "professional": "professional",
        "Professional": "Professional",
        "depth": "depth",
        "complex": "complex",
        "new": "new",
        "curiosityExcellent": "curiosityExcellent",
        "valuable": "valuable",
        "Stellar": "Stellar",
        "re": "re",
        "Front-end": "Front-end",
        "2-3": "2-3",
        "specific": "specific",
        "Full": "Full",
        "Village/Flexible": "Village/Flexible",
        "object-oriented": "object-oriented",
        "frameworksSherlock-style": "frameworksSherlock-style",
        "analytical": "analytical",
        "significant": "significant",
        "Website": "Website"
      },
      "NOUN": {
        "Marina": "Marina",
        "Management": "Management",
        "software": "software",
        "solutions": "solutions",
        "United": "United",
        "States": "States",
        "funding": "funding",
        "product": "product",
        "developers": "developers",
        "team": "team",
        "role": "role",
        "offering": "offering",
        "market": "market",
        "goal": "goal",
        "revenue": "revenue",
        "marina": "marina",
        "industry": "industry",
        "Front-end": "Front-end",
        "Developers": "Developers",
        "years": "years",
        "experience": "experience",
        "developmentIn": "developmentIn",
        "documentation": "documentation",
        "projectsProven": "projectsProven",
        "ability": "ability",
        "skills": "skills",
        "communication": "communication",
        "skillsStrategic": "skillsStrategic",
        "thinking": "thinking",
        "problem-solving": "problem-solving",
        "decision-making": "decision-making",
        "capabilitiesStrong": "capabilitiesStrong",
        "desire": "desire",
        "company": "company",
        "deliver": "deliver",
        "resultsWho": "resultsWho",
        "Software": "Software",
        "Innovative": "Innovative",
        "Solutions": "Solutions",
        "minimum": "minimum",
        "field": "field",
        "Candidates": "Candidates",
        "Service": "Service",
        "Products": "Products",
        "build": "build",
        "enhancements": "enhancements",
        "extensions": "extensions",
        "Details": "Details",
        "Time": "Time",
        "Part": "Part",
        "Remote": "Remote",
        "office": "office",
        "Atlanta": "Atlanta",
        "Tech": "Tech",
        "ScheduleRequirements": "ScheduleRequirements",
        "CSSHTMLJavaScriptReact": "CSSHTMLJavaScriptReact",
        "JSA": "JSA",
        "familiarity": "familiarity",
        "design": "design",
        "problem": "problem",
        "skillsExperience": "skillsExperience",
        "work": "work",
        "plus": "plus",
        "MUST": "MUST",
        "BE": "BE",
        "AUTHORIZED": "AUTHORIZED",
        "TO": "TO",
        "WORK": "WORK",
        "IN": "IN",
        "THE": "THE",
        "U.": "U.",
        "S.": "S.",
        "WE": "WE",
        "DO": "DO",
        "NOT": "NOT",
        "SPONSOR": "SPONSOR",
        "https": "https",
        "//boatrentalmanagement": "//boatrentalmanagement",
        "com/3423": "com/3423",
        "Piedmont": "Piedmont",
        "Rd": "Rd",
        "NE": "NE",
        "Suite": "Suite",
        "GA": "GA",
        "DetailsSalary": "DetailsSalary",
        "Per": "Per",
        "YearJob": "YearJob",
        "Typefulltime": "Typefulltime",
        "Day": "Day"
      },
      "PRT": {
        "to": "to",
        "To": "To"
      },
      "NUM": {
        "597": "597",
        "70000": "70000",
        "125000": "125000",
        "30305Job": "30305Job"
      }
    }
  },
  "222624569": {
    "Company": "Wood",
    "Job Title": "Application Developer",
    "Job Details": "DescriptionWood is a global leader in engineering and consultancy across energy and the built environment, helping to unlock solutions to some of the world’s most critical challenges|||| We provide consulting, projects and operations solutions in more than 60 countries, employing around 45,000 people|||| www||||woodplc||||comWe offer competitive salaries along with a complete benefits package including: medical, vision, & dental coverage, 401K Matching, Educational Reimbursement, and a variety of Training and Development Programs to help you develop the skills you need to succeed in your chosen career path||||Role Overview Wood Environment & Infrastructure Solutions is seeking an Application Developer with knowledge of different computer languages and operating systems for application development to meet client requirements|||| Key Responsibilities:Efficiently manage data to produce reports and meet client schedulesApply knowledge to develop code and provide support on specific portions of larger assignmentsSolve problems using standard methods; determine methods to apply to assigned tasksWork closely with computer analyst and engineers in using languages such as ||||NET, Xamarin, C#, JavaScript and SQL to develop the necessary specifications based on project scopesResponsibilities will vary between assigned projects based on the needs of the project, requiring the production of web and mobile applicationsMay create, maintain and implement source code that comprises applications or programsWill test, debug, and improve established applications already in useWork Environment:Mainly office environment; may require visiting other Wood offices if the position requiresOvertime and overnight stays on as needed basisSome travel by be required on as needed basis Skills / QualificationsEducation, Experience and Skills Required:Bachelor’s degree in a relevant computer science major, 3-5 years professional experience or equivalent combination of education and experienceUnderstanding and ability to apply the fundamental concepts, practices and procedures of your field of specializationDemonstrated experience developing solutions in ||||NET, Xamarin, C#, JavaScript and SQLMust pass drug test, background check and must have a satisfactory driving record in accordance with the Company's driving (MVR) policyIf you believe you have the necessary knowledge, experience and enthusiasm to succeed in this position, then we would like to hear from you||||We are an equal opportunity employer that recognizes the value of a diverse workforce|||| All qualified individuals will receive consideration for employment without regard to race, color, age, religion, gender, national origin, sexual orientation, gender identity, disability and/or protected veteran status in accordance with governing laws||||By submitting your resume, you consent to Wood plc sharing this information within its divisions in order to identify other employment opportunities for which you may be suitable||||Job DetailsJob Typefulltime, employeePosted 5 days ago||||",
    "KeyWords": {
      "NOUN": {
        "leader": "leader",
        "engineering": "engineering",
        "consultancy": "consultancy",
        "energy": "energy",
        "environment": "environment",
        "solutions": "solutions",
        "world": "world",
        "challenges": "challenges",
        "projects": "projects",
        "operations": "operations",
        "countries": "countries",
        "people": "people",
        "www": "www",
        "woodplc": "woodplc",
        "comWe": "comWe",
        "salaries": "salaries",
        "benefits": "benefits",
        "package": "package",
        "vision": "vision",
        "coverage": "coverage",
        "Matching": "Matching",
        "Educational": "Educational",
        "Reimbursement": "Reimbursement",
        "variety": "variety",
        "Training": "Training",
        "Development": "Development",
        "Programs": "Programs",
        "skills": "skills",
        "chosen": "chosen",
        "path": "path",
        "Role": "Role",
        "Overview": "Overview",
        "Wood": "Wood",
        "Environment": "Environment",
        "Infrastructure": "Infrastructure",
        "Solutions": "Solutions",
        "Application": "Application",
        "Developer": "Developer",
        "knowledge": "knowledge",
        "computer": "computer",
        "languages": "languages",
        "systems": "systems",
        "application": "application",
        "development": "development",
        "client": "client",
        "requirements": "requirements",
        "Responsibilities": "Responsibilities",
        "data": "data",
        "reports": "reports",
        "code": "code",
        "support": "support",
        "portions": "portions",
        "assignmentsSolve": "assignmentsSolve",
        "problems": "problems",
        "methods": "methods",
        "tasksWork": "tasksWork",
        "analyst": "analyst",
        "engineers": "engineers",
        "NET": "NET",
        "Xamarin": "Xamarin",
        "JavaScript": "JavaScript",
        "SQL": "SQL",
        "specifications": "specifications",
        "project": "project",
        "scopesResponsibilities": "scopesResponsibilities",
        "needs": "needs",
        "production": "production",
        "web": "web",
        "applicationsMay": "applicationsMay",
        "create": "create",
        "maintain": "maintain",
        "source": "source",
        "applications": "applications",
        "test": "test",
        "debug": "debug",
        "office": "office",
        "offices": "offices",
        "position": "position",
        "requiresOvertime": "requiresOvertime",
        "stays": "stays",
        "basisSome": "basisSome",
        "travel": "travel",
        "basis": "basis",
        "Skills": "Skills",
        "QualificationsEducation": "QualificationsEducation",
        "Experience": "Experience",
        "Required": "Required",
        "Bachelor": "Bachelor",
        "degree": "degree",
        "science": "science",
        "years": "years",
        "experience": "experience",
        "combination": "combination",
        "education": "education",
        "experienceUnderstanding": "experienceUnderstanding",
        "ability": "ability",
        "concepts": "concepts",
        "practices": "practices",
        "procedures": "procedures",
        "field": "field",
        "SQLMust": "SQLMust",
        "drug": "drug",
        "background": "background",
        "check": "check",
        "driving": "driving",
        "record": "record",
        "accordance": "accordance",
        "Company": "Company",
        "MVR": "MVR",
        "enthusiasm": "enthusiasm",
        "opportunity": "opportunity",
        "employer": "employer",
        "value": "value",
        "workforce": "workforce",
        "individuals": "individuals",
        "consideration": "consideration",
        "employment": "employment",
        "regard": "regard",
        "race": "race",
        "color": "color",
        "age": "age",
        "religion": "religion",
        "gender": "gender",
        "origin": "origin",
        "orientation": "orientation",
        "identity": "identity",
        "disability": "disability",
        "veteran": "veteran",
        "status": "status",
        "laws": "laws",
        "resume": "resume",
        "plc": "plc",
        "information": "information",
        "divisions": "divisions",
        "order": "order",
        "opportunities": "opportunities",
        "Job": "Job",
        "DetailsJob": "DetailsJob",
        "Typefulltime": "Typefulltime",
        "days": "days"
      },
      "VERB": {
        "built": "built",
        "helping": "helping",
        "unlock": "unlock",
        "provide": "provide",
        "consulting": "consulting",
        "employing": "employing",
        "offer": "offer",
        "including": "including",
        "help": "help",
        "develop": "develop",
        "need": "need",
        "succeed": "succeed",
        "career": "career",
        "is": "is",
        "seeking": "seeking",
        "operating": "operating",
        "meet": "meet",
        "manage": "manage",
        "produce": "produce",
        "knowledge": "knowledge",
        "using": "using",
        "determine": "determine",
        "apply": "apply",
        "assigned": "assigned",
        "based": "based",
        "will": "will",
        "vary": "vary",
        "requiring": "requiring",
        "comprises": "comprises",
        "programsWill": "programsWill",
        "improve": "improve",
        "established": "established",
        "may": "may",
        "require": "require",
        "visiting": "visiting",
        "be": "be",
        "required": "required",
        "needed": "needed",
        "developing": "developing",
        "pass": "pass",
        "must": "must",
        "have": "have",
        "policyIf": "policyIf",
        "believe": "believe",
        "would": "would",
        "like": "like",
        "hear": "hear",
        "are": "are",
        "recognizes": "recognizes",
        "receive": "receive",
        "protected": "protected",
        "governing": "governing",
        "submitting": "submitting",
        "consent": "consent",
        "sharing": "sharing",
        "identify": "identify",
        "employeePosted": "employeePosted"
      },
      "ADJ": {
        "most": "most",
        "critical": "critical",
        "more": "more",
        "competitive": "competitive",
        "complete": "complete",
        "medical": "medical",
        "dental": "dental",
        "different": "different",
        "Key": "Key",
        "specific": "specific",
        "larger": "larger",
        "standard": "standard",
        "such": "such",
        "necessary": "necessary",
        "mobile": "mobile",
        "implement": "implement",
        "useWork": "useWork",
        "other": "other",
        "overnight": "overnight",
        "needed": "needed",
        "relevant": "relevant",
        "major": "major",
        "3-5": "3-5",
        "professional": "professional",
        "equivalent": "equivalent",
        "fundamental": "fundamental",
        "specializationDemonstrated": "specializationDemonstrated",
        "satisfactory": "satisfactory",
        "equal": "equal",
        "diverse": "diverse",
        "qualified": "qualified",
        "national": "national",
        "sexual": "sexual",
        "suitable": "suitable"
      },
      "PRT": {
        "to": "to",
        "'s": "'s"
      },
      "NUM": {
        "45,000": "45,000",
        "401K": "401K"
      }
    }
  },
  "222747924": {
    "Company": "Liberty Jobs",
    "Job Title": "Software Engineer Angular or React",
    "Job Details": "",
    "KeyWords": {}
  },
  "222796131": {
    "Company": "EDGE Services, Inc",
    "Job Title": "Mainframe Developers (Remote)",
    "Job Details": "DescriptionMajor responsibilities: Identifies, analyzes, designs, and maintains cost-effective information technology solutions that align with business initiatives and corporate strategiesAnalyzes, defines, and documents requirements for data, workflow, logical processes, hardware, and operating systems environment, interfaces with other systems, internal and external controls, and outputDocuments, diagrams, organizes, information for inclusion in database; developing input/output record layouts, or program viewsDesigns, develops, implements, and maintains systems with support from other ISD areas, team members, and managementIdentifies and resolves conflicts between proposed solutions and existing systems to ensure compatibility Qualifications: In-depth knowledge and experience of financial industry applications and systems||||Ten (10) years of experience with COBOL, JCL, command-level IBM® Customer Information Control System (CICS©), batch processing and usage of the TSO/ISPF interface||||Ten (10) years of experience with IBM® DB2© Utilities - SQL Processing Using File Input (SPUFI©), Query Management Facility (QMF©) and Z/OS Mainframe Utilities - IEBGENER, IEFBR14, SYNCSORT||||Solid experience/knowledge of the Systems Development Life-cycle (SDLC)||||Solid experience/knowledge of software development best practices in accordance with the ITIL® or CMMI® capability models||||Strong analytical, planning and technical problem solving skills||||Advanced experience/knowledge in IBM© Mainframe systems, workflow and procedural analysis||||Job DetailsJob Typefulltime, contractPostedToday||||",
    "KeyWords": {
      "ADJ": {
        "cost-effective": "cost-effective",
        "corporate": "corporate",
        "logical": "logical",
        "other": "other",
        "internal": "internal",
        "external": "external",
        "In-depth": "In-depth",
        "financial": "financial",
        "command-level": "command-level",
        "Solid": "Solid",
        "best": "best",
        "Strong": "Strong",
        "analytical": "analytical",
        "technical": "technical",
        "workflow": "workflow",
        "procedural": "procedural"
      },
      "NOUN": {
        "Identifies": "Identifies",
        "designs": "designs",
        "information": "information",
        "technology": "technology",
        "solutions": "solutions",
        "business": "business",
        "initiatives": "initiatives",
        "strategiesAnalyzes": "strategiesAnalyzes",
        "defines": "defines",
        "documents": "documents",
        "requirements": "requirements",
        "data": "data",
        "workflow": "workflow",
        "processes": "processes",
        "hardware": "hardware",
        "systems": "systems",
        "environment": "environment",
        "interfaces": "interfaces",
        "controls": "controls",
        "outputDocuments": "outputDocuments",
        "diagrams": "diagrams",
        "inclusion": "inclusion",
        "database": "database",
        "input/output": "input/output",
        "record": "record",
        "program": "program",
        "viewsDesigns": "viewsDesigns",
        "develops": "develops",
        "implements": "implements",
        "support": "support",
        "ISD": "ISD",
        "areas": "areas",
        "team": "team",
        "members": "members",
        "managementIdentifies": "managementIdentifies",
        "conflicts": "conflicts",
        "compatibility": "compatibility",
        "Qualifications": "Qualifications",
        "knowledge": "knowledge",
        "experience": "experience",
        "industry": "industry",
        "applications": "applications",
        "Ten": "Ten",
        "years": "years",
        "COBOL": "COBOL",
        "JCL": "JCL",
        "IBM®": "IBM®",
        "Customer": "Customer",
        "Information": "Information",
        "Control": "Control",
        "System": "System",
        "CICS©": "CICS©",
        "batch": "batch",
        "processing": "processing",
        "usage": "usage",
        "TSO/ISPF": "TSO/ISPF",
        "interface": "interface",
        "DB2©": "DB2©",
        "Utilities": "Utilities",
        "SQL": "SQL",
        "Using": "Using",
        "File": "File",
        "Input": "Input",
        "SPUFI©": "SPUFI©",
        "Query": "Query",
        "Management": "Management",
        "Facility": "Facility",
        "QMF©": "QMF©",
        "Z/OS": "Z/OS",
        "Mainframe": "Mainframe",
        "IEBGENER": "IEBGENER",
        "IEFBR14": "IEFBR14",
        "SYNCSORT": "SYNCSORT",
        "Solid": "Solid",
        "experience/knowledge": "experience/knowledge",
        "Systems": "Systems",
        "Development": "Development",
        "Life-cycle": "Life-cycle",
        "SDLC": "SDLC",
        "software": "software",
        "development": "development",
        "practices": "practices",
        "accordance": "accordance",
        "ITIL®": "ITIL®",
        "CMMI®": "CMMI®",
        "capability": "capability",
        "models": "models",
        "planning": "planning",
        "problem": "problem",
        "skills": "skills",
        "Advanced": "Advanced",
        "IBM©": "IBM©",
        "analysis": "analysis",
        "Job": "Job",
        "DetailsJob": "DetailsJob",
        "Typefulltime": "Typefulltime",
        "contractPostedToday": "contractPostedToday"
      },
      "VERB": {
        "maintains": "maintains",
        "align": "align",
        "operating": "operating",
        "organizes": "organizes",
        "developing": "developing",
        "layouts": "layouts",
        "resolves": "resolves",
        "proposed": "proposed",
        "existing": "existing",
        "ensure": "ensure",
        "Processing": "Processing",
        "solving": "solving"
      },
      "PRT": {},
      "NUM": {
        "10": "10"
      }
    }
  },
  "222855029": {
    "Company": "ECA Staffing Solutions, Inc.",
    "Job Title": "SDET Lead Engineer",
    "Job Details": "DescriptionThis is a Contract-to-Hire remote opportunity||||  You will need to be in the Eastern time zone as the hours are 7:00am-4:00pm, EST||||  Must be able to work independently for any employer in the US without sponsorship!For immediate consideration, please send your updated Word resume to:  elizabeth@ecastaffingsolutions||||comPosition Summary: Seeking a well-rounded Lead Software Development Engineer in Test with a passion for utilizing their programming skills in all phases of Testing||||  The chosen resource should come in as a Selenium Java UI Test Automation expert capable of immediately contributing hands-on across multiple projects with a goal of 100% unattended script execution and reporting||||  In addition to contributing to UI Automation efforts in all facets, this resource will help drive and implement tests at the Unit, Component, Integration, Service, and API layers||||  This role interacts extensively with both offshore and onshore resources||||Duties:Hands-On participation in All Test Automation TasksKeyword/Action Driven UI Test AutomationScript Failure Analysis and Script HardeningCollaborate with Project and Development teams to improve Testability and CI/CD practices||||  Recommend/Advocate/Coordinate Test Automation Solutions|||| Design and implement new and enhance existing test approaches that appropriately scope tests at the Unit, Component, Integration, Service, API, or UI layer||||Participate hands-on in Test development, execution, reporting, and maintenance across functional, performance, and security testing efforts on various projects||||Requirements:Expert/Lead Level Selenium (Java) Test Automation Experience – 5+ YearsExperience solving Custom ControlsFluency to Code in Java – 5+ YearsCustom APIsFluency to Code in C# ||||NET – 5+ yearsWeb and WCF ServicesCustom APIsExperience with Unit / Integration Testing – understanding of mocks/stubs/||||||||||||Above Average Level Knowledge of Windows (Troubleshooting Skills)Excellent Communication Skills and Attention to DetailAdditional Skills:Microsoft ||||NET UI Automation LibrariesMS PowerShell – Desired State Configuration a PlusMS Azure DevOps Experience (Agile Template preferred)Cloud Experience (Azure preferred)Web Development ( JavaScript / CSS / …)Good understanding of Secure Development practicesGood understanding/experience with code and release management tools and  CI/CDTest Driven Development a plusEntity Framework a plusDevelopment of custom test harnesses a plusAgile Software Testing Experience (Test Plan/Case/Script Design and Execution)Good understanding of Microservices and Containers (Docker, Kubernetes, ||||||||||||)Job DetailsJob Typefulltime, employeePosted 4 days ago||||",
    "KeyWords": {
      "NOUN": {
        "remote": "remote",
        "opportunity": "opportunity",
        "time": "time",
        "zone": "zone",
        "hours": "hours",
        "EST": "EST",
        "Must": "Must",
        "employer": "employer",
        "US": "US",
        "sponsorship": "sponsorship",
        "consideration": "consideration",
        "Word": "Word",
        "resume": "resume",
        "ecastaffingsolutions": "ecastaffingsolutions",
        "comPosition": "comPosition",
        "Summary": "Summary",
        "Lead": "Lead",
        "Software": "Software",
        "Development": "Development",
        "Engineer": "Engineer",
        "Test": "Test",
        "passion": "passion",
        "programming": "programming",
        "skills": "skills",
        "phases": "phases",
        "resource": "resource",
        "Selenium": "Selenium",
        "Java": "Java",
        "UI": "UI",
        "Automation": "Automation",
        "expert": "expert",
        "projects": "projects",
        "goal": "goal",
        "script": "script",
        "execution": "execution",
        "reporting": "reporting",
        "addition": "addition",
        "efforts": "efforts",
        "facets": "facets",
        "tests": "tests",
        "Unit": "Unit",
        "Component": "Component",
        "Integration": "Integration",
        "Service": "Service",
        "API": "API",
        "layers": "layers",
        "role": "role",
        "resources": "resources",
        "Duties": "Duties",
        "participation": "participation",
        "TasksKeyword/Action": "TasksKeyword/Action",
        "Driven": "Driven",
        "AutomationScript": "AutomationScript",
        "Failure": "Failure",
        "Analysis": "Analysis",
        "Script": "Script",
        "HardeningCollaborate": "HardeningCollaborate",
        "Project": "Project",
        "teams": "teams",
        "Testability": "Testability",
        "CI/CD": "CI/CD",
        "practices": "practices",
        "Recommend/Advocate/Coordinate": "Recommend/Advocate/Coordinate",
        "Solutions": "Solutions",
        "Design": "Design",
        "test": "test",
        "approaches": "approaches",
        "layer": "layer",
        "development": "development",
        "maintenance": "maintenance",
        "performance": "performance",
        "security": "security",
        "Requirements": "Requirements",
        "Expert/Lead": "Expert/Lead",
        "Level": "Level",
        "Experience": "Experience",
        "YearsExperience": "YearsExperience",
        "Custom": "Custom",
        "ControlsFluency": "ControlsFluency",
        "Code": "Code",
        "YearsCustom": "YearsCustom",
        "APIsFluency": "APIsFluency",
        "NET": "NET",
        "yearsWeb": "yearsWeb",
        "WCF": "WCF",
        "ServicesCustom": "ServicesCustom",
        "APIsExperience": "APIsExperience",
        "Testing": "Testing",
        "understanding": "understanding",
        "mocks/stubs/": "mocks/stubs/",
        "Average": "Average",
        "Knowledge": "Knowledge",
        "Windows": "Windows",
        "Troubleshooting": "Troubleshooting",
        "Skills": "Skills",
        "Excellent": "Excellent",
        "Communication": "Communication",
        "Attention": "Attention",
        "DetailAdditional": "DetailAdditional",
        "Microsoft": "Microsoft",
        "LibrariesMS": "LibrariesMS",
        "PowerShell": "PowerShell",
        "Desired": "Desired",
        "State": "State",
        "Configuration": "Configuration",
        "PlusMS": "PlusMS",
        "Azure": "Azure",
        "DevOps": "DevOps",
        "Agile": "Agile",
        "Template": "Template",
        "Cloud": "Cloud",
        "Web": "Web",
        "JavaScript": "JavaScript",
        "CSS": "CSS",
        "Good": "Good",
        "Secure": "Secure",
        "understanding/experience": "understanding/experience",
        "code": "code",
        "release": "release",
        "management": "management",
        "tools": "tools",
        "CI/CDTest": "CI/CDTest",
        "plusEntity": "plusEntity",
        "Framework": "Framework",
        "plusDevelopment": "plusDevelopment",
        "plusAgile": "plusAgile",
        "Plan/Case/Script": "Plan/Case/Script",
        "Execution": "Execution",
        "Microservices": "Microservices",
        "Containers": "Containers",
        "Docker": "Docker",
        "Kubernetes": "Kubernetes",
        "Job": "Job",
        "DetailsJob": "DetailsJob",
        "Typefulltime": "Typefulltime",
        "days": "days"
      },
      "VERB": {
        "will": "will",
        "need": "need",
        "be": "be",
        "are": "are",
        "work": "work",
        "please": "please",
        "send": "send",
        "elizabeth": "elizabeth",
        "Seeking": "Seeking",
        "utilizing": "utilizing",
        "Testing": "Testing",
        "should": "should",
        "come": "come",
        "contributing": "contributing",
        "help": "help",
        "drive": "drive",
        "implement": "implement",
        "interacts": "interacts",
        "improve": "improve",
        "existing": "existing",
        "scope": "scope",
        "Participate": "Participate",
        "testing": "testing",
        "solving": "solving",
        "preferred": "preferred",
        "practicesGood": "practicesGood",
        "harnesses": "harnesses",
        "employeePosted": "employeePosted"
      },
      "ADJ": {
        "Eastern": "Eastern",
        "7:00am-4:00pm": "7:00am-4:00pm",
        "able": "able",
        "immediate": "immediate",
        "updated": "updated",
        "well-rounded": "well-rounded",
        "chosen": "chosen",
        "capable": "capable",
        "hands-on": "hands-on",
        "multiple": "multiple",
        "unattended": "unattended",
        "offshore": "offshore",
        "onshore": "onshore",
        "Hands-On": "Hands-On",
        "implement": "implement",
        "new": "new",
        "enhance": "enhance",
        "functional": "functional",
        "various": "various",
        "custom": "custom"
      },
      "PRT": {
        "to": "to"
      },
      "NUM": {
        "5+": "5+"
      }
    }
  },
  "222856630": {
    "Company": "Hays",
    "Job Title": "Senior .NET Developer (Microservices)",
    "Job Details": "DescriptionSenior ||||NET Developer (Microservices) - Perm - Kennesaw, GA - $110,000-$125,000 The end client is unable to sponsor or transfer visas for this position; all parties authorized to work in the US without sponsorship are encouraged to apply||||Seeking a |||| Senior ||||NET Developer (Microservices) in Kennesaw, GA|||| Role DescriptionThe Senior Software Engineer is responsible for the design, development, testing, and operations of applications critical to the business|||| The potential candidate has demonstrable, specific and personal experience of secure engineering practices and will be a part of an DevOps development team, building and working on enterprise grade software systems on top of the Microsoft ||||NET development stack|||| The Senior Software Engineer will provide technical guidance to teammates through coaching and mentorship||||Skills & Requirements* College or University degree in Computer Science or a related discipline||||* 5+ years' experience as a Software Engineer||||* Proficient with Microsoft ||||NET Core 3||||5+ development using C#||||* Extensive experience designing and developing enterprise grade software||||* Comprehensive understanding of object-oriented, service-oriented, and micro-services development techniques and theories||||* Experience with source control management systems and continuous integration/deployment (CI/CD) environments||||* Experience with automated testing; working on an agile team; multi-threading and concurrency; debugging, performance profiling and optimization||||Why Hays?You will be working with a professional recruiter who has intimate knowledge of the Information Technology industry and market trends |||| Your Hays recruiter will lead you through a thorough screening process in order to understand your skills, experience, needs, and drivers|||| You will also get support on resume writing, interview tips, and career planning, so when there's a position you really want, you're fully prepared to get it|||| Nervous about an upcoming interview? Unsure how to write a new resume?Visit the Hays Career Advice section to learn top tips to help you stand out from the crowd when job hunting|||| Hays is an Equal Opportunity Employer||||Drug testing may be required; please contact a recruiter for more information||||Job DetailsSalary$110000 - $125000 Per YearJob Typefulltime, employeePosted 26 days ago||||",
    "KeyWords": {
      "NOUN": {
        "NET": "NET",
        "Developer": "Developer",
        "Microservices": "Microservices",
        "Kennesaw": "Kennesaw",
        "GA": "GA",
        "end": "end",
        "client": "client",
        "visas": "visas",
        "position": "position",
        "parties": "parties",
        "US": "US",
        "sponsorship": "sponsorship",
        "Senior": "Senior",
        "GA.": "GA.",
        "Role": "Role",
        "DescriptionThe": "DescriptionThe",
        "Software": "Software",
        "Engineer": "Engineer",
        "design": "design",
        "development": "development",
        "operations": "operations",
        "applications": "applications",
        "business": "business",
        "candidate": "candidate",
        "experience": "experience",
        "secure": "secure",
        "engineering": "engineering",
        "practices": "practices",
        "part": "part",
        "DevOps": "DevOps",
        "team": "team",
        "building": "building",
        "enterprise": "enterprise",
        "grade": "grade",
        "software": "software",
        "systems": "systems",
        "top": "top",
        "Microsoft": "Microsoft",
        "stack": "stack",
        "guidance": "guidance",
        "teammates": "teammates",
        "coaching": "coaching",
        "mentorship": "mentorship",
        "Skills": "Skills",
        "Requirements": "Requirements",
        "College": "College",
        "University": "University",
        "Computer": "Computer",
        "Science": "Science",
        "discipline": "discipline",
        "years": "years",
        "designing": "designing",
        "understanding": "understanding",
        "micro-services": "micro-services",
        "techniques": "techniques",
        "theories": "theories",
        "Experience": "Experience",
        "source": "source",
        "control": "control",
        "management": "management",
        "integration/deployment": "integration/deployment",
        "CI/CD": "CI/CD",
        "environments": "environments",
        "concurrency": "concurrency",
        "debugging": "debugging",
        "performance": "performance",
        "profiling": "profiling",
        "optimization": "optimization",
        "Hays": "Hays",
        "recruiter": "recruiter",
        "intimate": "intimate",
        "knowledge": "knowledge",
        "Information": "Information",
        "Technology": "Technology",
        "industry": "industry",
        "market": "market",
        "trends": "trends",
        "screening": "screening",
        "process": "process",
        "order": "order",
        "skills": "skills",
        "needs": "needs",
        "drivers": "drivers",
        "support": "support",
        "resume": "resume",
        "interview": "interview",
        "tips": "tips",
        "career": "career",
        "planning": "planning",
        "Unsure": "Unsure",
        "Career": "Career",
        "Advice": "Advice",
        "section": "section",
        "crowd": "crowd",
        "job": "job",
        "Opportunity": "Opportunity",
        "Employer": "Employer",
        "Drug": "Drug",
        "testing": "testing",
        "information": "information",
        "Job": "Job",
        "DetailsSalary": "DetailsSalary",
        "Per": "Per",
        "YearJob": "YearJob",
        "Typefulltime": "Typefulltime",
        "days": "days"
      },
      "X": {},
      "ADJ": {
        "unable": "unable",
        "responsible": "responsible",
        "critical": "critical",
        "potential": "potential",
        "demonstrable": "demonstrable",
        "specific": "specific",
        "personal": "personal",
        "technical": "technical",
        "related": "related",
        "Proficient": "Proficient",
        "Extensive": "Extensive",
        "Comprehensive": "Comprehensive",
        "object-oriented": "object-oriented",
        "service-oriented": "service-oriented",
        "continuous": "continuous",
        "automated": "automated",
        "agile": "agile",
        "multi-threading": "multi-threading",
        "professional": "professional",
        "thorough": "thorough",
        "Nervous": "Nervous",
        "upcoming": "upcoming",
        "new": "new",
        "top": "top",
        "Equal": "Equal",
        "more": "more"
      },
      "NUM": {
        "26": "26",
        "110000": "110000",
        "125000": "125000",
        "5+": "5+"
      },
      "VERB": {
        "sponsor": "sponsor",
        "transfer": "transfer",
        "authorized": "authorized",
        "work": "work",
        "are": "are",
        "encouraged": "encouraged",
        "apply": "apply",
        "Seeking": "Seeking",
        "is": "is",
        "testing": "testing",
        "has": "has",
        "will": "will",
        "be": "be",
        "working": "working",
        "provide": "provide",
        "degree": "degree",
        "Core": "Core",
        "using": "using",
        "developing": "developing",
        "lead": "lead",
        "understand": "understand",
        "get": "get",
        "writing": "writing",
        "'s": "'s",
        "want": "want",
        "'re": "'re",
        "prepared": "prepared",
        "write": "write",
        "Visit": "Visit",
        "learn": "learn",
        "help": "help",
        "stand": "stand",
        "hunting": "hunting",
        "may": "may",
        "required": "required",
        "please": "please",
        "contact": "contact",
        "employeePosted": "employeePosted"
      },
      "PRT": {
        "to": "to",
        "out": "out"
      }
    }
  },
  "222902740": {
    "Company": "AMS Staffing, Inc.",
    "Job Title": "Senior Application Security Engineer (AWS) - 100% Remote",
    "Job Details": "DescriptionPlease send a resume in Word format if you are interested in this Senior Application Security Engineer opening near Itasca, IL 60143|||| Salary for this role is $140K - $170K (some flex) + 15% Bonus & EXCELLENT BENEFITS (open vacation policy, paid maternity/paternity, 401K, etc)!!!!!!!Looking for strong AWS Cloud and Application Security experience|||| 30-40% of the job will be spent on application security/counter activities, 30% on Cloud (AWS) and 20-30% on security program operations|||| Offensive security certifications and AWS certifications are nice to have, but not required||||If you are not interested, please forward to your network||||  AMS Staffing offers referral fees should they be hired|||| Job Title: AWS Cloud and Application SecurityLocation: Itasca, IL 60143Salary: $140K - $170K (some flex) + 15% Bonus & EXCELLENT BENEFITSTerm: Permanent / Full-Time RoleApply (here):https://loxo||||co/job/500250?t=1608342562268Please reply with an updated resume in Microsoft Word formatJOB DESCRIPTIONSenior Application Security Engineer plays a critical role in completing our mission every day by ensuring that client maintain and deploy new software/systems in a secure manner to reduce information security risks|||| The Sr Security Engineer take charge of the selection and deployment of world-class cyber security technologies with focus on Secure SDLC & Cloud Security|||| Acts as the evangelist for cyber security throughout Information Technology, consulting with the application development and infrastructure team on secure systems and applications design||||Key ResponsibilitiesSecure Development: Build strong relationships and be deeply embedded within product management and software engineering team|||| The Senior Security Engineer will drive the design and adoption of secure software development lifecycle practices across the areas of secure architecture and design, secure coding, security testing, and secure software release management||||Cloud Security: Build a secure cloud environment and help drive the adoption of secure deployment practices in Amazon Web Services Cloud||||Penetration Testing: Strong knowledge of network and web application exploitation, ethical hacking, penetration testing, computer forensics and tool development|||| Configures, schedules, manages and reviews internal and external network and application vulnerability scans and penetration tests|||| Monitors and reviews industry related vulnerabilities reviewing findings with appropriate teams, creating remediation plans and tracks and reports on progressInfrastructure Security: Works closely with the Infrastructure and Application Development teams to ensure proper configurations are implemented and tested on WAF, FW, IDS/IPS and platformIncident & Cyber Threat Management: Works with the appropriate teams to ensure all appropriate data is aggregated into the logging and monitoring tool and that the appropriate reports are produced and reviewed||||Competencies for Success: Cultivates Innovation, Competencies for Success, Cultivates Innovation, Decision Quality, Communicates Effectively, Manages ComplexityMeasures of Success: Delivery on information security roadmap and projects, Number of vulnerabilities and issues, Secure SDLCEducation and Experience:Bachelor's in Computer Science or Information Security, 5 to 10 years of experience working in technology and development with a specialty in security in a complex environment, focusing on protection of intellectual property and sensitive data||||Experience with static, dynamic and interactive application security testing platforms|||| (SAST/DAST/IAST)Experience with web application security best practices (e||||g|||| OWASP, CWE/SANS)Cloud Security experience (AWS, O365)Strong knowledge of network and web application exploitation, ethical hacking, penetration testing, computer forensics and tool developmentStrong knowledge of vulnerability assessment, scanning (Rapid7, Qualys, Tenable)Experience creating and maintaining security policies and standardsWorking knowledge of security best practices and standards such as ISO27001, ISO27002, PCI-DSS, NISTAbility to effectively manage multiple concurrent priorities and meet deadlines within a dynamic, fast-paced and challenging environmentStrong interpersonal and communication skillsDemonstrate the ability to clearly articulate complex technical scenarios to a non-technical audienceJob DetailsSalary$150000 - $170000 Per YearJob Typefulltime, employeePosted 25 days ago||||",
    "KeyWords": {
      "NOUN": {
        "resume": "resume",
        "Word": "Word",
        "format": "format",
        "Application": "Application",
        "Security": "Security",
        "Engineer": "Engineer",
        "opening": "opening",
        "Itasca": "Itasca",
        "IL": "IL",
        "Salary": "Salary",
        "role": "role",
        "flex": "flex",
        "Bonus": "Bonus",
        "EXCELLENT": "EXCELLENT",
        "BENEFITS": "BENEFITS",
        "vacation": "vacation",
        "policy": "policy",
        "maternity/paternity": "maternity/paternity",
        "AWS": "AWS",
        "Cloud": "Cloud",
        "experience": "experience",
        "job": "job",
        "application": "application",
        "security/counter": "security/counter",
        "activities": "activities",
        "security": "security",
        "program": "program",
        "operations": "operations",
        "certifications": "certifications",
        "network": "network",
        "AMS": "AMS",
        "offers": "offers",
        "fees": "fees",
        "Job": "Job",
        "Title": "Title",
        "SecurityLocation": "SecurityLocation",
        "BENEFITSTerm": "BENEFITSTerm",
        "RoleApply": "RoleApply",
        "https": "https",
        "//loxo": "//loxo",
        "co/job/500250": "co/job/500250",
        "t=1608342562268Please": "t=1608342562268Please",
        "reply": "reply",
        "Microsoft": "Microsoft",
        "formatJOB": "formatJOB",
        "DESCRIPTIONSenior": "DESCRIPTIONSenior",
        "mission": "mission",
        "day": "day",
        "client": "client",
        "maintain": "maintain",
        "software/systems": "software/systems",
        "secure": "secure",
        "manner": "manner",
        "information": "information",
        "risks": "risks",
        "Sr": "Sr",
        "charge": "charge",
        "selection": "selection",
        "deployment": "deployment",
        "technologies": "technologies",
        "focus": "focus",
        "Secure": "Secure",
        "SDLC": "SDLC",
        "evangelist": "evangelist",
        "cyber": "cyber",
        "Information": "Information",
        "Technology": "Technology",
        "development": "development",
        "infrastructure": "infrastructure",
        "team": "team",
        "systems": "systems",
        "applications": "applications",
        "design": "design",
        "ResponsibilitiesSecure": "ResponsibilitiesSecure",
        "Development": "Development",
        "Build": "Build",
        "relationships": "relationships",
        "product": "product",
        "management": "management",
        "software": "software",
        "engineering": "engineering",
        "Senior": "Senior",
        "adoption": "adoption",
        "lifecycle": "lifecycle",
        "practices": "practices",
        "areas": "areas",
        "architecture": "architecture",
        "coding": "coding",
        "testing": "testing",
        "release": "release",
        "cloud": "cloud",
        "environment": "environment",
        "Amazon": "Amazon",
        "Web": "Web",
        "Services": "Services",
        "Penetration": "Penetration",
        "knowledge": "knowledge",
        "web": "web",
        "exploitation": "exploitation",
        "hacking": "hacking",
        "penetration": "penetration",
        "computer": "computer",
        "forensics": "forensics",
        "tool": "tool",
        "Configures": "Configures",
        "schedules": "schedules",
        "manages": "manages",
        "vulnerability": "vulnerability",
        "scans": "scans",
        "tests": "tests",
        "Monitors": "Monitors",
        "reviews": "reviews",
        "industry": "industry",
        "vulnerabilities": "vulnerabilities",
        "findings": "findings",
        "teams": "teams",
        "remediation": "remediation",
        "plans": "plans",
        "tracks": "tracks",
        "reports": "reports",
        "Infrastructure": "Infrastructure",
        "configurations": "configurations",
        "WAF": "WAF",
        "FW": "FW",
        "IDS/IPS": "IDS/IPS",
        "platformIncident": "platformIncident",
        "Cyber": "Cyber",
        "Threat": "Threat",
        "Management": "Management",
        "data": "data",
        "logging": "logging",
        "monitoring": "monitoring",
        "Competencies": "Competencies",
        "Success": "Success",
        "Innovation": "Innovation",
        "Cultivates": "Cultivates",
        "Decision": "Decision",
        "Quality": "Quality",
        "Communicates": "Communicates",
        "Effectively": "Effectively",
        "Manages": "Manages",
        "ComplexityMeasures": "ComplexityMeasures",
        "Delivery": "Delivery",
        "roadmap": "roadmap",
        "projects": "projects",
        "Number": "Number",
        "issues": "issues",
        "SDLCEducation": "SDLCEducation",
        "Experience": "Experience",
        "Bachelor": "Bachelor",
        "Computer": "Computer",
        "Science": "Science",
        "years": "years",
        "technology": "technology",
        "specialty": "specialty",
        "protection": "protection",
        "property": "property",
        "platforms": "platforms",
        "SAST/DAST/IAST": "SAST/DAST/IAST",
        "g.": "g.",
        "OWASP": "OWASP",
        "CWE/SANS": "CWE/SANS",
        "O365": "O365",
        "Strong": "Strong",
        "assessment": "assessment",
        "Rapid7": "Rapid7",
        "Qualys": "Qualys",
        "Tenable": "Tenable",
        "policies": "policies",
        "standards": "standards",
        "ISO27001": "ISO27001",
        "ISO27002": "ISO27002",
        "PCI-DSS": "PCI-DSS",
        "NISTAbility": "NISTAbility",
        "concurrent": "concurrent",
        "priorities": "priorities",
        "meet": "meet",
        "deadlines": "deadlines",
        "communication": "communication",
        "ability": "ability",
        "scenarios": "scenarios",
        "audienceJob": "audienceJob",
        "DetailsSalary": "DetailsSalary",
        "Per": "Per",
        "YearJob": "YearJob",
        "Typefulltime": "Typefulltime",
        "days": "days"
      },
      "VERB": {
        "are": "are",
        "is": "is",
        "paid": "paid",
        "Looking": "Looking",
        "will": "will",
        "be": "be",
        "spent": "spent",
        "have": "have",
        "required": "required",
        "please": "please",
        "Staffing": "Staffing",
        "should": "should",
        "hired": "hired",
        "plays": "plays",
        "completing": "completing",
        "ensuring": "ensuring",
        "deploy": "deploy",
        "reduce": "reduce",
        "take": "take",
        "Acts": "Acts",
        "consulting": "consulting",
        "embedded": "embedded",
        "drive": "drive",
        "Build": "Build",
        "help": "help",
        "Testing": "Testing",
        "reviews": "reviews",
        "reviewing": "reviewing",
        "creating": "creating",
        "Works": "Works",
        "ensure": "ensure",
        "implemented": "implemented",
        "tested": "tested",
        "aggregated": "aggregated",
        "produced": "produced",
        "reviewed": "reviewed",
        "Cultivates": "Cultivates",
        "working": "working",
        "focusing": "focusing",
        "testing": "testing",
        "scanning": "scanning",
        "maintaining": "maintaining",
        "standardsWorking": "standardsWorking",
        "manage": "manage",
        "challenging": "challenging",
        "skillsDemonstrate": "skillsDemonstrate",
        "articulate": "articulate",
        "employeePosted": "employeePosted"
      },
      "ADJ": {
        "Senior": "Senior",
        "open": "open",
        "strong": "strong",
        "20-30": "20-30",
        "Offensive": "Offensive",
        "nice": "nice",
        "interested": "interested",
        "referral": "referral",
        "Permanent": "Permanent",
        "Full-Time": "Full-Time",
        "updated": "updated",
        "critical": "critical",
        "new": "new",
        "world-class": "world-class",
        "cyber": "cyber",
        "Key": "Key",
        "Strong": "Strong",
        "ethical": "ethical",
        "internal": "internal",
        "external": "external",
        "related": "related",
        "appropriate": "appropriate",
        "progressInfrastructure": "progressInfrastructure",
        "proper": "proper",
        "complex": "complex",
        "intellectual": "intellectual",
        "sensitive": "sensitive",
        "static": "static",
        "dynamic": "dynamic",
        "interactive": "interactive",
        "web": "web",
        "best": "best",
        "e.": "e.",
        "such": "such",
        "multiple": "multiple",
        "fast-paced": "fast-paced",
        "environmentStrong": "environmentStrong",
        "interpersonal": "interpersonal",
        "technical": "technical",
        "non-technical": "non-technical"
      },
      "NUM": {
        "10": "10",
        "15": "15",
        "25": "25",
        "30": "30",
        "150000": "150000",
        "170000": "170000",
        "140K": "140K",
        "170K": "170K",
        "401K": "401K",
        "30-40": "30-40",
        "60143Salary": "60143Salary"
      },
      "X": {},
      "PRT": {
        "to": "to",
        "'s": "'s"
      }
    }
  },
  "222946442": {
    "Company": "ADP Technology Services, Inc.",
    "Job Title": "Principal Application Developer",
    "Job Details": "DescriptionIT: ADP Technology Services, Inc|||| seeks a Principal Application Developer at our Alpharetta, GA loc|||| to participate in SDLC, incl|||| dsgn||||, test, test automation, review, & demo|||| of s/w solns|||| Bach’s deg|||| in Comp|||| Sci||||, Comp|||| Engg||||, Info|||| Sys||||, rel|||| Engg|||| discipline or a rel|||| field + 7 yrs of rel|||| exp|||| Alternatively, ADP will accept a Master’s deg|||| + 3 yrs of exp|||| 2 yrs of exp|||| must incl||||: Linux (CentOS/Amazon Linux); CI/CD sys– Teamcity & Octopus; Jenkins 2||||0 for Pipeline construction; Java; Python; Powershell; AWS; Containerization tech, incl|||| Docker, Rancher, Kubernetes, & AWS ECS; AWS IAM Policy Construction/Mgmt; Cloud Computing platforms, incl|||| Amazon AWS, Google Compute, & Azure; PaaS based components, incl|||| Elastic Beanstalk, Cloudfront, S3, & RDS; & App Lifecycle Mgmt tools, incl|||| New Relic, Dynatrace or Wily|||| To apply, please respond to req|||| 196192 at http://jobs||||adp||||com|||| Alternatively, applicants may mail their resume to the following address referencing req|||| 196192: Employment Practices, 1 ADP Blvd||||, MS 248, Roseland, NJ 07068||||Job DetailsJob Typefulltime, employeePosted 1 Day ago||||",
    "KeyWords": {
      "NOUN": {
        "ADP": "ADP",
        "Technology": "Technology",
        "Services": "Services",
        "Inc.": "Inc.",
        "Application": "Application",
        "Developer": "Developer",
        "Alpharetta": "Alpharetta",
        "GA": "GA",
        "loc": "loc",
        "SDLC": "SDLC",
        "incl": "incl",
        "dsgn": "dsgn",
        "test": "test",
        "automation": "automation",
        "review": "review",
        "demo": "demo",
        "solns": "solns",
        "Bach": "Bach",
        "deg": "deg",
        "Comp": "Comp",
        "Sci": "Sci",
        "Engg": "Engg",
        "Info": "Info",
        "Sys": "Sys",
        "rel": "rel",
        "discipline": "discipline",
        "field": "field",
        "yrs": "yrs",
        "exp": "exp",
        "Master": "Master",
        "Linux": "Linux",
        "CentOS/Amazon": "CentOS/Amazon",
        "CI/CD": "CI/CD",
        "Teamcity": "Teamcity",
        "Octopus": "Octopus",
        "Pipeline": "Pipeline",
        "construction": "construction",
        "Java": "Java",
        "Python": "Python",
        "Powershell": "Powershell",
        "AWS": "AWS",
        "Containerization": "Containerization",
        "tech": "tech",
        "Docker": "Docker",
        "Rancher": "Rancher",
        "Kubernetes": "Kubernetes",
        "ECS": "ECS",
        "IAM": "IAM",
        "Policy": "Policy",
        "Construction/Mgmt": "Construction/Mgmt",
        "Cloud": "Cloud",
        "Computing": "Computing",
        "platforms": "platforms",
        "Amazon": "Amazon",
        "Google": "Google",
        "Compute": "Compute",
        "Azure": "Azure",
        "PaaS": "PaaS",
        "components": "components",
        "Beanstalk": "Beanstalk",
        "Cloudfront": "Cloudfront",
        "S3": "S3",
        "RDS": "RDS",
        "App": "App",
        "Lifecycle": "Lifecycle",
        "Mgmt": "Mgmt",
        "tools": "tools",
        "New": "New",
        "Relic": "Relic",
        "Dynatrace": "Dynatrace",
        "Wily": "Wily",
        "respond": "respond",
        "http": "http",
        "//jobs": "//jobs",
        "adp": "adp",
        "com": "com",
        "applicants": "applicants",
        "resume": "resume",
        "address": "address",
        "req": "req",
        "Employment": "Employment",
        "Practices": "Practices",
        "Blvd": "Blvd",
        "MS": "MS",
        "Roseland": "Roseland",
        "NJ": "NJ",
        "Job": "Job",
        "DetailsJob": "DetailsJob",
        "Typefulltime": "Typefulltime",
        "Day": "Day"
      },
      "VERB": {
        "participate": "participate",
        "will": "will",
        "accept": "accept",
        "must": "must",
        "incl": "incl",
        "sys–": "sys–",
        "Jenkins": "Jenkins",
        "based": "based",
        "apply": "apply",
        "please": "please",
        "req": "req",
        "may": "may",
        "mail": "mail",
        "referencing": "referencing",
        "employeePosted": "employeePosted"
      },
      "ADJ": {
        "s/w": "s/w",
        "Elastic": "Elastic",
        "following": "following"
      },
      "PRT": {
        "To": "To",
        "to": "to"
      },
      "NUM": {
        "248": "248",
        "196192": "196192",
        "07068": "07068"
      }
    }
  },
  "222956881": {
    "Company": "AIC",
    "Job Title": "Data Warehouse / BI Developer II",
    "Job Details": "Description Title: Data Warehouse / BI Developer II Location: Remote Length: 6 months  Best candidates will also have experience in:* Machine Learning, Linear Regression, and statistical analysis* Experience with big data and event streaming concepts and visualization (Kafka, ELK, Splunk, Hadoop, Hive, Graphite, Prometheus)* Scripting Language (Python, JavaScript, *NIX)* Familiarity with Restful APIs and general Web Services* ETL and iPaaS Experience (Boomi, Pentaho)* Database Procedural Languages (PG/SQL,PL/SQL,T-SQL)* Data Warehouse (Kimball) and OLAP Modeling* General Relational Modeling (OLTP,OLEP, 3NF) Education / Experience / SkillsRequired:* Bachelor's or Master's Degree in Statistics, Math, Computer Science, Management Information Systems, Data Analytics or another quantitative discipline, or equivalent work experience* Minimum 5 year of experience in SQL* Advanced experience with Data Visualization tools (Tableau, Power BI)* Ability to visualize business concepts and analysis succinctly* Advanced Experience writing ad-hoc SQL queries (Postgres, Microsoft SQL)* Advanced Excel skills, including functions and pivot tables* General understanding of Business, Financial, Behavioral, Retail and Web analytics* Demonstrated ability to make complex data understandable and accessible to a non-technical audience* Excellent communication skills both written and verbal* Demonstrated ability to take initiative, solve complex problems, and make sound decisions* Authorization to work in the US Job Description:If you love data, robots, and coffee (not necessarily in that order!), then this is a great opportunity for you!The Costa Baristabot provides a specialty coffee experience which empowers people to create their perfect cups of coffee|||| By combining the best specialty ingredients with modern mobile technology, cloud computing, and robotics, we are transforming the entire coffee experience|||| Quality, consistency, and convenience…all in a small footprint|||| We are building the next generation of connected coffee experience and are looking for a creative and talented data analyst to help us to mine the wealth of data we generate about how people enjoy their coffee and use that information to drive our business and create a truly personalized experience for our customers|||| Strong candidates will be* A good cultural and communicative fit with all roles from Customer Support to Leadership* A highly adaptive, tenacious and positive attitude|||| You are someone who does not fear and indeed thrives in a fast-paced environment with rapidly changing requirements and context switching* A self-starter with a natural drive to clean up and formalize data and development processes as the Data team expands* A naturally analytical and diagnostic problem solver* Able to self-manage multiple projects and their prioritization at any given time while working independently Key Responsibilities* Develop/maintain/deliver critical business metric reporting as required by various business functions (Marketing, Engineering, Service, Operations, etc||||)* Respond to ad-hoc requests for analysis of customer, operational and engineering data* Present analysis results to functional and executive leaders* Contribute/develop insights into leveraging the data we collect to both improve our operational performance and our customer experience* Provide operational support for our data warehouse and operational reporting tools* Assist in the evaluation and implementation of data integration between operational processes as necessary Job DetailsJob Typefulltime, employeePosted 8 days ago||||",
    "KeyWords": {
      "NOUN": {
        "Title": "Title",
        "Data": "Data",
        "Warehouse": "Warehouse",
        "BI": "BI",
        "Developer": "Developer",
        "II": "II",
        "Location": "Location",
        "Length": "Length",
        "months": "months",
        "Best": "Best",
        "candidates": "candidates",
        "experience": "experience",
        "Machine": "Machine",
        "Learning": "Learning",
        "Linear": "Linear",
        "Regression": "Regression",
        "analysis": "analysis",
        "Experience": "Experience",
        "data": "data",
        "event": "event",
        "streaming": "streaming",
        "concepts": "concepts",
        "visualization": "visualization",
        "Kafka": "Kafka",
        "ELK": "ELK",
        "Splunk": "Splunk",
        "Hadoop": "Hadoop",
        "Hive": "Hive",
        "Graphite": "Graphite",
        "Prometheus": "Prometheus",
        "Language": "Language",
        "Python": "Python",
        "JavaScript": "JavaScript",
        "NIX": "NIX",
        "Familiarity": "Familiarity",
        "Restful": "Restful",
        "APIs": "APIs",
        "Web": "Web",
        "Services": "Services",
        "ETL": "ETL",
        "Boomi": "Boomi",
        "Pentaho": "Pentaho",
        "Database": "Database",
        "Procedural": "Procedural",
        "Languages": "Languages",
        "PG/SQL": "PG/SQL",
        "PL/SQL": "PL/SQL",
        "T-SQL": "T-SQL",
        "Kimball": "Kimball",
        "OLAP": "OLAP",
        "Modeling": "Modeling",
        "General": "General",
        "Relational": "Relational",
        "OLTP": "OLTP",
        "OLEP": "OLEP",
        "Education": "Education",
        "SkillsRequired": "SkillsRequired",
        "Bachelor": "Bachelor",
        "Master": "Master",
        "Degree": "Degree",
        "Statistics": "Statistics",
        "Math": "Math",
        "Computer": "Computer",
        "Science": "Science",
        "Management": "Management",
        "Information": "Information",
        "Systems": "Systems",
        "Analytics": "Analytics",
        "discipline": "discipline",
        "work": "work",
        "Minimum": "Minimum",
        "year": "year",
        "SQL": "SQL",
        "Advanced": "Advanced",
        "Visualization": "Visualization",
        "tools": "tools",
        "Tableau": "Tableau",
        "Power": "Power",
        "Ability": "Ability",
        "business": "business",
        "queries": "queries",
        "Postgres": "Postgres",
        "Microsoft": "Microsoft",
        "Excel": "Excel",
        "skills": "skills",
        "functions": "functions",
        "tables": "tables",
        "understanding": "understanding",
        "Business": "Business",
        "Financial": "Financial",
        "Behavioral": "Behavioral",
        "Retail": "Retail",
        "analytics": "analytics",
        "Demonstrated": "Demonstrated",
        "ability": "ability",
        "audience": "audience",
        "Excellent": "Excellent",
        "communication": "communication",
        "initiative": "initiative",
        "problems": "problems",
        "sound": "sound",
        "decisions": "decisions",
        "Authorization": "Authorization",
        "US": "US",
        "Job": "Job",
        "Description": "Description",
        "robots": "robots",
        "coffee": "coffee",
        "order": "order",
        "opportunity": "opportunity",
        "Costa": "Costa",
        "Baristabot": "Baristabot",
        "specialty": "specialty",
        "people": "people",
        "cups": "cups",
        "ingredients": "ingredients",
        "technology": "technology",
        "cloud": "cloud",
        "computing": "computing",
        "robotics": "robotics",
        "Quality": "Quality",
        "consistency": "consistency",
        "convenience…all": "convenience…all",
        "footprint": "footprint",
        "generation": "generation",
        "analyst": "analyst",
        "wealth": "wealth",
        "information": "information",
        "customers": "customers",
        "Strong": "Strong",
        "cultural": "cultural",
        "fit": "fit",
        "roles": "roles",
        "Customer": "Customer",
        "Support": "Support",
        "Leadership": "Leadership",
        "attitude": "attitude",
        "someone": "someone",
        "thrives": "thrives",
        "environment": "environment",
        "requirements": "requirements",
        "switching": "switching",
        "self-starter": "self-starter",
        "drive": "drive",
        "development": "development",
        "processes": "processes",
        "team": "team",
        "problem": "problem",
        "solver": "solver",
        "Able": "Able",
        "projects": "projects",
        "prioritization": "prioritization",
        "time": "time",
        "Key": "Key",
        "Responsibilities": "Responsibilities",
        "Develop/maintain/deliver": "Develop/maintain/deliver",
        "reporting": "reporting",
        "Marketing": "Marketing",
        "Engineering": "Engineering",
        "Service": "Service",
        "Operations": "Operations",
        "Respond": "Respond",
        "requests": "requests",
        "customer": "customer",
        "engineering": "engineering",
        "Present": "Present",
        "results": "results",
        "leaders": "leaders",
        "Contribute/develop": "Contribute/develop",
        "insights": "insights",
        "performance": "performance",
        "Provide": "Provide",
        "support": "support",
        "warehouse": "warehouse",
        "Assist": "Assist",
        "evaluation": "evaluation",
        "implementation": "implementation",
        "integration": "integration",
        "DetailsJob": "DetailsJob",
        "Typefulltime": "Typefulltime",
        "days": "days"
      },
      "ADJ": {
        "statistical": "statistical",
        "big": "big",
        "general": "general",
        "iPaaS": "iPaaS",
        "quantitative": "quantitative",
        "equivalent": "equivalent",
        "ad-hoc": "ad-hoc",
        "pivot": "pivot",
        "complex": "complex",
        "understandable": "understandable",
        "accessible": "accessible",
        "non-technical": "non-technical",
        "verbal": "verbal",
        "great": "great",
        "perfect": "perfect",
        "best": "best",
        "modern": "modern",
        "mobile": "mobile",
        "entire": "entire",
        "small": "small",
        "next": "next",
        "connected": "connected",
        "creative": "creative",
        "talented": "talented",
        "personalized": "personalized",
        "good": "good",
        "communicative": "communicative",
        "adaptive": "adaptive",
        "tenacious": "tenacious",
        "positive": "positive",
        "fast-paced": "fast-paced",
        "context": "context",
        "natural": "natural",
        "analytical": "analytical",
        "diagnostic": "diagnostic",
        "multiple": "multiple",
        "critical": "critical",
        "metric": "metric",
        "various": "various",
        "operational": "operational",
        "functional": "functional",
        "executive": "executive",
        "necessary": "necessary"
      },
      "VERB": {
        "have": "have",
        "Scripting": "Scripting",
        "visualize": "visualize",
        "writing": "writing",
        "including": "including",
        "make": "make",
        "written": "written",
        "take": "take",
        "solve": "solve",
        "work": "work",
        "love": "love",
        "is": "is",
        "provides": "provides",
        "empowers": "empowers",
        "create": "create",
        "combining": "combining",
        "are": "are",
        "transforming": "transforming",
        "building": "building",
        "looking": "looking",
        "help": "help",
        "mine": "mine",
        "generate": "generate",
        "enjoy": "enjoy",
        "use": "use",
        "drive": "drive",
        "will": "will",
        "be": "be",
        "does": "does",
        "fear": "fear",
        "changing": "changing",
        "clean": "clean",
        "formalize": "formalize",
        "expands": "expands",
        "self-manage": "self-manage",
        "given": "given",
        "working": "working",
        "required": "required",
        "leveraging": "leveraging",
        "collect": "collect",
        "improve": "improve",
        "employeePosted": "employeePosted"
      },
      "NUM": {},
      "PRT": {
        "'s": "'s",
        "to": "to",
        "up": "up"
      },
      "X": {}
    }
  },
  "222967821": {
    "Company": "Applied Resource Group",
    "Job Title": "Sr. Software Engineer (Elasticsearch)",
    "Job Details": "DescriptionSr|||| Software Engineer (Elasticsearch)Applied Resource Group is looking for an Elasticsearch veteran to be a driver for many of our e-commerce clients' future projects|||| You will interface with technical teams, lead some projects, and mentor more junior engineers|||| You will be integral to upgrades for their website, including AWS migrations, microservice implementations, and choosing queueing methodologies|||| ResponsibilitiesDevelop thorough technical requirements based on business needsDevelop high-quality code based on detailed designs that meet requirementsExtend our search capabilities to keep up with our growthImplement extensible architectures Implement modular designs for our Elasticsearch Repositories Build an infrastructure that protects each part of our system from the other parts Design our NoSQL solutions for a team dedicated to our selling and buying infrastructuresRequirementsBachelor’s degree in computer science, information technology or a related field plus 7 years practical experience, or equivalent8+ years of experience with open source or commercial search technology such as AWS Elasticsearch, Apache Lucene, or Apache Solr5+ years of software development experience in C#Experience with auto-suggests, search algorithms, recommendation engines, merchandising, and personalizationExperience processing large data sets (streaming and batch)Experience with event processing mechanisms such as Kafka, AWS SNS/SQS, RabbitMQExperience working with Kubernetes, Docker, and public cloud deployment platformsAbility to work independently within a geographically dispersed agile team participating in all Agile ceremoniesExcellent oral and written communication skillsJob DetailsSalary$135000 - $165000 Per YearJob Typefulltime, employeePosted 8 days ago||||",
    "KeyWords": {
      "NOUN": {
        "Software": "Software",
        "Engineer": "Engineer",
        "Elasticsearch": "Elasticsearch",
        "Applied": "Applied",
        "Resource": "Resource",
        "Group": "Group",
        "veteran": "veteran",
        "driver": "driver",
        "clients": "clients",
        "projects": "projects",
        "teams": "teams",
        "mentor": "mentor",
        "engineers": "engineers",
        "upgrades": "upgrades",
        "website": "website",
        "AWS": "AWS",
        "migrations": "migrations",
        "microservice": "microservice",
        "implementations": "implementations",
        "methodologies": "methodologies",
        "ResponsibilitiesDevelop": "ResponsibilitiesDevelop",
        "requirements": "requirements",
        "business": "business",
        "high-quality": "high-quality",
        "code": "code",
        "designs": "designs",
        "search": "search",
        "capabilities": "capabilities",
        "growthImplement": "growthImplement",
        "architectures": "architectures",
        "Implement": "Implement",
        "modular": "modular",
        "Repositories": "Repositories",
        "Build": "Build",
        "infrastructure": "infrastructure",
        "part": "part",
        "system": "system",
        "parts": "parts",
        "Design": "Design",
        "NoSQL": "NoSQL",
        "solutions": "solutions",
        "team": "team",
        "selling": "selling",
        "infrastructuresRequirementsBachelor": "infrastructuresRequirementsBachelor",
        "degree": "degree",
        "computer": "computer",
        "science": "science",
        "information": "information",
        "technology": "technology",
        "field": "field",
        "years": "years",
        "experience": "experience",
        "source": "source",
        "Apache": "Apache",
        "Lucene": "Lucene",
        "Solr5+": "Solr5+",
        "software": "software",
        "development": "development",
        "Experience": "Experience",
        "auto-suggests": "auto-suggests",
        "algorithms": "algorithms",
        "recommendation": "recommendation",
        "engines": "engines",
        "merchandising": "merchandising",
        "personalizationExperience": "personalizationExperience",
        "processing": "processing",
        "data": "data",
        "sets": "sets",
        "batch": "batch",
        "event": "event",
        "mechanisms": "mechanisms",
        "Kafka": "Kafka",
        "SNS/SQS": "SNS/SQS",
        "RabbitMQExperience": "RabbitMQExperience",
        "Kubernetes": "Kubernetes",
        "Docker": "Docker",
        "cloud": "cloud",
        "deployment": "deployment",
        "platformsAbility": "platformsAbility",
        "Agile": "Agile",
        "communication": "communication",
        "skillsJob": "skillsJob",
        "DetailsSalary": "DetailsSalary",
        "Per": "Per",
        "YearJob": "YearJob",
        "Typefulltime": "Typefulltime",
        "days": "days"
      },
      "VERB": {
        "looking": "looking",
        "be": "be",
        "will": "will",
        "interface": "interface",
        "lead": "lead",
        "including": "including",
        "choosing": "choosing",
        "queueing": "queueing",
        "based": "based",
        "meet": "meet",
        "requirementsExtend": "requirementsExtend",
        "keep": "keep",
        "protects": "protects",
        "dedicated": "dedicated",
        "buying": "buying",
        "streaming": "streaming",
        "processing": "processing",
        "working": "working",
        "work": "work",
        "dispersed": "dispersed",
        "participating": "participating",
        "written": "written",
        "employeePosted": "employeePosted"
      },
      "PRT": {
        "to": "to",
        "up": "up"
      },
      "ADJ": {
        "e-commerce": "e-commerce",
        "future": "future",
        "technical": "technical",
        "more": "more",
        "junior": "junior",
        "integral": "integral",
        "needsDevelop": "needsDevelop",
        "detailed": "detailed",
        "extensible": "extensible",
        "other": "other",
        "related": "related",
        "practical": "practical",
        "equivalent8+": "equivalent8+",
        "open": "open",
        "commercial": "commercial",
        "such": "such",
        "large": "large",
        "public": "public",
        "agile": "agile",
        "ceremoniesExcellent": "ceremoniesExcellent",
        "oral": "oral"
      },
      "NUM": {
        "165000": "165000"
      }
    }
  },
  "222968013": {
    "Company": "Apex Systems",
    "Job Title": "SAS Programmer Analyst",
    "Job Details": "DescriptionTitle: SAS ProgrammerLocation: Atlanta, GADuration: 6 month contractPurpose: Supporting the CDC's efforts this project requires strong epidemiological, statistical, and SAS programming expertise, experience using SUDAAN, and experience with web applications and website management||||This task requires1) Understanding and application of general statistical approaches including multivariate techniques (logistic regression, generalized linear models, proportional hazards modeling), and use of Kaplan-Meier survival analysis;2) Strong SAS programming skills;3) Orderly management of microcomputer files in a Windows environment to develop databases and analysis programs for data analysis;4) Statistical analysis of large, complex survey data requiring the use of SUDAAN;5) developing statistical reports and presenting data in Excel, particularly the ability to efficiently produce large complex Excel tables efficiently and reports from SAS in customized formats to fit the needs of periodic reports;6) Using PROC REPORT and other report production features of SAS to produce excel files of influenza vaccination coverage estimates;7) Importing, exporting, and manipulating data files (SAS, SUDAAN), including recoding, transforming, and creating variables to accommodate analytic needs;8) Using web applications to create interactive online reports and manage web content;9) Preparing written reports and presenting at sectional or national meetings; and 10) Performing other analytical and data related duties, as needed||||Education Required: MS, MPH, MSPH in Epidemiology, Statistics, Biostatistics, or MathRequired Skills: Applicants must have 3-5 years of statistical programming experience using SAS and SUDAAN with complex survey data, including SAS macro programming and design of data management systems for error checking and SAS report writing Technical experience with data management, dataset creation, data analysis and report generation||||  Experience with BRFSS data, or similar large data set, longitudinal data analysis, and large public health datasets|||| Experience in survey methods and survey design|||| Experience developing analysis plans and statistical reports|||| Must be able to work independently, with minimal direction|||| Excellent spoken and written communication skills in English||||\t Desired Skills: Prior experience with the analysis of influenza and public health epidemiologic dataEEO EmployerApex Systems is an equal opportunity employer|||| We do not discriminate or allow discrimination on the basis of race, color, religion, creed, sex (including pregnancy, childbirth, breastfeeding, or related medical conditions), age, sexual orientation, gender identity, national origin, ancestry, citizenship, genetic information, registered domestic partner status, marital status, disability, status as a crime victim, protected veteran status, political affiliation, union membership, or any other characteristic protected by law|||| Apex will consider qualified applicants with criminal histories in a manner consistent with the requirements of applicable law|||| If you have visited our website in search of information on employment opportunities or to apply for a position, and you require an accommodation in using our website for a search or application, please contact our Employee Services Department at employeeservices@apexsystemsinc||||com or 844-463-6178||||Job DetailsJob Typefulltime, employeePosted 8 days ago||||",
    "KeyWords": {
      "NOUN": {
        "ProgrammerLocation": "ProgrammerLocation",
        "Atlanta": "Atlanta",
        "GADuration": "GADuration",
        "month": "month",
        "contractPurpose": "contractPurpose",
        "CDC": "CDC",
        "efforts": "efforts",
        "project": "project",
        "SAS": "SAS",
        "programming": "programming",
        "expertise": "expertise",
        "experience": "experience",
        "SUDAAN": "SUDAAN",
        "web": "web",
        "applications": "applications",
        "management": "management",
        "task": "task",
        "requires1": "requires1",
        "Understanding": "Understanding",
        "application": "application",
        "approaches": "approaches",
        "multivariate": "multivariate",
        "techniques": "techniques",
        "regression": "regression",
        "models": "models",
        "hazards": "hazards",
        "use": "use",
        "Kaplan-Meier": "Kaplan-Meier",
        "analysis": "analysis",
        "Strong": "Strong",
        "skills": "skills",
        "Orderly": "Orderly",
        "microcomputer": "microcomputer",
        "files": "files",
        "Windows": "Windows",
        "environment": "environment",
        "databases": "databases",
        "programs": "programs",
        "data": "data",
        "survey": "survey",
        "reports": "reports",
        "Excel": "Excel",
        "ability": "ability",
        "tables": "tables",
        "formats": "formats",
        "needs": "needs",
        "PROC": "PROC",
        "REPORT": "REPORT",
        "report": "report",
        "production": "production",
        "features": "features",
        "vaccination": "vaccination",
        "coverage": "coverage",
        "estimates": "estimates",
        "Importing": "Importing",
        "recoding": "recoding",
        "transforming": "transforming",
        "variables": "variables",
        "online": "online",
        "manage": "manage",
        "content": "content",
        "meetings": "meetings",
        "duties": "duties",
        "Education": "Education",
        "MS": "MS",
        "MPH": "MPH",
        "MSPH": "MSPH",
        "Epidemiology": "Epidemiology",
        "Statistics": "Statistics",
        "Biostatistics": "Biostatistics",
        "MathRequired": "MathRequired",
        "Skills": "Skills",
        "Applicants": "Applicants",
        "years": "years",
        "macro": "macro",
        "design": "design",
        "systems": "systems",
        "error": "error",
        "checking": "checking",
        "creation": "creation",
        "generation": "generation",
        "Experience": "Experience",
        "BRFSS": "BRFSS",
        "set": "set",
        "health": "health",
        "datasets": "datasets",
        "methods": "methods",
        "plans": "plans",
        "Must": "Must",
        "direction": "direction",
        "Excellent": "Excellent",
        "communication": "communication",
        "English": "English",
        "Desired": "Desired",
        "influenza": "influenza",
        "epidemiologic": "epidemiologic",
        "dataEEO": "dataEEO",
        "EmployerApex": "EmployerApex",
        "Systems": "Systems",
        "opportunity": "opportunity",
        "employer": "employer",
        "discrimination": "discrimination",
        "basis": "basis",
        "race": "race",
        "color": "color",
        "religion": "religion",
        "creed": "creed",
        "sex": "sex",
        "pregnancy": "pregnancy",
        "childbirth": "childbirth",
        "breastfeeding": "breastfeeding",
        "conditions": "conditions",
        "age": "age",
        "orientation": "orientation",
        "gender": "gender",
        "identity": "identity",
        "origin": "origin",
        "ancestry": "ancestry",
        "citizenship": "citizenship",
        "information": "information",
        "partner": "partner",
        "status": "status",
        "disability": "disability",
        "crime": "crime",
        "victim": "victim",
        "veteran": "veteran",
        "affiliation": "affiliation",
        "union": "union",
        "membership": "membership",
        "law": "law",
        "Apex": "Apex",
        "applicants": "applicants",
        "histories": "histories",
        "manner": "manner",
        "requirements": "requirements",
        "website": "website",
        "search": "search",
        "employment": "employment",
        "opportunities": "opportunities",
        "position": "position",
        "accommodation": "accommodation",
        "Employee": "Employee",
        "Services": "Services",
        "Department": "Department",
        "employeeservices": "employeeservices",
        "apexsystemsinc": "apexsystemsinc",
        "com": "com",
        "Job": "Job",
        "DetailsJob": "DetailsJob",
        "Typefulltime": "Typefulltime",
        "days": "days"
      },
      "ADJ": {
        "strong": "strong",
        "epidemiological": "epidemiological",
        "statistical": "statistical",
        "website": "website",
        "general": "general",
        "logistic": "logistic",
        "linear": "linear",
        "proportional": "proportional",
        "survival": "survival",
        "Statistical": "Statistical",
        "large": "large",
        "complex": "complex",
        "customized": "customized",
        "periodic": "periodic",
        "other": "other",
        "excel": "excel",
        "influenza": "influenza",
        "analytic": "analytic",
        "web": "web",
        "interactive": "interactive",
        "sectional": "sectional",
        "national": "national",
        "analytical": "analytical",
        "related": "related",
        "3-5": "3-5",
        "data": "data",
        "Technical": "Technical",
        "similar": "similar",
        "longitudinal": "longitudinal",
        "public": "public",
        "able": "able",
        "minimal": "minimal",
        "spoken": "spoken",
        "Prior": "Prior",
        "equal": "equal",
        "medical": "medical",
        "sexual": "sexual",
        "genetic": "genetic",
        "domestic": "domestic",
        "marital": "marital",
        "political": "political",
        "characteristic": "characteristic",
        "qualified": "qualified",
        "criminal": "criminal",
        "consistent": "consistent",
        "applicable": "applicable",
        "844-463-6178": "844-463-6178"
      },
      "VERB": {
        "requires": "requires",
        "using": "using",
        "including": "including",
        "generalized": "generalized",
        "modeling": "modeling",
        "programming": "programming",
        "develop": "develop",
        "requiring": "requiring",
        "developing": "developing",
        "presenting": "presenting",
        "produce": "produce",
        "fit": "fit",
        "Using": "Using",
        "exporting": "exporting",
        "manipulating": "manipulating",
        "creating": "creating",
        "accommodate": "accommodate",
        "create": "create",
        "Preparing": "Preparing",
        "written": "written",
        "Performing": "Performing",
        "needed": "needed",
        "Required": "Required",
        "must": "must",
        "have": "have",
        "writing": "writing",
        "dataset": "dataset",
        "be": "be",
        "work": "work",
        "is": "is",
        "do": "do",
        "discriminate": "discriminate",
        "allow": "allow",
        "registered": "registered",
        "protected": "protected",
        "will": "will",
        "consider": "consider",
        "visited": "visited",
        "apply": "apply",
        "require": "require",
        "please": "please",
        "contact": "contact",
        "employeePosted": "employeePosted"
      },
      "PRT": {
        "to": "to"
      },
      "NUM": {}
    }
  },
  "223016033": {
    "Company": "Eliassen Group",
    "Job Title": "Azure Cloud Infrastructure Engineer (w-2 only)",
    "Job Details": "DescriptionAzure Cloud Infrastructure Engineer (w-2 only) Our client, a leader in their industry, has an excellent opportunity available for an Azure Cloud Infrastructure Engineer to work on a 6-month + contract position in Alpharetta, GA|||| The pay rate is in the $60 to $70/hour w-2 range|||| This position will be remote until the Covid restrictions clear and then will be onsite in Alpharetta|||| Available for w-2 only|||| No travel is required||||  Responsibilities of the Azure Cloud Infrastructure Engineer:Build and administer Azure cloud infrastructure consisting of computing, security, networking, database, and infrastructure as codeConstruct and manage CI/CD pipelines Automation using Bash, PowerShell, Azure CLI, Python, and Terraform Requirements for the Azure Cloud Infrastructure Engineer:Seeking an Azure Cloud specialist with five + years of related experienceExperience with Bash/PowerShell/Azure CLIStrong hands-on experience with Terraform and PackerExperience with security, networking, databases, and infrastructure as code as it pertains to Microsoft AzureExperience with orchestration frameworks and Continuous Integration and Delivery (CI/CD) tools (preferably Azure DevOps tools)Experience with Linux and Windows operating systemsExperience with one or more high-level programming languages such as Python, Go, or TypescriptExperience with Kubernetes Please send your MS Word resume to Ben Crosby at bcrosby@eliassen||||com or call me at 770-399-4508 for immediate consideration|||| Direct w-2 employment only – No 3rd Parties – Position not eligible for Visa Sponsorship or Transfer|||| Job #:347537 Why Choose Eliassen Group?Working as an Eliassen Group contractor gives you exceptional benefits! Our consultants receive medical, dental, vision, disability, life, and prescription drug coverage through United Health Group|||| We also offer a 401(k) plan through Fidelity with matching, direct deposit, weekly payment, and a $1000 referral bonus plan|||| Eliassen Group also has a Consultant Advocacy Program with specialized consultant care professionals dedicated to serving you once you start working with us|||| We are currently achieving “World Class” Net Promoter Score Status and are one of Inc|||| Magazine’s 50 Best Places to Work|||| Locally, Atlanta Business Chronicle has also rated us One of the Best Places to Work in Atlanta in 2017||||  We have over 300 clients in 22 offices and have access to the best companies and most sought-after IT career and consulting opportunities in America|||| Apply with Eliassen Group today to see how we can serve you!     Job DetailsSalary$60 - $70 Per YearJob Typefulltime, contractPosted 7 days ago||||",
    "KeyWords": {
      "NOUN": {
        "Cloud": "Cloud",
        "Infrastructure": "Infrastructure",
        "Engineer": "Engineer",
        "client": "client",
        "leader": "leader",
        "industry": "industry",
        "opportunity": "opportunity",
        "Azure": "Azure",
        "contract": "contract",
        "position": "position",
        "Alpharetta": "Alpharetta",
        "GA": "GA",
        "pay": "pay",
        "rate": "rate",
        "range": "range",
        "Covid": "Covid",
        "restrictions": "restrictions",
        "travel": "travel",
        "Responsibilities": "Responsibilities",
        "Build": "Build",
        "cloud": "cloud",
        "infrastructure": "infrastructure",
        "security": "security",
        "networking": "networking",
        "database": "database",
        "codeConstruct": "codeConstruct",
        "manage": "manage",
        "CI/CD": "CI/CD",
        "Automation": "Automation",
        "Bash": "Bash",
        "PowerShell": "PowerShell",
        "CLI": "CLI",
        "Python": "Python",
        "Terraform": "Terraform",
        "Requirements": "Requirements",
        "specialist": "specialist",
        "years": "years",
        "experienceExperience": "experienceExperience",
        "Bash/PowerShell/Azure": "Bash/PowerShell/Azure",
        "CLIStrong": "CLIStrong",
        "experience": "experience",
        "PackerExperience": "PackerExperience",
        "databases": "databases",
        "code": "code",
        "Microsoft": "Microsoft",
        "AzureExperience": "AzureExperience",
        "orchestration": "orchestration",
        "frameworks": "frameworks",
        "Integration": "Integration",
        "Delivery": "Delivery",
        "tools": "tools",
        "DevOps": "DevOps",
        "Experience": "Experience",
        "Linux": "Linux",
        "Windows": "Windows",
        "systemsExperience": "systemsExperience",
        "programming": "programming",
        "languages": "languages",
        "Go": "Go",
        "TypescriptExperience": "TypescriptExperience",
        "Kubernetes": "Kubernetes",
        "Please": "Please",
        "MS": "MS",
        "Word": "Word",
        "resume": "resume",
        "Ben": "Ben",
        "Crosby": "Crosby",
        "bcrosby": "bcrosby",
        "eliassen": "eliassen",
        "com": "com",
        "770-399-4508": "770-399-4508",
        "consideration": "consideration",
        "employment": "employment",
        "Parties": "Parties",
        "Position": "Position",
        "Visa": "Visa",
        "Sponsorship": "Sponsorship",
        "Transfer": "Transfer",
        "Job": "Job",
        ":347537": ":347537",
        "Choose": "Choose",
        "Eliassen": "Eliassen",
        "Group": "Group",
        "Working": "Working",
        "contractor": "contractor",
        "benefits": "benefits",
        "consultants": "consultants",
        "vision": "vision",
        "disability": "disability",
        "life": "life",
        "prescription": "prescription",
        "drug": "drug",
        "coverage": "coverage",
        "United": "United",
        "Health": "Health",
        "plan": "plan",
        "Fidelity": "Fidelity",
        "matching": "matching",
        "deposit": "deposit",
        "payment": "payment",
        "bonus": "bonus",
        "Advocacy": "Advocacy",
        "Program": "Program",
        "consultant": "consultant",
        "care": "care",
        "professionals": "professionals",
        "World": "World",
        "Class": "Class",
        "Net": "Net",
        "Promoter": "Promoter",
        "Score": "Score",
        "Status": "Status",
        "Inc.": "Inc.",
        "Magazine": "Magazine",
        "Best": "Best",
        "Places": "Places",
        "Atlanta": "Atlanta",
        "Business": "Business",
        "Chronicle": "Chronicle",
        "clients": "clients",
        "offices": "offices",
        "access": "access",
        "companies": "companies",
        "IT": "IT",
        "career": "career",
        "opportunities": "opportunities",
        "America": "America",
        "Apply": "Apply",
        "today": "today",
        "DetailsSalary": "DetailsSalary",
        "Per": "Per",
        "YearJob": "YearJob",
        "Typefulltime": "Typefulltime",
        "days": "days"
      },
      "ADJ": {
        "excellent": "excellent",
        "available": "available",
        "6-month": "6-month",
        "w-2": "w-2",
        "clear": "clear",
        "Available": "Available",
        "administer": "administer",
        "related": "related",
        "hands-on": "hands-on",
        "Continuous": "Continuous",
        "more": "more",
        "high-level": "high-level",
        "such": "such",
        "immediate": "immediate",
        "Direct": "Direct",
        "3rd": "3rd",
        "eligible": "eligible",
        "exceptional": "exceptional",
        "medical": "medical",
        "dental": "dental",
        "direct": "direct",
        "weekly": "weekly",
        "referral": "referral",
        "Consultant": "Consultant",
        "specialized": "specialized",
        "best": "best",
        "most": "most",
        "sought-after": "sought-after"
      },
      "VERB": {
        "work": "work",
        "is": "is",
        "will": "will",
        "be": "be",
        "remote": "remote",
        "required": "required",
        "consisting": "consisting",
        "computing": "computing",
        "pipelines": "pipelines",
        "using": "using",
        "Seeking": "Seeking",
        "pertains": "pertains",
        "operating": "operating",
        "send": "send",
        "call": "call",
        "gives": "gives",
        "receive": "receive",
        "offer": "offer",
        "has": "has",
        "dedicated": "dedicated",
        "serving": "serving",
        "start": "start",
        "working": "working",
        "are": "are",
        "achieving": "achieving",
        "Work": "Work",
        "rated": "rated",
        "have": "have",
        "consulting": "consulting",
        "see": "see",
        "can": "can",
        "serve": "serve",
        "contractPosted": "contractPosted"
      },
      "PRT": {
        "to": "to",
        "over": "over"
      },
      "NUM": {
        "22": "22",
        "50": "50",
        "60": "60",
        "70": "70",
        "300": "300",
        "401": "401",
        "1000": "1000",
        "2017": "2017",
        "70/hour": "70/hour",
        "five": "five",
        "one": "one",
        "One": "One"
      }
    }
  },
  "223023024": {
    "Company": "LifeQ Inc.",
    "Job Title": "Embedded Software Engineer",
    "Job Details": "DescriptionEmbedded Software Engineer \n\n\tAn ADP Client, LifeQ is currently seeking an Embedded Software Engineer \n\n\tto join the team Alpharetta, GA 30022||||\n\n\tWho We Are:\n\n\t•            Join the LifeQ electronic engineering team! LifeQ is the leading independent provider of wearable device biometrics in the world|||| Our engineering team develops algorithms for extracting and analyzing biometric data, works with a range of sensors for biometric measurement, develops wearable device prototypes, and integrates this technology into commercial wearable devices|||| As we serve a range of customers across the industries of insurance, consumer tech, and healthcare, LifeQ technology is currently embedded in wearable devices on the wrists of millions of people across the world|||| To deliver these solutions and advance the frontier of biometrics, we partner with global leaders of industry, research, and health||||\n\n\t•            https://www||||lifeq||||com/solutions/ \n\n\tAbout the role:\n\n\tLifeQ is seeking a dynamic, enthusiastic, experienced Embedded Software Engineer to be part of the Engineering function|||| LifeQ provides a fast-paced and dynamic work environment with industry-leading technology and exposure to influential international corporations|||| Employees enjoy a comfortable office environment with benefits such as a gym, creative remote and office-based work policy, a fully equipped kitchen and amazing coffee! The ideal candidate will be someone with great interpersonal skills, has a willingness to learn and a drive for innovative solutions to launch the company forward|||| Responsible for providing project planning and management for established initiatives within a company|||| You will ensure that projects are completed to specification, within an established time frame and budget||||\n\n\tEssential Duties and Responsibilities:\n\n\t•            Designing, Building and maintaining embedded code subsystems and algorithms||||\n\n\t•            Working closely with engineers and project manager at some of the biggest tech companies in the world||||\n\n\t•            Collaborating with adjacent internal technical teams: Hardware, software, data analytics, and QC Teams||||\n\n\t•            Writing, understanding and explaining embedded code and concepts||||\n\n\t•            Designing, enhancing and maintaining systems for building, testing and continuously integrating code||||\n\n\tOur Ideal Candidate:\n\n\t(Minimum Requirements)\n\n\t•            A university degree in Computer Science, Electronic Engineering, or related field||||\n\n\t•            Experienced Programmer in C\n\n\t•            Analytical thinker and problem solver \n\n\t•            Self-motivated, self-starter, ambitious, willing to take on initiative\n\n\t(Preferred Requirements)\n\n\t•            Post-graduate Degree in Computer Science, Electronic Engineering or related field\n\n\t•            Solid basis (computer science or related field) in data structure, algorithm, and code optimization\n\n\t•            Prior experience working with Wearables or other loT devices\n\n\t•            Comport working with Python\n\n\t•            Experience in sensor signal conditioning, DSP, and data analysis\n\n\tJob Specifics:\n\n\t•            Travel: In the foreseeable future - yes - right now, no||||\n\n\t•            Employment Type: Full time\n\n\t•            Type of person: Critical thinking, strong in your domain\n\n\t•            Working hours: We are a startup - normal work week is applicable - full time team member||||\n\n\t•            Vacancy reason: Simple - we are growing and need smart people on the bus\n\n\tWhat We Offer:\n\n\t•            Competitive pay; commensurate with experience\n\n\t•            Benefits package is available (Medical, Dental, Vision, Life) 401k Match, PTO, Holiday Pay, etc|||| \n\n\tTo Apply: \n\n\tPlease submit your resume via the \"APPLY NOW\" button\n\n\tEqual Opportunity Employer\n\n\t#INDFULLJob DetailsJob TypefulltimePosted 6 days ago||||",
    "KeyWords": {
      "NOUN": {
        "Software": "Software",
        "Engineer": "Engineer",
        "ADP": "ADP",
        "Client": "Client",
        "LifeQ": "LifeQ",
        "Embedded": "Embedded",
        "team": "team",
        "Alpharetta": "Alpharetta",
        "GA": "GA",
        "Join": "Join",
        "engineering": "engineering",
        "provider": "provider",
        "device": "device",
        "biometrics": "biometrics",
        "world": "world",
        "data": "data",
        "range": "range",
        "sensors": "sensors",
        "measurement": "measurement",
        "prototypes": "prototypes",
        "technology": "technology",
        "devices": "devices",
        "customers": "customers",
        "industries": "industries",
        "insurance": "insurance",
        "consumer": "consumer",
        "tech": "tech",
        "healthcare": "healthcare",
        "wrists": "wrists",
        "millions": "millions",
        "people": "people",
        "solutions": "solutions",
        "frontier": "frontier",
        "partner": "partner",
        "leaders": "leaders",
        "industry": "industry",
        "research": "research",
        "health": "health",
        "https": "https",
        "//www": "//www",
        "lifeq": "lifeq",
        "com/solutions/": "com/solutions/",
        "role": "role",
        "part": "part",
        "Engineering": "Engineering",
        "function": "function",
        "work": "work",
        "environment": "environment",
        "exposure": "exposure",
        "corporations": "corporations",
        "Employees": "Employees",
        "office": "office",
        "benefits": "benefits",
        "gym": "gym",
        "remote": "remote",
        "policy": "policy",
        "kitchen": "kitchen",
        "coffee": "coffee",
        "candidate": "candidate",
        "someone": "someone",
        "skills": "skills",
        "willingness": "willingness",
        "drive": "drive",
        "company": "company",
        "project": "project",
        "planning": "planning",
        "management": "management",
        "initiatives": "initiatives",
        "projects": "projects",
        "specification": "specification",
        "time": "time",
        "frame": "frame",
        "budget": "budget",
        "Duties": "Duties",
        "Responsibilities": "Responsibilities",
        "Designing": "Designing",
        "Building": "Building",
        "code": "code",
        "subsystems": "subsystems",
        "algorithms": "algorithms",
        "engineers": "engineers",
        "manager": "manager",
        "companies": "companies",
        "teams": "teams",
        "Hardware": "Hardware",
        "software": "software",
        "analytics": "analytics",
        "QC": "QC",
        "Teams": "Teams",
        "Writing": "Writing",
        "concepts": "concepts",
        "systems": "systems",
        "building": "building",
        "Candidate": "Candidate",
        "Minimum": "Minimum",
        "Requirements": "Requirements",
        "university": "university",
        "degree": "degree",
        "Computer": "Computer",
        "Science": "Science",
        "Electronic": "Electronic",
        "field": "field",
        "Programmer": "Programmer",
        "Analytical": "Analytical",
        "thinker": "thinker",
        "problem": "problem",
        "solver": "solver",
        "Self-motivated": "Self-motivated",
        "self-starter": "self-starter",
        "initiative": "initiative",
        "Preferred": "Preferred",
        "Post-graduate": "Post-graduate",
        "Degree": "Degree",
        "Solid": "Solid",
        "basis": "basis",
        "computer": "computer",
        "science": "science",
        "structure": "structure",
        "algorithm": "algorithm",
        "optimization": "optimization",
        "Prior": "Prior",
        "experience": "experience",
        "Wearables": "Wearables",
        "loT": "loT",
        "Comport": "Comport",
        "Python": "Python",
        "Experience": "Experience",
        "conditioning": "conditioning",
        "DSP": "DSP",
        "analysis": "analysis",
        "Job": "Job",
        "Specifics": "Specifics",
        "Travel": "Travel",
        "Type": "Type",
        "person": "person",
        "thinking": "thinking",
        "domain": "domain",
        "hours": "hours",
        "week": "week",
        "member": "member",
        "Vacancy": "Vacancy",
        "reason": "reason",
        "bus": "bus",
        "Competitive": "Competitive",
        "pay": "pay",
        "commensurate": "commensurate",
        "Benefits": "Benefits",
        "package": "package",
        "Medical": "Medical",
        "Dental": "Dental",
        "Vision": "Vision",
        "Life": "Life",
        "Match": "Match",
        "PTO": "PTO",
        "Holiday": "Holiday",
        "Pay": "Pay",
        "Please": "Please",
        "resume": "resume",
        "APPLY": "APPLY",
        "NOW": "NOW",
        "button": "button",
        "Equal": "Equal",
        "Opportunity": "Opportunity",
        "Employer": "Employer",
        "INDFULLJob": "INDFULLJob",
        "DetailsJob": "DetailsJob",
        "days": "days"
      },
      "VERB": {
        "seeking": "seeking",
        "join": "join",
        "Are": "Are",
        "is": "is",
        "leading": "leading",
        "develops": "develops",
        "extracting": "extracting",
        "analyzing": "analyzing",
        "works": "works",
        "integrates": "integrates",
        "serve": "serve",
        "embedded": "embedded",
        "deliver": "deliver",
        "advance": "advance",
        "experienced": "experienced",
        "be": "be",
        "provides": "provides",
        "enjoy": "enjoy",
        "equipped": "equipped",
        "will": "will",
        "has": "has",
        "learn": "learn",
        "launch": "launch",
        "providing": "providing",
        "established": "established",
        "ensure": "ensure",
        "are": "are",
        "completed": "completed",
        "maintaining": "maintaining",
        "Working": "Working",
        "Collaborating": "Collaborating",
        "understanding": "understanding",
        "explaining": "explaining",
        "enhancing": "enhancing",
        "testing": "testing",
        "Experienced": "Experienced",
        "take": "take",
        "related": "related",
        "working": "working",
        "growing": "growing",
        "need": "need",
        "Offer": "Offer",
        "Apply": "Apply",
        "submit": "submit",
        "TypefulltimePosted": "TypefulltimePosted"
      },
      "PRT": {
        "To": "To",
        "to": "to"
      },
      "NUM": {
        "401k": "401k"
      },
      "ADJ": {
        "independent": "independent",
        "wearable": "wearable",
        "biometric": "biometric",
        "commercial": "commercial",
        "global": "global",
        "dynamic": "dynamic",
        "enthusiastic": "enthusiastic",
        "fast-paced": "fast-paced",
        "industry-leading": "industry-leading",
        "influential": "influential",
        "international": "international",
        "comfortable": "comfortable",
        "such": "such",
        "creative": "creative",
        "office-based": "office-based",
        "amazing": "amazing",
        "ideal": "ideal",
        "great": "great",
        "interpersonal": "interpersonal",
        "innovative": "innovative",
        "Responsible": "Responsible",
        "established": "established",
        "Essential": "Essential",
        "embedded": "embedded",
        "biggest": "biggest",
        "adjacent": "adjacent",
        "internal": "internal",
        "technical": "technical",
        "integrating": "integrating",
        "Ideal": "Ideal",
        "related": "related",
        "ambitious": "ambitious",
        "willing": "willing",
        "other": "other",
        "sensor": "sensor",
        "signal": "signal",
        "foreseeable": "foreseeable",
        "future": "future",
        "Employment": "Employment",
        "Full": "Full",
        "Critical": "Critical",
        "strong": "strong",
        "startup": "startup",
        "normal": "normal",
        "applicable": "applicable",
        "full": "full",
        "Simple": "Simple",
        "smart": "smart",
        "available": "available"
      },
      "X": {
        "etc": "etc"
      },
      ".": {
        "''": "''"
      }
    }
  },
  "223120415": {
    "Company": "North Highland",
    "Job Title": "Low Code Developer",
    "Job Details": "DescriptionLEAVE YOUR MARK ON A BETTER WORLD||||COLLABORATE WITH AMAZING PEOPLE||||MAKE CHANGE HAPPEN||||At North Highland, we believe in doing great things together|||| With you|||| With our clients|||| With a perspective on actions today that shape tomorrow|||| As the world’s most innovative, collaborative consulting group, we’ve built a space to share ideas like never before|||| Do you have the skills, passion and commitment to transform industries for the better? Think you can bring your A-game every day? If so, join us|||| We like big thinkers with action on the brain…Why North Highland? Every choice you make will give you the opportunity to grow|||| It’s our employee ownership model - with plenty of coaching and personal development opportunities in the mix|||| For us, training doesn’t have an off switch|||| You’ll learn new things, both during and beyond traditional working hours|||| We want people who strive for the next level, then the next||||At North Highland, you’re never a number|||| Our firm is large enough to scale up, test your mettle and tackle big challenges, but small enough that clients won’t lose your face in a crowd|||| You’re recognized individually||||We started as three leaders and a kitchen table|||| Which means we know expectations are made to be broken|||| Want to surprise us? Do it|||| Experiment and stretch yourself|||| There’s room to grow as a budding entrepreneur|||| Exciting work you will do:The Low-code engineer will be responsible for developing applications using a low-code development platform, setting up and configuring systems for each client's unique requirements|||| Delivering  enterprise applications with minimal traditional coding needed Working with three key elements: form builders, pre-built templates, drag-and-drop visual interface, entity builder Researching and analyzing internal business processes with the scope of optimizing and automating them Building technology like a software engineer, but faster and smarter using productivity tools Strong confidence in leading customer project engagements is essential, but it can be gained in time, too|||| Capture and clearly articulate requirements: work closely with end clients in order to prioritize different working items Establish implementation capabilities and limitations, performance requirements and interfaces for the end-user solution Deliver efficient solutions using low-code: analyze clients business, systems, and workflow processes and come up with solutions that meet customer's needs Carry out solution testing: ensure efficient onboarding processes for new clients; carry out root-cause analysis to develop logical conclusions and suggest alternative configurations Overall ownership of solution implementation: be in charge of assigned customer projects, ensuring timely and efficient communication and solutions are delivered to plan Coordinate and execute testing, in concert with customers to ensure successful implementation What you will need: Minimum (2) years experience Technical Support, specializing in software and problem diagnosis Leading and planning technical software implementation processes Working with customers to capture and define requirements Leading implementation activities Knowledge of APIs and experience of software integration Agile working practice, structured project management, and communication Ability to diagnose application issues and to decide what can be done with low-code instead of traditional coding (80/20 rule) Intuitive about how an idea can be turned to an actual working application using drag and drop visual environment Familiarity with pre-built templates, drag-and-drop visual interface, entity builder Basic SQL, HTML, CSS, JavaScript, and general Web 2||||0 techniques experience For more complex applications, experience with front end frameworks (Bootstrap, Materialize) would be useful Productivity and performance focus Problem-solving skills and solution-oriented attitude Cross-functional teams clear communication Client-oriented and a collaborative spirit Proactivity in automating processes as much as possible; Curious and a continuous hunger for learning and staying up to date with the latest solutions on the market (especially in the low-code field) Analytical mind Creativity, open-minded attitude ** Applicants must be authorized to work in the United States without the need for visa sponsorship by North Highland||||  Work visa sponsorship will not be provided, now or in the future, for this position||||Click HERE to apply North Highland makes change happen for organizations who dare to be different|||| By melding workforce, customer and operational transformation, they are one of the world’s leading consulting groups, with 65+ offices around the globe|||| They break new ground today so tomorrow is easier to explore||||For more information, visit northhighland||||com and connect with us on LinkedIn, Twitter and Facebook||||North Highland is an Equal Employment Opportunity (EEO)/Affirmative Action employer|||| All qualified applicants will receive fair and impartial consideration without regard to race, color, sex, gender identity, religion, national origin, age, sexual orientation, disability, veteran status, or any other characteristic protected by law||||Job DetailsJob Typefulltime, employeePostedToday||||",
    "KeyWords": {
      "NOUN": {
        "YOUR": "YOUR",
        "MARK": "MARK",
        "ON": "ON",
        "BETTER": "BETTER",
        "WORLD": "WORLD",
        "COLLABORATE": "COLLABORATE",
        "WITH": "WITH",
        "AMAZING": "AMAZING",
        "PEOPLE": "PEOPLE",
        "MAKE": "MAKE",
        "CHANGE": "CHANGE",
        "HAPPEN": "HAPPEN",
        "North": "North",
        "Highland": "Highland",
        "things": "things",
        "clients": "clients",
        "perspective": "perspective",
        "actions": "actions",
        "today": "today",
        "shape": "shape",
        "tomorrow": "tomorrow",
        "world": "world",
        "consulting": "consulting",
        "group": "group",
        "space": "space",
        "share": "share",
        "ideas": "ideas",
        "skills": "skills",
        "passion": "passion",
        "commitment": "commitment",
        "industries": "industries",
        "day": "day",
        "thinkers": "thinkers",
        "action": "action",
        "Every": "Every",
        "choice": "choice",
        "opportunity": "opportunity",
        "employee": "employee",
        "ownership": "ownership",
        "model": "model",
        "plenty": "plenty",
        "coaching": "coaching",
        "development": "development",
        "opportunities": "opportunities",
        "mix": "mix",
        "switch": "switch",
        "hours": "hours",
        "people": "people",
        "level": "level",
        "number": "number",
        "firm": "firm",
        "mettle": "mettle",
        "tackle": "tackle",
        "challenges": "challenges",
        "face": "face",
        "crowd": "crowd",
        "leaders": "leaders",
        "kitchen": "kitchen",
        "table": "table",
        "expectations": "expectations",
        "Experiment": "Experiment",
        "room": "room",
        "budding": "budding",
        "entrepreneur": "entrepreneur",
        "work": "work",
        "Low-code": "Low-code",
        "engineer": "engineer",
        "applications": "applications",
        "platform": "platform",
        "systems": "systems",
        "client": "client",
        "requirements": "requirements",
        "enterprise": "enterprise",
        "coding": "coding",
        "elements": "elements",
        "form": "form",
        "builders": "builders",
        "templates": "templates",
        "interface": "interface",
        "entity": "entity",
        "builder": "builder",
        "Researching": "Researching",
        "business": "business",
        "processes": "processes",
        "scope": "scope",
        "Building": "Building",
        "technology": "technology",
        "software": "software",
        "productivity": "productivity",
        "tools": "tools",
        "Strong": "Strong",
        "confidence": "confidence",
        "customer": "customer",
        "project": "project",
        "engagements": "engagements",
        "time": "time",
        "Capture": "Capture",
        "order": "order",
        "items": "items",
        "implementation": "implementation",
        "capabilities": "capabilities",
        "limitations": "limitations",
        "performance": "performance",
        "interfaces": "interfaces",
        "solution": "solution",
        "Deliver": "Deliver",
        "solutions": "solutions",
        "low-code": "low-code",
        "needs": "needs",
        "Carry": "Carry",
        "testing": "testing",
        "root-cause": "root-cause",
        "analysis": "analysis",
        "conclusions": "conclusions",
        "configurations": "configurations",
        "charge": "charge",
        "projects": "projects",
        "communication": "communication",
        "Coordinate": "Coordinate",
        "concert": "concert",
        "customers": "customers",
        "Minimum": "Minimum",
        "years": "years",
        "Support": "Support",
        "problem": "problem",
        "diagnosis": "diagnosis",
        "Leading": "Leading",
        "activities": "activities",
        "Knowledge": "Knowledge",
        "APIs": "APIs",
        "experience": "experience",
        "integration": "integration",
        "Agile": "Agile",
        "practice": "practice",
        "management": "management",
        "Ability": "Ability",
        "application": "application",
        "issues": "issues",
        "rule": "rule",
        "idea": "idea",
        "working": "working",
        "drag": "drag",
        "drop": "drop",
        "environment": "environment",
        "Familiarity": "Familiarity",
        "Basic": "Basic",
        "SQL": "SQL",
        "HTML": "HTML",
        "CSS": "CSS",
        "JavaScript": "JavaScript",
        "Web": "Web",
        "techniques": "techniques",
        "end": "end",
        "frameworks": "frameworks",
        "Bootstrap": "Bootstrap",
        "Materialize": "Materialize",
        "Productivity": "Productivity",
        "focus": "focus",
        "Problem-solving": "Problem-solving",
        "attitude": "attitude",
        "teams": "teams",
        "Client-oriented": "Client-oriented",
        "spirit": "spirit",
        "Proactivity": "Proactivity",
        "Curious": "Curious",
        "hunger": "hunger",
        "date": "date",
        "market": "market",
        "field": "field",
        "Analytical": "Analytical",
        "mind": "mind",
        "Creativity": "Creativity",
        "Applicants": "Applicants",
        "United": "United",
        "States": "States",
        "need": "need",
        "sponsorship": "sponsorship",
        "Work": "Work",
        "future": "future",
        "position": "position",
        "Click": "Click",
        "HERE": "HERE",
        "change": "change",
        "organizations": "organizations",
        "workforce": "workforce",
        "transformation": "transformation",
        "groups": "groups",
        "offices": "offices",
        "globe": "globe",
        "ground": "ground",
        "information": "information",
        "visit": "visit",
        "northhighland": "northhighland",
        "com": "com",
        "connect": "connect",
        "LinkedIn": "LinkedIn",
        "Twitter": "Twitter",
        "Facebook": "Facebook",
        "Employment": "Employment",
        "Opportunity": "Opportunity",
        "EEO": "EEO",
        "Action": "Action",
        "employer": "employer",
        "applicants": "applicants",
        "fair": "fair",
        "consideration": "consideration",
        "regard": "regard",
        "race": "race",
        "color": "color",
        "sex": "sex",
        "gender": "gender",
        "identity": "identity",
        "religion": "religion",
        "origin": "origin",
        "age": "age",
        "orientation": "orientation",
        "disability": "disability",
        "veteran": "veteran",
        "status": "status",
        "law": "law",
        "Job": "Job",
        "DetailsJob": "DetailsJob",
        "Typefulltime": "Typefulltime",
        "employeePostedToday": "employeePostedToday"
      },
      "VERB": {
        "doing": "doing",
        "built": "built",
        "Do": "Do",
        "have": "have",
        "transform": "transform",
        "Think": "Think",
        "can": "can",
        "bring": "bring",
        "join": "join",
        "like": "like",
        "make": "make",
        "will": "will",
        "give": "give",
        "grow": "grow",
        "training": "training",
        "ll": "ll",
        "want": "want",
        "strive": "strive",
        "re": "re",
        "is": "is",
        "scale": "scale",
        "test": "test",
        "won": "won",
        "lose": "lose",
        "recognized": "recognized",
        "started": "started",
        "means": "means",
        "know": "know",
        "are": "are",
        "made": "made",
        "be": "be",
        "broken": "broken",
        "Want": "Want",
        "surprise": "surprise",
        "stretch": "stretch",
        "do": "do",
        "developing": "developing",
        "using": "using",
        "setting": "setting",
        "configuring": "configuring",
        "Delivering": "Delivering",
        "needed": "needed",
        "Working": "Working",
        "analyzing": "analyzing",
        "optimizing": "optimizing",
        "automating": "automating",
        "leading": "leading",
        "gained": "gained",
        "prioritize": "prioritize",
        "working": "working",
        "come": "come",
        "meet": "meet",
        "ensure": "ensure",
        "onboarding": "onboarding",
        "carry": "carry",
        "develop": "develop",
        "suggest": "suggest",
        "ensuring": "ensuring",
        "delivered": "delivered",
        "plan": "plan",
        "execute": "execute",
        "need": "need",
        "specializing": "specializing",
        "planning": "planning",
        "processes": "processes",
        "capture": "capture",
        "define": "define",
        "Leading": "Leading",
        "structured": "structured",
        "diagnose": "diagnose",
        "decide": "decide",
        "done": "done",
        "Intuitive": "Intuitive",
        "turned": "turned",
        "would": "would",
        "learning": "learning",
        "staying": "staying",
        "must": "must",
        "authorized": "authorized",
        "work": "work",
        "provided": "provided",
        "apply": "apply",
        "makes": "makes",
        "happen": "happen",
        "dare": "dare",
        "melding": "melding",
        "consulting": "consulting",
        "break": "break",
        "explore": "explore",
        "receive": "receive",
        "protected": "protected"
      },
      "ADJ": {
        "innovative": "innovative",
        "collaborative": "collaborative",
        "ve": "ve",
        "better": "better",
        "A-game": "A-game",
        "big": "big",
        "brain…Why": "brain…Why",
        "personal": "personal",
        "doesn": "doesn",
        "learn": "learn",
        "new": "new",
        "traditional": "traditional",
        "working": "working",
        "next": "next",
        "large": "large",
        "small": "small",
        "Which": "Which",
        "Exciting": "Exciting",
        "responsible": "responsible",
        "low-code": "low-code",
        "unique": "unique",
        "minimal": "minimal",
        "key": "key",
        "pre-built": "pre-built",
        "drag-and-drop": "drag-and-drop",
        "visual": "visual",
        "internal": "internal",
        "essential": "essential",
        "articulate": "articulate",
        "end": "end",
        "different": "different",
        "Establish": "Establish",
        "end-user": "end-user",
        "efficient": "efficient",
        "analyze": "analyze",
        "workflow": "workflow",
        "logical": "logical",
        "alternative": "alternative",
        "Overall": "Overall",
        "assigned": "assigned",
        "successful": "successful",
        "Technical": "Technical",
        "technical": "technical",
        "actual": "actual",
        "general": "general",
        "complex": "complex",
        "front": "front",
        "useful": "useful",
        "solution-oriented": "solution-oriented",
        "Cross-functional": "Cross-functional",
        "clear": "clear",
        "possible": "possible",
        "continuous": "continuous",
        "latest": "latest",
        "open-minded": "open-minded",
        "visa": "visa",
        "operational": "operational",
        "easier": "easier",
        "more": "more",
        "Equal": "Equal",
        "/Affirmative": "/Affirmative",
        "qualified": "qualified",
        "impartial": "impartial",
        "national": "national",
        "sexual": "sexual",
        "other": "other",
        "characteristic": "characteristic"
      },
      "PRT": {
        "to": "to",
        "off": "off",
        "up": "up",
        "'s": "'s",
        "out": "out"
      },
      "NUM": {
        "three": "three",
        "80/20": "80/20",
        "one": "one",
        "65+": "65+"
      }
    }
  },
  "223123867": {
    "Company": "Honeywell",
    "Job Title": "Advanced Software Engineer.",
    "Job Details": "DescriptionAdvanced Software Engineer Advanced Software Engineer for HoneywellInternational Inc|||| (Atlanta, GA)Responsibilities: Analyze requirements for different software components and subsystems|||| Create Test plans||||Evaluate tools and technologies appropriately for performance testing|||| Create best practices for performance engineering group|||| Develop performance testing framework for Honeywell Internet of things platform||||Develop test cases|||| Write code to Automate Test case with scripts||||Execute Software Scripts to capture performance metrics of different software components||||Integrate Software Testing Scripts into Build pipeline|||| Analyze test results|||| Identify performance bottle necks|||| Create Test reports||||Additional Information: Location: Atlanta, GA40 hours/weekEligible for Employee Referral ProgramIf offered employment must have legal right to work in U||||S|||| EOE||||Contact: HR Services, Honeywell International, Inc||||, 115 Tabor Road, Morris Plains, NJ 07950 Please reference: MS/SD # 256163Requirements:Master’sdegree or foreign equivalent in Computer Science or a related field and four(4) years of experience in the job offered or acceptable alternateoccupation||||  Full term of experience mustinclude: Shell scripting; C# or other high-level language; Python; Selenium; andJava|||| Experience must include: Creating load testing; Stress testing scripts;Jmeter; Locust; and performance and reliability engineering for cloud applicationsor platform||||Additional InformationJOB ID: req256163Category: EngineeringLocation: 715 Peachtree Street, N||||E||||,Atlanta,Georgia,30308,United StatesExemptHoneywell is an equal opportunity employer|||| Qualified applicants will be considered without regard to age, race, creed, color, national origin, ancestry, marital status, affectional or sexual orientation, gender identity or expression, disability, nationality, sex, or veteran status||||Job DetailsJob Typefulltime, employeePostedToday||||",
    "KeyWords": {
      "NOUN": {
        "Software": "Software",
        "Engineer": "Engineer",
        "Advanced": "Advanced",
        "HoneywellInternational": "HoneywellInternational",
        "Inc.": "Inc.",
        "Atlanta": "Atlanta",
        "GA": "GA",
        "Responsibilities": "Responsibilities",
        "Analyze": "Analyze",
        "requirements": "requirements",
        "software": "software",
        "components": "components",
        "subsystems": "subsystems",
        "Create": "Create",
        "Test": "Test",
        "Evaluate": "Evaluate",
        "tools": "tools",
        "technologies": "technologies",
        "performance": "performance",
        "testing": "testing",
        "practices": "practices",
        "engineering": "engineering",
        "group": "group",
        "Develop": "Develop",
        "framework": "framework",
        "Honeywell": "Honeywell",
        "Internet": "Internet",
        "things": "things",
        "platform": "platform",
        "test": "test",
        "cases": "cases",
        "Write": "Write",
        "code": "code",
        "Automate": "Automate",
        "case": "case",
        "scripts": "scripts",
        "Execute": "Execute",
        "Scripts": "Scripts",
        "metrics": "metrics",
        "Integrate": "Integrate",
        "Build": "Build",
        "pipeline": "pipeline",
        "results": "results",
        "Identify": "Identify",
        "bottle": "bottle",
        "necks": "necks",
        "reports": "reports",
        "Information": "Information",
        "Location": "Location",
        "GA40": "GA40",
        "hours/weekEligible": "hours/weekEligible",
        "Employee": "Employee",
        "Referral": "Referral",
        "ProgramIf": "ProgramIf",
        "employment": "employment",
        "right": "right",
        "U.": "U.",
        "S.": "S.",
        "EOE": "EOE",
        "Contact": "Contact",
        "HR": "HR",
        "Services": "Services",
        "International": "International",
        "Tabor": "Tabor",
        "Road": "Road",
        "Morris": "Morris",
        "Plains": "Plains",
        "NJ": "NJ",
        "Please": "Please",
        "reference": "reference",
        "MS/SD": "MS/SD",
        "256163Requirements": "256163Requirements",
        "Master": "Master",
        "equivalent": "equivalent",
        "Computer": "Computer",
        "Science": "Science",
        "field": "field",
        "years": "years",
        "experience": "experience",
        "job": "job",
        "alternateoccupation": "alternateoccupation",
        "Full": "Full",
        "term": "term",
        "mustinclude": "mustinclude",
        "Shell": "Shell",
        "language": "language",
        "Python": "Python",
        "Selenium": "Selenium",
        "andJava": "andJava",
        "Experience": "Experience",
        "Creating": "Creating",
        "load": "load",
        "Stress": "Stress",
        "Jmeter": "Jmeter",
        "Locust": "Locust",
        "reliability": "reliability",
        "cloud": "cloud",
        "applicationsor": "applicationsor",
        "InformationJOB": "InformationJOB",
        "ID": "ID",
        "req256163Category": "req256163Category",
        "EngineeringLocation": "EngineeringLocation",
        "Peachtree": "Peachtree",
        "Street": "Street",
        "N.": "N.",
        "E.": "E.",
        "Georgia,30308": "Georgia,30308",
        "United": "United",
        "StatesExemptHoneywell": "StatesExemptHoneywell",
        "opportunity": "opportunity",
        "employer": "employer",
        "applicants": "applicants",
        "regard": "regard",
        "age": "age",
        "race": "race",
        "creed": "creed",
        "color": "color",
        "origin": "origin",
        "ancestry": "ancestry",
        "status": "status",
        "orientation": "orientation",
        "gender": "gender",
        "identity": "identity",
        "expression": "expression",
        "disability": "disability",
        "nationality": "nationality",
        "sex": "sex",
        "veteran": "veteran",
        "Job": "Job",
        "DetailsJob": "DetailsJob",
        "Typefulltime": "Typefulltime",
        "employeePostedToday": "employeePostedToday"
      },
      "ADJ": {
        "best": "best",
        "different": "different",
        "Additional": "Additional",
        "legal": "legal",
        "foreign": "foreign",
        "related": "related",
        "acceptable": "acceptable",
        "other": "other",
        "high-level": "high-level",
        "equal": "equal",
        "national": "national",
        "marital": "marital",
        "affectional": "affectional",
        "sexual": "sexual"
      },
      "VERB": {
        "testing": "testing",
        "Develop": "Develop",
        "capture": "capture",
        "Testing": "Testing",
        "offered": "offered",
        "must": "must",
        "have": "have",
        "work": "work",
        "sdegree": "sdegree",
        "scripting": "scripting",
        "include": "include",
        "is": "is",
        "Qualified": "Qualified",
        "will": "will",
        "be": "be",
        "considered": "considered"
      },
      "PRT": {
        "to": "to"
      },
      "NUM": {
        "715": "715",
        "07950": "07950",
        "four": "four"
      }
    }
  },
  "223125080": {
    "Company": "Honeywell",
    "Job Title": "Software Engineer I",
    "Job Details": "DescriptionJoin a team recognized for leadership, innovation and diversityThe future is what you make it||||  When you join Honeywell, you become a member of our global team of thinkers, innovators, dreamers and doers who make the things that make the future|||| That means changing the way we fly, fueling jets in an eco-friendly way, keeping buildings smart and safe and even making it possible to breathe on Mars||||  Working at Honeywell isn't just about developing cool things|||| That’s why all of our employees enjoy access to dynamic career opportunities across different fields and industries||||  Are you ready to help us make the future?  Honeywell Building Technologies (HBT) is a strategic business unit within Honeywell Buildings||||  HBT innovates to protect and save lives worldwide every day||||  It is a global leader in commercial fire systems and commercial security products||||  Its quality products, integrated system solutions, and services make life safer, more comfortable, more secure, and more productive in every corner of our world||||  You can find leading-edge HBT technology all around you, including at airports, hotels, healthcare institutions, business centers, stadiums, industries, and schools||||  As a Software Engineer II, you’ll join a team that designs, develops, and integrates highly complex software applications within Honeywell|||| Being an active and integral member of a team to achieve the completion of goals, while also generating innovative solutions in work situations; trying different and novel ways to deal with problems and opportunities||||  Responsibilities include:   Involved in any or all the phases of the software developmentCustomer interaction; providing value-added software features to our productsElaborating the requirement to prototype, design, coding, testing, deploying, and supportWork within an agile development framework while collaborating with other senior developers in the teamSimplify the requirement and validate continuously for the course corrections and deliver it in phasesYOU MUST HAVE    Bachelor’s degree  6 months of software experience using C# and other Microsoft tools Due to work requirements, must be a US Citizen or Green Card holder WE VALUE   An analytical influencer with excellent communication and interpersonal skills and a positive attitude Experience in developing cloud-enabled applications with multiple front-ends using various development, debugging and troubleshooting tools/systems (C#, Blazor, React JS, jQuery, Git, HTML5, JavaScript, CSS, ||||Net Core, Web API, ADO||||Net, Docker, Containers, Kubernetes) Familiarity with continuous integration and delivery tools/practices (e||||g||||, Jenkins, Bamboo, Puppet, Chef) Experience with source control and bug tracking tools (e||||g||||, JIRA, BitBucket) Understanding of cloud infrastructure services (e||||g||||, Microsoft Azure ) Knowledge of relational databases and SQL Experience executing Agile software methodology Knowledge of test-driven development Diverse and global teaming and collaboration Experience with web application security and understanding of basic cryptography is a plus Ability to consistently make timely decisions even in the face of complexity, balancing systematic analysis with decisiveness Ability to convey subtle or complex messages clearly, as appropriate for the topic and audience Knowledge of security Access Control domain, product and technology     Additional InformationJOB ID: HRD107611Category: EngineeringLocation: 715 Peachtree Street, N||||E||||,Atlanta,Georgia,30308,United StatesExemptGlobal (ALL)Honeywell is an equal opportunity employer|||| Qualified applicants will be considered without regard to age, race, creed, color, national origin, ancestry, marital status, affectional or sexual orientation, gender identity or expression, disability, nationality, sex, or veteran status||||Job DetailsJob Typefulltime, employeePostedToday||||",
    "KeyWords": {
      "VERB": {
        "recognized": "recognized",
        "is": "is",
        "make": "make",
        "join": "join",
        "become": "become",
        "means": "means",
        "changing": "changing",
        "fly": "fly",
        "fueling": "fueling",
        "keeping": "keeping",
        "making": "making",
        "breathe": "breathe",
        "Working": "Working",
        "developing": "developing",
        "enjoy": "enjoy",
        "dynamic": "dynamic",
        "Are": "Are",
        "help": "help",
        "innovates": "innovates",
        "protect": "protect",
        "save": "save",
        "can": "can",
        "find": "find",
        "including": "including",
        "designs": "designs",
        "integrates": "integrates",
        "Being": "Being",
        "achieve": "achieve",
        "generating": "generating",
        "trying": "trying",
        "deal": "deal",
        "include": "include",
        "Involved": "Involved",
        "providing": "providing",
        "productsElaborating": "productsElaborating",
        "prototype": "prototype",
        "testing": "testing",
        "deploying": "deploying",
        "collaborating": "collaborating",
        "deliver": "deliver",
        "using": "using",
        "work": "work",
        "must": "must",
        "be": "be",
        "debugging": "debugging",
        "troubleshooting": "troubleshooting",
        "executing": "executing",
        "balancing": "balancing",
        "convey": "convey",
        "Qualified": "Qualified",
        "will": "will",
        "considered": "considered"
      },
      "NOUN": {
        "leadership": "leadership",
        "innovation": "innovation",
        "future": "future",
        "Honeywell": "Honeywell",
        "member": "member",
        "team": "team",
        "thinkers": "thinkers",
        "innovators": "innovators",
        "dreamers": "dreamers",
        "doers": "doers",
        "things": "things",
        "way": "way",
        "jets": "jets",
        "buildings": "buildings",
        "smart": "smart",
        "Mars": "Mars",
        "employees": "employees",
        "access": "access",
        "career": "career",
        "opportunities": "opportunities",
        "fields": "fields",
        "industries": "industries",
        "Building": "Building",
        "Technologies": "Technologies",
        "HBT": "HBT",
        "business": "business",
        "unit": "unit",
        "Buildings": "Buildings",
        "lives": "lives",
        "day": "day",
        "leader": "leader",
        "fire": "fire",
        "systems": "systems",
        "security": "security",
        "products": "products",
        "quality": "quality",
        "system": "system",
        "solutions": "solutions",
        "services": "services",
        "life": "life",
        "safer": "safer",
        "secure": "secure",
        "corner": "corner",
        "world": "world",
        "technology": "technology",
        "airports": "airports",
        "hotels": "hotels",
        "healthcare": "healthcare",
        "institutions": "institutions",
        "centers": "centers",
        "stadiums": "stadiums",
        "schools": "schools",
        "Software": "Software",
        "Engineer": "Engineer",
        "II": "II",
        "join": "join",
        "develops": "develops",
        "software": "software",
        "applications": "applications",
        "completion": "completion",
        "goals": "goals",
        "work": "work",
        "situations": "situations",
        "ways": "ways",
        "problems": "problems",
        "Responsibilities": "Responsibilities",
        "phases": "phases",
        "interaction": "interaction",
        "features": "features",
        "requirement": "requirement",
        "design": "design",
        "coding": "coding",
        "supportWork": "supportWork",
        "agile": "agile",
        "development": "development",
        "framework": "framework",
        "developers": "developers",
        "teamSimplify": "teamSimplify",
        "validate": "validate",
        "course": "course",
        "corrections": "corrections",
        "phasesYOU": "phasesYOU",
        "MUST": "MUST",
        "HAVE": "HAVE",
        "Bachelor": "Bachelor",
        "months": "months",
        "experience": "experience",
        "Microsoft": "Microsoft",
        "tools": "tools",
        "Due": "Due",
        "requirements": "requirements",
        "US": "US",
        "Citizen": "Citizen",
        "Green": "Green",
        "Card": "Card",
        "holder": "holder",
        "WE": "WE",
        "VALUE": "VALUE",
        "influencer": "influencer",
        "communication": "communication",
        "skills": "skills",
        "attitude": "attitude",
        "Experience": "Experience",
        "front-ends": "front-ends",
        "tools/systems": "tools/systems",
        "Blazor": "Blazor",
        "React": "React",
        "JS": "JS",
        "jQuery": "jQuery",
        "Git": "Git",
        "HTML5": "HTML5",
        "JavaScript": "JavaScript",
        "CSS": "CSS",
        "Core": "Core",
        "Web": "Web",
        "API": "API",
        "ADO": "ADO",
        "Net": "Net",
        "Docker": "Docker",
        "Containers": "Containers",
        "Kubernetes": "Kubernetes",
        "Familiarity": "Familiarity",
        "integration": "integration",
        "delivery": "delivery",
        "tools/practices": "tools/practices",
        "g.": "g.",
        "Jenkins": "Jenkins",
        "Bamboo": "Bamboo",
        "Puppet": "Puppet",
        "Chef": "Chef",
        "source": "source",
        "control": "control",
        "bug": "bug",
        "tracking": "tracking",
        "JIRA": "JIRA",
        "BitBucket": "BitBucket",
        "Understanding": "Understanding",
        "infrastructure": "infrastructure",
        "Azure": "Azure",
        "Knowledge": "Knowledge",
        "databases": "databases",
        "SQL": "SQL",
        "Agile": "Agile",
        "methodology": "methodology",
        "Diverse": "Diverse",
        "teaming": "teaming",
        "collaboration": "collaboration",
        "application": "application",
        "understanding": "understanding",
        "cryptography": "cryptography",
        "Ability": "Ability",
        "decisions": "decisions",
        "face": "face",
        "complexity": "complexity",
        "analysis": "analysis",
        "messages": "messages",
        "appropriate": "appropriate",
        "topic": "topic",
        "audience": "audience",
        "Access": "Access",
        "Control": "Control",
        "domain": "domain",
        "product": "product",
        "Additional": "Additional",
        "InformationJOB": "InformationJOB",
        "ID": "ID",
        "HRD107611Category": "HRD107611Category",
        "EngineeringLocation": "EngineeringLocation",
        "Peachtree": "Peachtree",
        "Street": "Street",
        "N.": "N.",
        "E.": "E.",
        "Atlanta": "Atlanta",
        "Georgia,30308": "Georgia,30308",
        "United": "United",
        "StatesExemptGlobal": "StatesExemptGlobal",
        "ALL": "ALL",
        "opportunity": "opportunity",
        "employer": "employer",
        "applicants": "applicants",
        "regard": "regard",
        "age": "age",
        "race": "race",
        "creed": "creed",
        "color": "color",
        "origin": "origin",
        "ancestry": "ancestry",
        "status": "status",
        "orientation": "orientation",
        "gender": "gender",
        "identity": "identity",
        "expression": "expression",
        "disability": "disability",
        "nationality": "nationality",
        "sex": "sex",
        "veteran": "veteran",
        "Job": "Job",
        "DetailsJob": "DetailsJob",
        "Typefulltime": "Typefulltime",
        "employeePostedToday": "employeePostedToday"
      },
      "ADJ": {
        "global": "global",
        "eco-friendly": "eco-friendly",
        "safe": "safe",
        "possible": "possible",
        "cool": "cool",
        "different": "different",
        "ready": "ready",
        "strategic": "strategic",
        "worldwide": "worldwide",
        "commercial": "commercial",
        "integrated": "integrated",
        "comfortable": "comfortable",
        "productive": "productive",
        "leading-edge": "leading-edge",
        "ll": "ll",
        "complex": "complex",
        "active": "active",
        "integral": "integral",
        "innovative": "innovative",
        "novel": "novel",
        "developmentCustomer": "developmentCustomer",
        "value-added": "value-added",
        "other": "other",
        "senior": "senior",
        "degree": "degree",
        "analytical": "analytical",
        "excellent": "excellent",
        "interpersonal": "interpersonal",
        "positive": "positive",
        "cloud-enabled": "cloud-enabled",
        "multiple": "multiple",
        "various": "various",
        "Net": "Net",
        "continuous": "continuous",
        "e.": "e.",
        "cloud": "cloud",
        "relational": "relational",
        "test-driven": "test-driven",
        "web": "web",
        "basic": "basic",
        "plus": "plus",
        "timely": "timely",
        "systematic": "systematic",
        "decisiveness": "decisiveness",
        "subtle": "subtle",
        "equal": "equal",
        "national": "national",
        "marital": "marital",
        "affectional": "affectional",
        "sexual": "sexual"
      },
      "PRT": {
        "to": "to"
      },
      "NUM": {}
    }
  },
  "223160715": {
    "Company": "ABBTECH Professional Resources",
    "Job Title": "Bus Programmer Analyst II (Statistical Programmer)",
    "Job Details": "",
    "KeyWords": {}
  },
  "223207485": {
    "Company": "Enhance IT",
    "Job Title": "Entry Level Data Engineer Analyst / Python Developer",
    "Job Details": "DescriptionWho We Are: Enhance IT is an IT/Management firm that specializes in training, placement and IT consultation|||| We are an industry leader in providing top-level skilled and experienced consultants in a variety of technologies to meet our client’s needs in today’s fast paced environment||||  What you will be doing: You will be joining our ever-expanding data scientist team as it grows to meet the needs of the market|||| We want individuals who think “outside the box” and are comfortable asking “why?” The ideal candidate for this role is highly analytical with a knack for analysis, math and statistics|||| They are a team player possessing critical thinking and problem-solving skills with a passion for machine-learning and research|||| They need to possess the technical skills to explain the “how” and “what” behind technical decisions to non-tech stakeholders|||| What you need for this position: Master's degree from an accredited college/university in Computer Science, Statistics, Mathematics, Engineering, Econometrics, or related fields, PhD is preferred|||| Alternatively, Bachelor’s Degree with at least 2 years’ experience as a Data Analyst, Data Scientist, or Research Assistant|||| Strong Proficiency in Python or Java programming language, or expertise with functional/object-oriented programming|||| Ability to translate objectives to a project plan with milestones, and resource/technology requirements, and teach, lead, and manage projects/people/clients to successful execution|||| Ability to work across multiple engagements with clients to assess needs, provide assistance, and resolve problems, using structured problem solving and communication to both technical and non-technical audiences|||| Availability to travel and live in the U||||S||||Bonus points: Experience with command-line scripting, data structures and algorithms and ability to work in a Linux environment, processing large amounts of data in a cloud environment|||| Experience in machine learning, artificial intelligence and/or artificial neural networks|||| Proficiency in applying various mathematical and statistical models to include, but not limited to: discrete event simulation, factor analysis, genetic algorithms, Bayesian probability models, hidden Markov models, sensitivity analysis, sampling, probability, multivariate data analysis, regression, PCA, time-series analysis|||| Broad understanding of databases (e||||g|||| SQL, NoSQL, Lucene, Mongo), and high-performance or distributed processing (e||||g|||| using MapReduce, Spark, Pig, and/or Hive)|||| Experience with visualization software (Tableau, D3, MicroStrategy, PowerBI)||||  Experience delivering solutions in an Agile environment|||| Experience with Tensorflow, Theano or Keras|||| Portfolio of public & private data science projects you’re proud of (GitHub, Kaggle, DrivenData, etc||||) Publications in peer-reviewed journals|||| Other programming languages such as Scala, Java, R Benefits & PerksFull benefits including Medical/Dental/VisionPaid travel to and from the Atlanta HQPaid Time Off401(k) savings planPaid training in Atlanta, GA prior to going on live projectsJob DetailsJob Typefulltime, employeePosted 3 days ago||||",
    "KeyWords": {
      "VERB": {
        "is": "is",
        "specializes": "specializes",
        "are": "are",
        "providing": "providing",
        "skilled": "skilled",
        "meet": "meet",
        "will": "will",
        "be": "be",
        "doing": "doing",
        "joining": "joining",
        "grows": "grows",
        "want": "want",
        "think": "think",
        "asking": "asking",
        "possessing": "possessing",
        "need": "need",
        "possess": "possess",
        "explain": "explain",
        "preferred": "preferred",
        "translate": "translate",
        "work": "work",
        "assess": "assess",
        "provide": "provide",
        "resolve": "resolve",
        "using": "using",
        "structured": "structured",
        "solving": "solving",
        "travel": "travel",
        "live": "live",
        "processing": "processing",
        "applying": "applying",
        "include": "include",
        "sampling": "sampling",
        "distributed": "distributed",
        "delivering": "delivering",
        "programming": "programming",
        "including": "including",
        "planPaid": "planPaid",
        "going": "going",
        "employeePosted": "employeePosted"
      },
      "NOUN": {
        "IT": "IT",
        "firm": "firm",
        "training": "training",
        "placement": "placement",
        "consultation": "consultation",
        "industry": "industry",
        "leader": "leader",
        "top-level": "top-level",
        "consultants": "consultants",
        "variety": "variety",
        "technologies": "technologies",
        "client": "client",
        "needs": "needs",
        "today": "today",
        "environment": "environment",
        "data": "data",
        "scientist": "scientist",
        "team": "team",
        "market": "market",
        "individuals": "individuals",
        "box": "box",
        "candidate": "candidate",
        "role": "role",
        "knack": "knack",
        "analysis": "analysis",
        "math": "math",
        "statistics": "statistics",
        "player": "player",
        "thinking": "thinking",
        "skills": "skills",
        "passion": "passion",
        "research": "research",
        "decisions": "decisions",
        "stakeholders": "stakeholders",
        "position": "position",
        "Master": "Master",
        "degree": "degree",
        "college/university": "college/university",
        "Computer": "Computer",
        "Science": "Science",
        "Statistics": "Statistics",
        "Mathematics": "Mathematics",
        "Engineering": "Engineering",
        "Econometrics": "Econometrics",
        "fields": "fields",
        "PhD": "PhD",
        "Bachelor": "Bachelor",
        "Degree": "Degree",
        "years": "years",
        "experience": "experience",
        "Data": "Data",
        "Analyst": "Analyst",
        "Scientist": "Scientist",
        "Research": "Research",
        "Assistant": "Assistant",
        "Strong": "Strong",
        "Proficiency": "Proficiency",
        "Python": "Python",
        "Java": "Java",
        "language": "language",
        "expertise": "expertise",
        "programming": "programming",
        "Ability": "Ability",
        "objectives": "objectives",
        "project": "project",
        "plan": "plan",
        "milestones": "milestones",
        "resource/technology": "resource/technology",
        "requirements": "requirements",
        "teach": "teach",
        "lead": "lead",
        "manage": "manage",
        "projects/people/clients": "projects/people/clients",
        "execution": "execution",
        "engagements": "engagements",
        "clients": "clients",
        "assistance": "assistance",
        "problems": "problems",
        "problem": "problem",
        "communication": "communication",
        "audiences": "audiences",
        "Availability": "Availability",
        "U.": "U.",
        "S.": "S.",
        "Bonus": "Bonus",
        "points": "points",
        "Experience": "Experience",
        "scripting": "scripting",
        "structures": "structures",
        "algorithms": "algorithms",
        "ability": "ability",
        "Linux": "Linux",
        "amounts": "amounts",
        "cloud": "cloud",
        "machine": "machine",
        "learning": "learning",
        "intelligence": "intelligence",
        "networks": "networks",
        "models": "models",
        "event": "event",
        "simulation": "simulation",
        "factor": "factor",
        "probability": "probability",
        "Markov": "Markov",
        "sensitivity": "sensitivity",
        "multivariate": "multivariate",
        "regression": "regression",
        "PCA": "PCA",
        "Broad": "Broad",
        "understanding": "understanding",
        "databases": "databases",
        "g.": "g.",
        "SQL": "SQL",
        "NoSQL": "NoSQL",
        "Lucene": "Lucene",
        "Mongo": "Mongo",
        "high-performance": "high-performance",
        "processing": "processing",
        "MapReduce": "MapReduce",
        "Spark": "Spark",
        "Pig": "Pig",
        "Hive": "Hive",
        "visualization": "visualization",
        "software": "software",
        "Tableau": "Tableau",
        "D3": "D3",
        "MicroStrategy": "MicroStrategy",
        "PowerBI": "PowerBI",
        "solutions": "solutions",
        "Agile": "Agile",
        "Tensorflow": "Tensorflow",
        "Theano": "Theano",
        "Keras": "Keras",
        "Portfolio": "Portfolio",
        "science": "science",
        "projects": "projects",
        "proud": "proud",
        "GitHub": "GitHub",
        "Kaggle": "Kaggle",
        "DrivenData": "DrivenData",
        "Publications": "Publications",
        "journals": "journals",
        "languages": "languages",
        "Scala": "Scala",
        "Benefits": "Benefits",
        "PerksFull": "PerksFull",
        "benefits": "benefits",
        "Medical/Dental/VisionPaid": "Medical/Dental/VisionPaid",
        "travel": "travel",
        "Atlanta": "Atlanta",
        "HQPaid": "HQPaid",
        "Time": "Time",
        "Off401": "Off401",
        "savings": "savings",
        "GA": "GA",
        "projectsJob": "projectsJob",
        "DetailsJob": "DetailsJob",
        "Typefulltime": "Typefulltime",
        "days": "days"
      },
      "ADJ": {
        "experienced": "experienced",
        "paced": "paced",
        "ever-expanding": "ever-expanding",
        "comfortable": "comfortable",
        "ideal": "ideal",
        "analytical": "analytical",
        "critical": "critical",
        "problem-solving": "problem-solving",
        "machine-learning": "machine-learning",
        "technical": "technical",
        "non-tech": "non-tech",
        "accredited": "accredited",
        "related": "related",
        "least": "least",
        "programming": "programming",
        "functional/object-oriented": "functional/object-oriented",
        "successful": "successful",
        "multiple": "multiple",
        "non-technical": "non-technical",
        "command-line": "command-line",
        "large": "large",
        "artificial": "artificial",
        "and/or": "and/or",
        "neural": "neural",
        "various": "various",
        "mathematical": "mathematical",
        "statistical": "statistical",
        "limited": "limited",
        "discrete": "discrete",
        "genetic": "genetic",
        "Bayesian": "Bayesian",
        "hidden": "hidden",
        "time-series": "time-series",
        "e.": "e.",
        "public": "public",
        "private": "private",
        "re": "re",
        "peer-reviewed": "peer-reviewed",
        "Other": "Other",
        "such": "such",
        "live": "live"
      },
      "PRT": {
        "to": "to",
        "'s": "'s"
      },
      "X": {}
    }
  },
  "223235358": {
    "Company": "ADP Technology Services, Inc.",
    "Job Title": "Senior Application Developer",
    "Job Details": "DescriptionIT: ADP Technology Services, Inc|||| seeks a Senior Application Developer at our Alpharetta, GA loc|||| to participate in the SDLC incl|||| planning, construction, testing, reviews, & demonstrations|||| Bach’s deg in Comp|||| Sci||||, Info|||| Sys||||, Elec|||| Engg|||| or a rel|||| field + 5 yrs of related exp|||| 2 yrs of exp must incl||||: Java/J2EE; JavaScript; Angular JS; Groovy; Webservices, incl|||| REST & SOAP; Spring & Hibernate; Oracle SQL Developer; JAXB; JAVA Applet; SCSS; Swagger; & JUnit|||| To apply, please respond to req|||| 196497 at http://jobs||||adp||||com|||| Alternatively, applicants may mail their resume to the following address referencing req|||| 196497: Employment Practices, 1 ADP Blvd||||, MS 248, Roseland, NJ 07068||||Job DetailsJob Typefulltime, employeePosted 1 Day ago||||",
    "KeyWords": {
      "NOUN": {
        "ADP": "ADP",
        "Technology": "Technology",
        "Services": "Services",
        "Inc.": "Inc.",
        "Application": "Application",
        "Developer": "Developer",
        "Alpharetta": "Alpharetta",
        "GA": "GA",
        "loc": "loc",
        "SDLC": "SDLC",
        "incl": "incl",
        "planning": "planning",
        "construction": "construction",
        "reviews": "reviews",
        "demonstrations": "demonstrations",
        "Bach": "Bach",
        "deg": "deg",
        "Comp": "Comp",
        "Sci": "Sci",
        "Info": "Info",
        "Sys": "Sys",
        "Elec": "Elec",
        "Engg": "Engg",
        "rel": "rel",
        "field": "field",
        "yrs": "yrs",
        "exp": "exp",
        "Java/J2EE": "Java/J2EE",
        "JavaScript": "JavaScript",
        "Angular": "Angular",
        "JS": "JS",
        "Groovy": "Groovy",
        "Webservices": "Webservices",
        "REST": "REST",
        "SOAP": "SOAP",
        "Spring": "Spring",
        "Hibernate": "Hibernate",
        "Oracle": "Oracle",
        "SQL": "SQL",
        "JAXB": "JAXB",
        "JAVA": "JAVA",
        "Applet": "Applet",
        "SCSS": "SCSS",
        "Swagger": "Swagger",
        "JUnit": "JUnit",
        "respond": "respond",
        "http": "http",
        "//jobs": "//jobs",
        "adp": "adp",
        "com": "com",
        "applicants": "applicants",
        "resume": "resume",
        "address": "address",
        "req": "req",
        "Employment": "Employment",
        "Practices": "Practices",
        "Blvd": "Blvd",
        "MS": "MS",
        "Roseland": "Roseland",
        "NJ": "NJ",
        "Job": "Job",
        "DetailsJob": "DetailsJob",
        "Typefulltime": "Typefulltime",
        "Day": "Day"
      },
      "VERB": {
        "participate": "participate",
        "testing": "testing",
        "must": "must",
        "incl": "incl",
        "apply": "apply",
        "please": "please",
        "req": "req",
        "may": "may",
        "mail": "mail",
        "referencing": "referencing",
        "employeePosted": "employeePosted"
      },
      "ADJ": {
        "related": "related",
        "following": "following"
      },
      "PRT": {
        "To": "To",
        "to": "to"
      },
      "NUM": {
        "248": "248",
        "196497": "196497",
        "07068": "07068"
      }
    }
  },
  "223247056": {
    "Company": "Applied Resource Group",
    "Job Title": "Sr. .NET Software Engineer",
    "Job Details": "DescriptionSummary:We are looking for a Senior Software Developer to help drive the design, development and delivery of enterprise level software applications to our clients|||| You will be hands-on in the development of new and existing C# components to support customers throughout the Atlanta, GA market||||Duties and Responsibilities - Software EngineerImplement new and existing software in C#,||||NET, Javascript, Angular||||JS & React||||JS to support the delivery of our best-in-class software applications to customers||||Exercise passion for meeting the highest standard of engineering quality by developing elegant designs and writing clean, precise code||||Analyzes, designs, and programs viable solutions of medium to highly complex business problems defined by user requirementsReviews detailed functional specifications from the user communityDevelop time estimates for project schedulesProvides technical assistance to other developers and systems analysts when neededWork on multiple high priority projects concurrentlyEmploy productivity aids in all aspects of assignmentsMaintain and enhances technical skills through formal and on-the-job trainingWork in a broad range of technologies ranging from graphics systems, networking and protocols, encryption and security, hardware and drivers, as well as tool and SDK standardsAll other duties as assignedRequirements - Senior Software Developer position:Advanced to Expert level C# & ||||NET skillsSolid query writing capabilities in MS SQL2-5 years of commercial development experience with an emphasis on delivering libraries and frameworks within the tech fieldPossible hire for 5+ year Senior-Level engineer looking to go to support Junior and Mid-Tier developers to the next level||||NET client application experienceSoftware development experience with object-oriented design||||Knowledge of software engineering best practices, including design patterns and UML||||Must possess good analytical, problem solving, and debugging skills||||Experience with the full product development lifecycle and multiple releases of enterprise-class software productsDemonstrates excellent oral and written, communication, and customer service skills||||Demonstrates an extremely high level of accuracy and attention to detail||||Ability to work independently and be team oriented||||A Bachelor’s degree in Computer Science, Engineering, a related field, or its equivalent is preferredJob DetailsSalary$100000 - $125000 Per YearJob Typefulltime, employeePosted 8 days ago||||",
    "KeyWords": {
      "ADJ": {
        "hands-on": "hands-on",
        "new": "new",
        "highest": "highest",
        "elegant": "elegant",
        "clean": "clean",
        "precise": "precise",
        "viable": "viable",
        "complex": "complex",
        "user": "user",
        "functional": "functional",
        "technical": "technical",
        "other": "other",
        "multiple": "multiple",
        "high": "high",
        "formal": "formal",
        "on-the-job": "on-the-job",
        "broad": "broad",
        "Advanced": "Advanced",
        "NET": "NET",
        "skillsSolid": "skillsSolid",
        "commercial": "commercial",
        "fieldPossible": "fieldPossible",
        "next": "next",
        "object-oriented": "object-oriented",
        "best": "best",
        "good": "good",
        "analytical": "analytical",
        "full": "full",
        "excellent": "excellent",
        "oral": "oral",
        "related": "related",
        "preferredJob": "preferredJob"
      },
      "VERB": {
        "looking": "looking",
        "help": "help",
        "drive": "drive",
        "will": "will",
        "be": "be",
        "existing": "existing",
        "support": "support",
        "meeting": "meeting",
        "developing": "developing",
        "writing": "writing",
        "designs": "designs",
        "defined": "defined",
        "detailed": "detailed",
        "schedulesProvides": "schedulesProvides",
        "concurrentlyEmploy": "concurrentlyEmploy",
        "enhances": "enhances",
        "ranging": "ranging",
        "networking": "networking",
        "standardsAll": "standardsAll",
        "delivering": "delivering",
        "go": "go",
        "including": "including",
        "debugging": "debugging",
        "productsDemonstrates": "productsDemonstrates",
        "written": "written",
        "Demonstrates": "Demonstrates",
        "detail": "detail",
        "work": "work",
        "oriented": "oriented",
        "is": "is",
        "employeePosted": "employeePosted"
      },
      "NOUN": {
        "Software": "Software",
        "Developer": "Developer",
        "design": "design",
        "development": "development",
        "delivery": "delivery",
        "enterprise": "enterprise",
        "level": "level",
        "software": "software",
        "applications": "applications",
        "clients": "clients",
        "components": "components",
        "customers": "customers",
        "Atlanta": "Atlanta",
        "GA": "GA",
        "market": "market",
        "Duties": "Duties",
        "Responsibilities": "Responsibilities",
        "EngineerImplement": "EngineerImplement",
        "NET": "NET",
        "Javascript": "Javascript",
        "Angular": "Angular",
        "JS": "JS",
        "React": "React",
        "best-in-class": "best-in-class",
        "Exercise": "Exercise",
        "passion": "passion",
        "standard": "standard",
        "engineering": "engineering",
        "quality": "quality",
        "designs": "designs",
        "code": "code",
        "Analyzes": "Analyzes",
        "programs": "programs",
        "solutions": "solutions",
        "medium": "medium",
        "business": "business",
        "problems": "problems",
        "requirementsReviews": "requirementsReviews",
        "specifications": "specifications",
        "user": "user",
        "communityDevelop": "communityDevelop",
        "time": "time",
        "estimates": "estimates",
        "project": "project",
        "assistance": "assistance",
        "developers": "developers",
        "systems": "systems",
        "analysts": "analysts",
        "neededWork": "neededWork",
        "priority": "priority",
        "projects": "projects",
        "productivity": "productivity",
        "aids": "aids",
        "aspects": "aspects",
        "assignmentsMaintain": "assignmentsMaintain",
        "skills": "skills",
        "trainingWork": "trainingWork",
        "range": "range",
        "technologies": "technologies",
        "graphics": "graphics",
        "protocols": "protocols",
        "encryption": "encryption",
        "security": "security",
        "hardware": "hardware",
        "drivers": "drivers",
        "tool": "tool",
        "SDK": "SDK",
        "duties": "duties",
        "assignedRequirements": "assignedRequirements",
        "Senior": "Senior",
        "position": "position",
        "Expert": "Expert",
        "query": "query",
        "capabilities": "capabilities",
        "MS": "MS",
        "SQL2-5": "SQL2-5",
        "years": "years",
        "experience": "experience",
        "emphasis": "emphasis",
        "libraries": "libraries",
        "frameworks": "frameworks",
        "tech": "tech",
        "hire": "hire",
        "year": "year",
        "Senior-Level": "Senior-Level",
        "engineer": "engineer",
        "Junior": "Junior",
        "Mid-Tier": "Mid-Tier",
        "client": "client",
        "application": "application",
        "experienceSoftware": "experienceSoftware",
        "Knowledge": "Knowledge",
        "practices": "practices",
        "patterns": "patterns",
        "UML": "UML",
        "Must": "Must",
        "problem": "problem",
        "solving": "solving",
        "Experience": "Experience",
        "product": "product",
        "lifecycle": "lifecycle",
        "releases": "releases",
        "enterprise-class": "enterprise-class",
        "communication": "communication",
        "customer": "customer",
        "service": "service",
        "accuracy": "accuracy",
        "attention": "attention",
        "Ability": "Ability",
        "team": "team",
        "Bachelor": "Bachelor",
        "degree": "degree",
        "Computer": "Computer",
        "Science": "Science",
        "Engineering": "Engineering",
        "field": "field",
        "equivalent": "equivalent",
        "DetailsSalary": "DetailsSalary",
        "Per": "Per",
        "YearJob": "YearJob",
        "Typefulltime": "Typefulltime",
        "days": "days"
      },
      "PRT": {
        "to": "to"
      },
      "NUM": {
        "100000": "100000",
        "125000": "125000"
      }
    }
  },
  "223249455": {
    "Company": "The Judge Group",
    "Job Title": "Genesys IVR Developer w/ Java/J2EE (679964)",
    "Job Details": "DescriptionLocation:  Atlanta, GASalary:  Salaried Employment positionDescription:  Our client is currently seeking a Genesys IVR Developer w/ Java/J2EE (679964) for a Full time Perm Employment position contact Brian at 732||||497||||4294, bkubiak@judge||||com8+ Years’ Experience working in IVR with 5 - 6 + years in Genesys|||| Hands-on experience with coding using Genesys IVR tools||||Experience in coding using Java/J2EE to customize code generated from Genesys tool||||This is a highly technical position for someone who can dive deep, build complex, Genesys routines||||Broad responsibilities include owning the technical engagement and ultimate success around specific implementation projects|||| Experience working with deployment pipelinesDesign, Develop and Implement Genesys IVR toolJava/J2EE coding experienceAgile environment Work independentlyOwn code end-to-end from design to development, and work closely with senior technical leaders within the team Sound understanding of computer science fundamentals and practical industry experience|||| Domain:BFS – Contact CenterBrian K|||| Kubiak,Sr|||| Technical Recruiter, The Judge GroupDirect Dial: 732||||497||||4294 | Email: bkubiak@judge||||comlinkedin||||com/in/brian-k-kubiak-3593983Celebrating 50 Years of SuccessClick to learn more about Judge’s Technology, Talent & Learning SolutionsContact:bkubiak@judge||||comThis job and many more are available through The Judge Group|||| Find us on the web at www||||judge||||comJob DetailsJob Typefulltime, employeePosted 8 days ago||||",
    "KeyWords": {
      "NOUN": {
        "Atlanta": "Atlanta",
        "GASalary": "GASalary",
        "positionDescription": "positionDescription",
        "client": "client",
        "Genesys": "Genesys",
        "IVR": "IVR",
        "Developer": "Developer",
        "w/": "w/",
        "Java/J2EE": "Java/J2EE",
        "Full": "Full",
        "time": "time",
        "Perm": "Perm",
        "Employment": "Employment",
        "position": "position",
        "contact": "contact",
        "Brian": "Brian",
        "bkubiak": "bkubiak",
        "judge": "judge",
        "Years": "Years",
        "Experience": "Experience",
        "years": "years",
        "experience": "experience",
        "tools": "tools",
        "code": "code",
        "tool": "tool",
        "someone": "someone",
        "complex": "complex",
        "routines": "routines",
        "Broad": "Broad",
        "responsibilities": "responsibilities",
        "engagement": "engagement",
        "success": "success",
        "implementation": "implementation",
        "projects": "projects",
        "pipelinesDesign": "pipelinesDesign",
        "Develop": "Develop",
        "Implement": "Implement",
        "toolJava/J2EE": "toolJava/J2EE",
        "environment": "environment",
        "Work": "Work",
        "independentlyOwn": "independentlyOwn",
        "end-to-end": "end-to-end",
        "design": "design",
        "development": "development",
        "work": "work",
        "leaders": "leaders",
        "team": "team",
        "Sound": "Sound",
        "understanding": "understanding",
        "computer": "computer",
        "science": "science",
        "fundamentals": "fundamentals",
        "industry": "industry",
        "Domain": "Domain",
        "BFS": "BFS",
        "Contact": "Contact",
        "CenterBrian": "CenterBrian",
        "K.": "K.",
        "Kubiak": "Kubiak",
        "Sr": "Sr",
        "Technical": "Technical",
        "Recruiter": "Recruiter",
        "Judge": "Judge",
        "GroupDirect": "GroupDirect",
        "Dial": "Dial",
        "Email": "Email",
        "comlinkedin": "comlinkedin",
        "SuccessClick": "SuccessClick",
        "Technology": "Technology",
        "Talent": "Talent",
        "Learning": "Learning",
        "SolutionsContact": "SolutionsContact",
        "job": "job",
        "Group": "Group",
        "Find": "Find",
        "web": "web",
        "www": "www",
        "DetailsJob": "DetailsJob",
        "Typefulltime": "Typefulltime",
        "days": "days"
      },
      "ADJ": {
        "Employment": "Employment",
        "com8+": "com8+",
        "Hands-on": "Hands-on",
        "technical": "technical",
        "deep": "deep",
        "build": "build",
        "ultimate": "ultimate",
        "specific": "specific",
        "deployment": "deployment",
        "experienceAgile": "experienceAgile",
        "senior": "senior",
        "practical": "practical",
        "com/in/brian-k-kubiak-3593983Celebrating": "com/in/brian-k-kubiak-3593983Celebrating",
        "more": "more",
        "comThis": "comThis",
        "many": "many",
        "available": "available",
        "comJob": "comJob"
      },
      "VERB": {
        "seeking": "seeking",
        "working": "working",
        "coding": "coding",
        "using": "using",
        "customize": "customize",
        "generated": "generated",
        "is": "is",
        "can": "can",
        "dive": "dive",
        "include": "include",
        "owning": "owning",
        "learn": "learn",
        "are": "are",
        "employeePosted": "employeePosted"
      },
      "NUM": {
        "50": "50",
        "497": "497",
        "732": "732",
        "4294": "4294"
      },
      "PRT": {
        "to": "to"
      }
    }
  },
  "223265138": {
    "Company": "Infinite Computer Solutions Inc",
    "Job Title": "Developer - Amazon Connect Work",
    "Job Details": "DescriptionDeveloper - Amazon Connect Work Location: Atlanta, GA (Remote Until COVID)Duration: 6 - 12 months      Positions Requested : 1 Required Skills: Please see the below skill requirements|||| It doesn't have to be a senior developer as long as the person has the right skill set listed below||||Good experience in developing IVR applications using AWS services - Amazon Connect, Lex, Lambda and DynamoDB services|||| This is a mandatory requirement||||Good hands-on programming skills in Java and NodeJS|||| This is a mandatory requirement||||Programming skills in Python is preferred||||Should have good communication and analytical skills||||Should have willingness to learn new skills, be flexible and take full ownership of the assigned tasks||||++++++++++++++++++++++++++++++++++++++++++++++++++++++++++++++++++++++++++++++++Infinite is proud to be an equal opportunity workplace and is an affirmative action employer||||-Regards,Kushagra Shuklakushagra||||shukla@infinite||||comConnect/Follow me here: https://www||||linkedin||||com/in/shuklakushagra1994/Job DetailsJob Typefulltime, employeePosted 7 days ago||||",
    "KeyWords": {
      "NOUN": {
        "Amazon": "Amazon",
        "Connect": "Connect",
        "Work": "Work",
        "Location": "Location",
        "Atlanta": "Atlanta",
        "GA": "GA",
        "Remote": "Remote",
        "COVID": "COVID",
        "Duration": "Duration",
        "months": "months",
        "Positions": "Positions",
        "Required": "Required",
        "Skills": "Skills",
        "Please": "Please",
        "below": "below",
        "skill": "skill",
        "requirements": "requirements",
        "developer": "developer",
        "person": "person",
        "right": "right",
        "experience": "experience",
        "IVR": "IVR",
        "applications": "applications",
        "AWS": "AWS",
        "services": "services",
        "Lex": "Lex",
        "Lambda": "Lambda",
        "DynamoDB": "DynamoDB",
        "requirement": "requirement",
        "programming": "programming",
        "skills": "skills",
        "Java": "Java",
        "NodeJS": "NodeJS",
        "Python": "Python",
        "communication": "communication",
        "willingness": "willingness",
        "ownership": "ownership",
        "tasks": "tasks",
        "++++++++++++++++++++++++++++++++++++++++++++++++++++++++++++++++++++++++++++++++Infinite": "++++++++++++++++++++++++++++++++++++++++++++++++++++++++++++++++++++++++++++++++Infinite",
        "opportunity": "opportunity",
        "workplace": "workplace",
        "action": "action",
        "employer": "employer",
        "-Regards": "-Regards",
        "Kushagra": "Kushagra",
        "Shuklakushagra": "Shuklakushagra",
        "shukla": "shukla",
        "infinite": "infinite",
        "https": "https",
        "//www": "//www",
        "linkedin": "linkedin",
        "DetailsJob": "DetailsJob",
        "Typefulltime": "Typefulltime",
        "days": "days"
      },
      "NUM": {},
      "VERB": {
        "see": "see",
        "does": "does",
        "have": "have",
        "be": "be",
        "has": "has",
        "set": "set",
        "listed": "listed",
        "developing": "developing",
        "using": "using",
        "is": "is",
        "Programming": "Programming",
        "preferred": "preferred",
        "Should": "Should",
        "learn": "learn",
        "take": "take",
        "comConnect/Follow": "comConnect/Follow",
        "employeePosted": "employeePosted"
      },
      "PRT": {
        "to": "to"
      },
      "ADJ": {
        "Good": "Good",
        "mandatory": "mandatory",
        "hands-on": "hands-on",
        "good": "good",
        "analytical": "analytical",
        "new": "new",
        "flexible": "flexible",
        "full": "full",
        "assigned": "assigned",
        "proud": "proud",
        "equal": "equal",
        "affirmative": "affirmative",
        "com/in/shuklakushagra1994/Job": "com/in/shuklakushagra1994/Job"
      }
    }
  },
  "223277005": {
    "Company": "Technosoft",
    "Job Title": "Cloud Architect",
    "Job Details": "DescriptionTechnosoft Corporation is a privately held Digital Services company with around 4,400 employees globally|||| Today, Technosoft delivers solutions covering digital transformation, data science and business intelligence, cloud management, Salesforce and SAP management, cyber security and IT infrastructure management|||| In addition to having many long-standing clients, Technosoft has garnered much external recognition winning numerous awards for IT excellence and innovation|||| We have immediate openings for Cloud Architect, Decatur, GA (Work remote until Covid is over, then work will pick up in Decatur GA, Client Office), kindly have a look on below job description, if you are interested please send me your updated word document resume with immediate contact details for more discussion|||| Responsibilities:Cloud Architect certification, senior-level experience with cloud implementations||||In partnership with other leaders in the firm, you will focus on delivering cloud solutions using Google Cloud|||| As a key member of Architecture group, you will help ensure success in building and migrating applications, software and services on public cloud||||Promote public cloud internally to sales and delivery teams to drive growth||||Educate customers of all sizes on the value proposition of Public Cloud and participate in deep architectural discussions to ensure solutions are designed for successful deployment in the cloudAct as a technical liaison between customers, delivery teams and support||||Job DetailsJob Typefulltime, employeePosted 5 days ago||||",
    "KeyWords": {
      "NOUN": {
        "Corporation": "Corporation",
        "Digital": "Digital",
        "Services": "Services",
        "company": "company",
        "employees": "employees",
        "Today": "Today",
        "Technosoft": "Technosoft",
        "delivers": "delivers",
        "solutions": "solutions",
        "transformation": "transformation",
        "data": "data",
        "science": "science",
        "business": "business",
        "intelligence": "intelligence",
        "management": "management",
        "Salesforce": "Salesforce",
        "SAP": "SAP",
        "security": "security",
        "IT": "IT",
        "infrastructure": "infrastructure",
        "addition": "addition",
        "clients": "clients",
        "recognition": "recognition",
        "awards": "awards",
        "excellence": "excellence",
        "innovation": "innovation",
        "openings": "openings",
        "Cloud": "Cloud",
        "Architect": "Architect",
        "Decatur": "Decatur",
        "GA": "GA",
        "Work": "Work",
        "Covid": "Covid",
        "work": "work",
        "Client": "Client",
        "Office": "Office",
        "look": "look",
        "job": "job",
        "description": "description",
        "please": "please",
        "word": "word",
        "document": "document",
        "resume": "resume",
        "contact": "contact",
        "details": "details",
        "discussion": "discussion",
        "Responsibilities": "Responsibilities",
        "certification": "certification",
        "experience": "experience",
        "implementations": "implementations",
        "partnership": "partnership",
        "leaders": "leaders",
        "firm": "firm",
        "Google": "Google",
        "member": "member",
        "Architecture": "Architecture",
        "group": "group",
        "success": "success",
        "building": "building",
        "migrating": "migrating",
        "applications": "applications",
        "software": "software",
        "services": "services",
        "cloud": "cloud",
        "Promote": "Promote",
        "sales": "sales",
        "delivery": "delivery",
        "teams": "teams",
        "growth": "growth",
        "Educate": "Educate",
        "customers": "customers",
        "sizes": "sizes",
        "value": "value",
        "proposition": "proposition",
        "Public": "Public",
        "discussions": "discussions",
        "deployment": "deployment",
        "cloudAct": "cloudAct",
        "liaison": "liaison",
        "support": "support",
        "Job": "Job",
        "DetailsJob": "DetailsJob",
        "Typefulltime": "Typefulltime",
        "days": "days"
      },
      "VERB": {
        "held": "held",
        "covering": "covering",
        "cyber": "cyber",
        "having": "having",
        "has": "has",
        "garnered": "garnered",
        "winning": "winning",
        "have": "have",
        "is": "is",
        "will": "will",
        "pick": "pick",
        "are": "are",
        "send": "send",
        "focus": "focus",
        "delivering": "delivering",
        "using": "using",
        "help": "help",
        "ensure": "ensure",
        "cloud": "cloud",
        "drive": "drive",
        "participate": "participate",
        "designed": "designed",
        "employeePosted": "employeePosted"
      },
      "NUM": {},
      "ADJ": {
        "cloud": "cloud",
        "many": "many",
        "long-standing": "long-standing",
        "much": "much",
        "external": "external",
        "numerous": "numerous",
        "immediate": "immediate",
        "interested": "interested",
        "updated": "updated",
        "more": "more",
        "senior-level": "senior-level",
        "other": "other",
        "key": "key",
        "public": "public",
        "deep": "deep",
        "architectural": "architectural",
        "successful": "successful",
        "technical": "technical"
      },
      "PRT": {
        "up": "up",
        "to": "to"
      }
    }
  },
  "223297011": {
    "Company": "Object Technology Solutions, Inc. (OTSI)",
    "Job Title": "Senior Software Engineer",
    "Job Details": "DescriptionSENIOR SOFTWARE ENGINEERLocation: Atlanta , GA with occasional Travel as required||||JOB SUMMARY:  The Software Engineer designs and develops internal and external business systems/applications, systems interfaces, databases, reporting, or business intelligence systems, as required to deliver new systems functionality supporting corporate business objectives||||RESPONSIBILITIES:  Owns the technical vision and development of a sub domain or capability||||Technology and SystemDevelops web, mobile and user interface (UI) applications to deliver new systems functionality supporting corporate business objectives|||| Leads moderately complex projects||||Utilizes development skills to build software and unit test new systems functionality per technical specifications, with deliverables to include builds and releases||||Ensures Continuous Integration and Build is in place||||Maintains technical skills and expertise through continuing education and training||||Project ManagementTranslates business, and functional requirements into documented technical specifications or User Stories||||Communicates design, requirements,functionality, and limitations of systems/applications||||Utilizes development skills to build (code) and unit test new systems functionality per technical specifications, with deliverables to include code builds and documented unit test results||||Develops or updates support documentation as needed by the DecOps function and lead Peer Review to allow acceptance of systems changes into production||||Oversees build and unit test production deployment packages||||Facilitates/leads reviews (walkthroughs) or grooming sessions and demos of technical specifications and program code with other members of the technical team, communicating design, requirements, feature set, functionality and limitations of systems/applications to team and development lead||||Utilizes product lifecycle methodology as a guide for development activities||||Provides on-call and after hours support as required for production releases and to respond and provide active resolution support on production outages||||Contribute to and work to meet project schedules||||Relationship and People Management ▪ Performs peer reviews||||Collaborates with architects and other Software Engineers on design||||Collaborates with other Business and IT partner teams on successful delivery of product enhancements and support||||Occassionally supervises contract resources||||MINIMUM REQUIRED:Minimum 5 years’ Application Development Experience, Designing and developmentC#, ASP||||Net, J2EE Application Framework, Siebel, Oblix, etc , Oracle or SQL 2000Minimum 5 years’ professional experience using 3 or more development languages or tools (e||||g||||, C#, ASP||||Net, J2EE Application Framework, Siebel, Oblix, etc||||)||||Experience as a Software Engineer is desirable, preferably in the wireless industry||||Must have Lead Experience||||Develops user interfaces, middle tier and/or interfaces, database, business intelligence, or packaged applications like Siebel or Rightpoint||||EDUCATION: Bachelor’s Degree|||| Bachelor’s degree in Computer Science or a related field||||Job DetailsJob Typefulltime, employeePosted 6 days ago||||",
    "KeyWords": {
      "NOUN": {
        "SOFTWARE": "SOFTWARE",
        "ENGINEERLocation": "ENGINEERLocation",
        "Atlanta": "Atlanta",
        "GA": "GA",
        "Travel": "Travel",
        "JOB": "JOB",
        "SUMMARY": "SUMMARY",
        "Software": "Software",
        "Engineer": "Engineer",
        "designs": "designs",
        "business": "business",
        "systems/applications": "systems/applications",
        "systems": "systems",
        "interfaces": "interfaces",
        "databases": "databases",
        "reporting": "reporting",
        "intelligence": "intelligence",
        "functionality": "functionality",
        "objectives": "objectives",
        "RESPONSIBILITIES": "RESPONSIBILITIES",
        "Owns": "Owns",
        "vision": "vision",
        "development": "development",
        "sub": "sub",
        "domain": "domain",
        "capability": "capability",
        "Technology": "Technology",
        "SystemDevelops": "SystemDevelops",
        "web": "web",
        "interface": "interface",
        "UI": "UI",
        "applications": "applications",
        "Leads": "Leads",
        "projects": "projects",
        "Utilizes": "Utilizes",
        "skills": "skills",
        "software": "software",
        "unit": "unit",
        "specifications": "specifications",
        "deliverables": "deliverables",
        "builds": "builds",
        "releases": "releases",
        "Ensures": "Ensures",
        "Integration": "Integration",
        "Build": "Build",
        "place": "place",
        "Maintains": "Maintains",
        "expertise": "expertise",
        "education": "education",
        "training": "training",
        "Project": "Project",
        "ManagementTranslates": "ManagementTranslates",
        "requirements": "requirements",
        "User": "User",
        "Stories": "Stories",
        "Communicates": "Communicates",
        "design": "design",
        "limitations": "limitations",
        "code": "code",
        "test": "test",
        "results": "results",
        "Develops": "Develops",
        "support": "support",
        "documentation": "documentation",
        "DecOps": "DecOps",
        "function": "function",
        "Peer": "Peer",
        "Review": "Review",
        "acceptance": "acceptance",
        "changes": "changes",
        "production": "production",
        "deployment": "deployment",
        "packages": "packages",
        "Facilitates/leads": "Facilitates/leads",
        "walkthroughs": "walkthroughs",
        "sessions": "sessions",
        "demos": "demos",
        "program": "program",
        "members": "members",
        "team": "team",
        "feature": "feature",
        "lead": "lead",
        "product": "product",
        "lifecycle": "lifecycle",
        "methodology": "methodology",
        "guide": "guide",
        "activities": "activities",
        "Provides": "Provides",
        "hours": "hours",
        "resolution": "resolution",
        "outages": "outages",
        "Contribute": "Contribute",
        "schedules": "schedules",
        "Relationship": "Relationship",
        "People": "People",
        "Management": "Management",
        "Performs": "Performs",
        "reviews": "reviews",
        "Collaborates": "Collaborates",
        "architects": "architects",
        "Engineers": "Engineers",
        "Business": "Business",
        "IT": "IT",
        "partner": "partner",
        "teams": "teams",
        "delivery": "delivery",
        "enhancements": "enhancements",
        "Occassionally": "Occassionally",
        "contract": "contract",
        "resources": "resources",
        "MINIMUM": "MINIMUM",
        "years": "years",
        "Application": "Application",
        "Development": "Development",
        "Experience": "Experience",
        "Designing": "Designing",
        "ASP": "ASP",
        "Net": "Net",
        "J2EE": "J2EE",
        "Framework": "Framework",
        "Siebel": "Siebel",
        "Oblix": "Oblix",
        "Oracle": "Oracle",
        "SQL": "SQL",
        "experience": "experience",
        "languages": "languages",
        "tools": "tools",
        "g.": "g.",
        "wireless": "wireless",
        "industry": "industry",
        "Must": "Must",
        "Lead": "Lead",
        "and/or": "and/or",
        "database": "database",
        "Rightpoint": "Rightpoint",
        "EDUCATION": "EDUCATION",
        "Bachelor": "Bachelor",
        "Degree": "Degree",
        "degree": "degree",
        "Computer": "Computer",
        "Science": "Science",
        "field": "field",
        "Job": "Job",
        "DetailsJob": "DetailsJob",
        "Typefulltime": "Typefulltime",
        "days": "days"
      },
      "ADJ": {
        "internal": "internal",
        "external": "external",
        "new": "new",
        "corporate": "corporate",
        "technical": "technical",
        "mobile": "mobile",
        "user": "user",
        "complex": "complex",
        "Continuous": "Continuous",
        "functional": "functional",
        "documented": "documented",
        "updates": "updates",
        "lead": "lead",
        "build": "build",
        "other": "other",
        "Utilizes": "Utilizes",
        "on-call": "on-call",
        "active": "active",
        "project": "project",
        "successful": "successful",
        "REQUIRED": "REQUIRED",
        "Minimum": "Minimum",
        "developmentC": "developmentC",
        "professional": "professional",
        "more": "more",
        "e.": "e.",
        "desirable": "desirable",
        "middle": "middle",
        "tier": "tier",
        "related": "related"
      },
      "VERB": {
        "develops": "develops",
        "required": "required",
        "deliver": "deliver",
        "supporting": "supporting",
        "build": "build",
        "test": "test",
        "include": "include",
        "is": "is",
        "continuing": "continuing",
        "documented": "documented",
        "needed": "needed",
        "allow": "allow",
        "reviews": "reviews",
        "grooming": "grooming",
        "communicating": "communicating",
        "set": "set",
        "team": "team",
        "respond": "respond",
        "provide": "provide",
        "work": "work",
        "meet": "meet",
        "peer": "peer",
        "supervises": "supervises",
        "using": "using",
        "have": "have",
        "packaged": "packaged",
        "employeePosted": "employeePosted"
      },
      "PRT": {
        "to": "to"
      },
      "X": {
        "etc": "etc"
      },
      "NUM": {}
    }
  },
  "223327186": {
    "Company": "American Cybersystems",
    "Job Title": "Azure Cloud Engineer (Remote)",
    "Job Details": "DescriptionJD: Position: Business Analyst (Technical)Skills: Must-have: Experience working in both Agile and Waterfall models||||Experience in driving technical projects from requirements gathering stages to development to QA to production phases||||Ability to work as a liaison between Product Managers and Tech Leads||||Elicit, analyze, specify requirements||||Work with the dev team to ensure these requirements are met||||Coordinate QA and production release phases||||Coordinate different tracks (development, UX, design, QA etc||||)Track metrics, identify blockers, and generate status reports for stakeholder consumption||||Any PM tools such as Asana, Jira, etc||||Good written and spoken communication skills||||Have a process-oriented approach and bring structure to green field projects||||Good-to-have:Data Analysis/ other technical background|||| Ability to create and update data visualization charts/ dashboards using any popular tools such as Excel, Tableau, Power BI etc||||Job DetailsJob Typefulltime, employeePosted 5 days ago||||",
    "KeyWords": {
      "NOUN": {
        "Position": "Position",
        "Analyst": "Analyst",
        "Technical": "Technical",
        "Experience": "Experience",
        "Agile": "Agile",
        "Waterfall": "Waterfall",
        "models": "models",
        "projects": "projects",
        "requirements": "requirements",
        "stages": "stages",
        "development": "development",
        "QA": "QA",
        "production": "production",
        "phases": "phases",
        "Ability": "Ability",
        "liaison": "liaison",
        "Product": "Product",
        "Managers": "Managers",
        "Tech": "Tech",
        "Leads": "Leads",
        "Elicit": "Elicit",
        "analyze": "analyze",
        "specify": "specify",
        "Work": "Work",
        "dev": "dev",
        "team": "team",
        "Coordinate": "Coordinate",
        "release": "release",
        "tracks": "tracks",
        "UX": "UX",
        "design": "design",
        "Track": "Track",
        "metrics": "metrics",
        "identify": "identify",
        "blockers": "blockers",
        "generate": "generate",
        "status": "status",
        "reports": "reports",
        "stakeholder": "stakeholder",
        "consumption": "consumption",
        "PM": "PM",
        "tools": "tools",
        "Asana": "Asana",
        "Jira": "Jira",
        "communication": "communication",
        "skills": "skills",
        "approach": "approach",
        "structure": "structure",
        "field": "field",
        "Good-to-have": "Good-to-have",
        "Data": "Data",
        "Analysis/": "Analysis/",
        "background": "background",
        "data": "data",
        "visualization": "visualization",
        "charts/": "charts/",
        "dashboards": "dashboards",
        "Excel": "Excel",
        "Tableau": "Tableau",
        "Power": "Power",
        "BI": "BI",
        "Job": "Job",
        "DetailsJob": "DetailsJob",
        "Typefulltime": "Typefulltime",
        "days": "days"
      },
      "ADJ": {
        "Must-have": "Must-have",
        "technical": "technical",
        "different": "different",
        "such": "such",
        "Good": "Good",
        "process-oriented": "process-oriented",
        "green": "green",
        "other": "other",
        "popular": "popular"
      },
      "VERB": {
        "working": "working",
        "driving": "driving",
        "gathering": "gathering",
        "work": "work",
        "ensure": "ensure",
        "are": "are",
        "met": "met",
        "written": "written",
        "spoken": "spoken",
        "Have": "Have",
        "bring": "bring",
        "create": "create",
        "update": "update",
        "using": "using",
        "employeePosted": "employeePosted"
      },
      "PRT": {
        "to": "to"
      },
      "X": {
        "etc": "etc"
      }
    }
  },
  "223327422": {
    "Company": "Hexaware Technologies",
    "Job Title": "Backend Developer",
    "Job Details": "DescriptionHighly energetic candidate with a Bachelor’s degree in Computer Science, Software Engineering, MIS or equivalent degree with 5 years of work experience in IT industry||||Understanding of Software Development Lifecycle in Waterfall and Agile framework|||| Knowledge on DevOps would be plusExcellent communication skills, quick learning attitude, strong logic, reasoning and critical thinking skills to solve problems||||4+ years of experience with Spring Core, Spring Boot, Spring MVC, Spring Integration and Spring SecurityOOPS concept, java, exception handling, multithreading, collection framework, Spring, Hibernate, Spring Boot, webservices||||Hands-on experience with Database development and tools with SQL, O/RM, Flyway, OLTP Database Tuning, etc||||Experience with implementing integration solutions with RESTful Web ServicesJob DetailsJob Typefulltime, employeePosted 5 days ago||||",
    "KeyWords": {
      "NOUN": {
        "candidate": "candidate",
        "Bachelor": "Bachelor",
        "degree": "degree",
        "Computer": "Computer",
        "Science": "Science",
        "Software": "Software",
        "Engineering": "Engineering",
        "MIS": "MIS",
        "years": "years",
        "work": "work",
        "experience": "experience",
        "IT": "IT",
        "industry": "industry",
        "Understanding": "Understanding",
        "Development": "Development",
        "Lifecycle": "Lifecycle",
        "Waterfall": "Waterfall",
        "Agile": "Agile",
        "framework": "framework",
        "Knowledge": "Knowledge",
        "DevOps": "DevOps",
        "communication": "communication",
        "skills": "skills",
        "attitude": "attitude",
        "logic": "logic",
        "thinking": "thinking",
        "problems": "problems",
        "Spring": "Spring",
        "Core": "Core",
        "Boot": "Boot",
        "MVC": "MVC",
        "Integration": "Integration",
        "SecurityOOPS": "SecurityOOPS",
        "concept": "concept",
        "java": "java",
        "exception": "exception",
        "handling": "handling",
        "multithreading": "multithreading",
        "collection": "collection",
        "Hibernate": "Hibernate",
        "webservices": "webservices",
        "Database": "Database",
        "development": "development",
        "tools": "tools",
        "SQL": "SQL",
        "O/RM": "O/RM",
        "Flyway": "Flyway",
        "OLTP": "OLTP",
        "Tuning": "Tuning",
        "Experience": "Experience",
        "integration": "integration",
        "solutions": "solutions",
        "RESTful": "RESTful",
        "Web": "Web",
        "ServicesJob": "ServicesJob",
        "DetailsJob": "DetailsJob",
        "Typefulltime": "Typefulltime",
        "days": "days"
      },
      "ADJ": {
        "equivalent": "equivalent",
        "plusExcellent": "plusExcellent",
        "quick": "quick",
        "strong": "strong",
        "critical": "critical",
        "Hands-on": "Hands-on"
      },
      "VERB": {
        "be": "be",
        "learning": "learning",
        "reasoning": "reasoning",
        "solve": "solve",
        "implementing": "implementing",
        "employeePosted": "employeePosted"
      },
      "PRT": {},
      "NUM": {},
      "X": {}
    }
  },
  "223328536": {
    "Company": "Randstad Technologies",
    "Job Title": "Application Developer",
    "Job Details": "Description job summary:Searching for a Middleware Application Developer to partner with our clients Solution Architects and SOA Architects for designing net new features|||| Day to day tasks will require development, customizations, and production support for FMW Applications|||| Perform maintenance activities related to adjusting security posture, and supporting changes related to infrastructures and external services that impact services|||| (certificates, token exchange, OKTA, API security protocols, etc)\n location: Smyrna, Georgiajob type: Contractsalary: $50 - 80  per hourwork hours: 8am to 4pmeducation: Bachelors responsibilities:•Coordinating and executing development deliverables within schedule||||•Partnering with Solution Architects and SOA Architects for designing net new features||||•Day to day tasks will require development, customizations, and production support for FMW Applications||||•Perform maintenance activities related to adjusting security posture, and supporting changes related to infrastructures and external services that impact services|||| (certificates, token exchange, OKTA, API security protocols, etc)•Diagnose and address performance issues at all levels of the tech stack (i||||e|||| WebLogic, Databases)•Represent and explain upcoming change request to Change Advisory Board•Job functions will require candidate to work on some weekend and evenings for support qualifications:•Experience level: Experienced•Minimum 7 years of experience•Education: Bachelors skills: •JAVA DEVELOPER (7 years of experience is preferred)•middleware (7 years of experience is preferred)•ORACLE PROGRAMMER (7 years of experience is preferred)•Service Oriented Architecture (7 years of experience is preferred)•Oracle Integration Cloud (7 years of experience is preferred)Equal Opportunity Employer: Race, Color, Religion, Sex, Sexual Orientation, Gender Identity, National Origin, Age, Genetic Information, Disability, Protected Veteran Status, or any other legally protected group status||||\nJob DetailsSalary$50 - $80 Per HourJob Typefulltime, contractPosted 5 days ago||||",
    "KeyWords": {
      "NOUN": {
        "job": "job",
        "summary": "summary",
        "Middleware": "Middleware",
        "Application": "Application",
        "Developer": "Developer",
        "partner": "partner",
        "clients": "clients",
        "Solution": "Solution",
        "Architects": "Architects",
        "SOA": "SOA",
        "features": "features",
        "Day": "Day",
        "day": "day",
        "tasks": "tasks",
        "development": "development",
        "customizations": "customizations",
        "production": "production",
        "support": "support",
        "FMW": "FMW",
        "Applications": "Applications",
        "Perform": "Perform",
        "maintenance": "maintenance",
        "activities": "activities",
        "security": "security",
        "posture": "posture",
        "changes": "changes",
        "infrastructures": "infrastructures",
        "services": "services",
        "impact": "impact",
        "certificates": "certificates",
        "exchange": "exchange",
        "OKTA": "OKTA",
        "API": "API",
        "protocols": "protocols",
        "location": "location",
        "Smyrna": "Smyrna",
        "Georgiajob": "Georgiajob",
        "type": "type",
        "hourwork": "hourwork",
        "hours": "hours",
        "Bachelors": "Bachelors",
        "responsibilities": "responsibilities",
        "•Coordinating": "•Coordinating",
        "deliverables": "deliverables",
        "schedule": "schedule",
        "•Day": "•Day",
        "performance": "performance",
        "issues": "issues",
        "levels": "levels",
        "stack": "stack",
        "e.": "e.",
        "WebLogic": "WebLogic",
        "Databases": "Databases",
        "•Represent": "•Represent",
        "change": "change",
        "request": "request",
        "Change": "Change",
        "Advisory": "Advisory",
        "Board•Job": "Board•Job",
        "functions": "functions",
        "candidate": "candidate",
        "weekend": "weekend",
        "evenings": "evenings",
        "qualifications": "qualifications",
        "•Experience": "•Experience",
        "level": "level",
        "years": "years",
        "experience•Education": "experience•Education",
        "skills": "skills",
        "•JAVA": "•JAVA",
        "DEVELOPER": "DEVELOPER",
        "experience": "experience",
        "•middleware": "•middleware",
        "PROGRAMMER": "PROGRAMMER",
        "•Service": "•Service",
        "Architecture": "Architecture",
        "•Oracle": "•Oracle",
        "Integration": "Integration",
        "Cloud": "Cloud",
        "Opportunity": "Opportunity",
        "Employer": "Employer",
        "Race": "Race",
        "Color": "Color",
        "Religion": "Religion",
        "Sex": "Sex",
        "Sexual": "Sexual",
        "Orientation": "Orientation",
        "Gender": "Gender",
        "Identity": "Identity",
        "National": "National",
        "Origin": "Origin",
        "Age": "Age",
        "Genetic": "Genetic",
        "Information": "Information",
        "Disability": "Disability",
        "Protected": "Protected",
        "Veteran": "Veteran",
        "Status": "Status",
        "group": "group",
        "status": "status",
        "Job": "Job",
        "DetailsSalary": "DetailsSalary",
        "Per": "Per",
        "HourJob": "HourJob",
        "Typefulltime": "Typefulltime",
        "days": "days"
      },
      "VERB": {
        "designing": "designing",
        "will": "will",
        "require": "require",
        "related": "related",
        "adjusting": "adjusting",
        "supporting": "supporting",
        "executing": "executing",
        "•Partnering": "•Partnering",
        "•Perform": "•Perform",
        "explain": "explain",
        "work": "work",
        "is": "is",
        "preferred": "preferred",
        "Oriented": "Oriented",
        "protected": "protected",
        "contractPosted": "contractPosted"
      },
      "PRT": {
        "to": "to"
      },
      "ADJ": {
        "new": "new",
        "external": "external",
        "token": "token",
        "Contractsalary": "Contractsalary",
        "net": "net",
        "address": "address",
        "tech": "tech",
        "i.": "i.",
        "upcoming": "upcoming",
        "Experienced•Minimum": "Experienced•Minimum",
        "Equal": "Equal",
        "other": "other"
      },
      "X": {
        "etc": "etc",
        "•Diagnose": "•Diagnose",
        "•ORACLE": "•ORACLE"
      },
      "NUM": {
        "50": "50",
        "80": "80",
        "8am": "8am",
        "4pmeducation": "4pmeducation"
      }
    }
  },
  "223329785": {
    "Company": "Company Confidential",
    "Job Title": "Entry Level Devops / AWS / Cloud Engineer",
    "Job Details": "DescriptionWho We Are: Enhance IT is an IT/Management firm that specializes in training, placement and IT consultation|||| We are an industry leader in providing top-level skilled and experienced consultants in a variety of technologies to meet our client’s needs in today’s fast paced environment||||  What you will be doing: Designing and deploying dynamically scalable, available, fault-tolerant, and reliable applications on the AWS Cloud using EC2, VPC, IAM, S3, Cloud Formation, Bastion Host, AWS VPN, Lambda, AWS EMR, Kinesis, Redshift, KMS, CloudWatch, SNS, RDS|||| Monitoring AWS Resources and metrics with CloudWatch and building alerts using the metrics to create fault tolerant system|||| Supervise, deploy and maintain several simultaneous releases through multiple test environments|||| Determine complex build, release, and environment issues in a multi-component environment|||| Work collaboratively with software engineering team to design continuous integration best practices, deploy applications and automate operations and processes|||| Develop infrastructure deployment automation scripts for seamless upgrades avoiding downtime|||| and processes to support uptime SLA requirements|||| Troubleshoot and resolve issues in development, test, QA, and production environments to maintain uptime commitments|||| Apply knowledge of the latest trends in the DevOps industry and engage with client facing teams to consult and potentially help to implement DevOps practices||||Ensure high quality software with the right balance of unit / integration / functional test automation|||| Appling knowledge of Git for source code version control and incorporated with Jenkins for CI/CD pipeline, code quality tracking, and user management with build tool Maven||||What you need for this position: Has previous experience in the ff roles: AWS Engineer, AWS Consultant, AWS Solution Architect, AWS Software Developer, Cloud Engineer, AWS DevOps Engineer, AWS Developer, Cloud Developer, Cloud Infrastructure Engineer, System Engineer, System Administrator, Site Reliability Engineer, IAM Engineer||||Can code in: Java or C# or C++ or Python (one or the other) More than one is a plus - With also SQL and Linux – Good for the resumes to have Linux on them|||| Must know how to code in one of these coding languages: Java, Scala, Python, GO, C#, C++|||| Must have scripting knowledge in one of these scripting languages: Json, Python, YAML||||Must have a Bachelors Degree in Computer Science: Software Engineering, Mathematics, , Electrical Engineering, Statistical Computing, Mathematical Statistics, Mechanical Engineering, Information Systems: Software Engineering, Software Development, Information Technology: Programming and Software Development, Computer Science, Computer Systems Engineering, Industrial Engineering, Actuarial Science, Physics, Economics|||| Nice to have a Master`s Degree on the above mentioned field||||Benefits & PerksFull benefits including Medical/Dental/Vision Paid travel to and from the Atlanta HQPaid Time Off401(k) savings planTraining in Atlanta, GA prior to going on live projects Job DetailsJob Typefulltime, employeePosted 5 days ago||||",
    "KeyWords": {
      "VERB": {
        "is": "is",
        "specializes": "specializes",
        "are": "are",
        "providing": "providing",
        "skilled": "skilled",
        "meet": "meet",
        "will": "will",
        "be": "be",
        "doing": "doing",
        "deploying": "deploying",
        "using": "using",
        "create": "create",
        "maintain": "maintain",
        "Work": "Work",
        "design": "design",
        "automate": "automate",
        "Develop": "Develop",
        "avoiding": "avoiding",
        "processes": "processes",
        "support": "support",
        "resolve": "resolve",
        "facing": "facing",
        "consult": "consult",
        "help": "help",
        "implement": "implement",
        "incorporated": "incorporated",
        "code": "code",
        "need": "need",
        "Can": "Can",
        "have": "have",
        "know": "know",
        "coding": "coding",
        "scripting": "scripting",
        "mentioned": "mentioned",
        "including": "including",
        "savings": "savings",
        "planTraining": "planTraining",
        "going": "going",
        "employeePosted": "employeePosted"
      },
      "NOUN": {
        "IT": "IT",
        "firm": "firm",
        "training": "training",
        "placement": "placement",
        "consultation": "consultation",
        "industry": "industry",
        "leader": "leader",
        "top-level": "top-level",
        "consultants": "consultants",
        "variety": "variety",
        "technologies": "technologies",
        "client": "client",
        "needs": "needs",
        "today": "today",
        "environment": "environment",
        "Designing": "Designing",
        "applications": "applications",
        "AWS": "AWS",
        "Cloud": "Cloud",
        "EC2": "EC2",
        "VPC": "VPC",
        "IAM": "IAM",
        "S3": "S3",
        "Formation": "Formation",
        "Bastion": "Bastion",
        "Host": "Host",
        "VPN": "VPN",
        "Lambda": "Lambda",
        "EMR": "EMR",
        "Kinesis": "Kinesis",
        "Redshift": "Redshift",
        "KMS": "KMS",
        "CloudWatch": "CloudWatch",
        "SNS": "SNS",
        "RDS": "RDS",
        "Monitoring": "Monitoring",
        "Resources": "Resources",
        "metrics": "metrics",
        "building": "building",
        "alerts": "alerts",
        "fault": "fault",
        "system": "system",
        "Supervise": "Supervise",
        "deploy": "deploy",
        "releases": "releases",
        "test": "test",
        "environments": "environments",
        "Determine": "Determine",
        "build": "build",
        "release": "release",
        "issues": "issues",
        "software": "software",
        "engineering": "engineering",
        "team": "team",
        "integration": "integration",
        "practices": "practices",
        "operations": "operations",
        "processes": "processes",
        "automation": "automation",
        "scripts": "scripts",
        "seamless": "seamless",
        "upgrades": "upgrades",
        "downtime": "downtime",
        "SLA": "SLA",
        "requirements": "requirements",
        "Troubleshoot": "Troubleshoot",
        "development": "development",
        "QA": "QA",
        "production": "production",
        "commitments": "commitments",
        "Apply": "Apply",
        "knowledge": "knowledge",
        "trends": "trends",
        "DevOps": "DevOps",
        "engage": "engage",
        "teams": "teams",
        "Ensure": "Ensure",
        "quality": "quality",
        "balance": "balance",
        "unit": "unit",
        "Appling": "Appling",
        "Git": "Git",
        "source": "source",
        "code": "code",
        "version": "version",
        "control": "control",
        "Jenkins": "Jenkins",
        "CI/CD": "CI/CD",
        "pipeline": "pipeline",
        "tracking": "tracking",
        "management": "management",
        "tool": "tool",
        "Maven": "Maven",
        "position": "position",
        "Has": "Has",
        "experience": "experience",
        "roles": "roles",
        "Engineer": "Engineer",
        "Consultant": "Consultant",
        "Solution": "Solution",
        "Architect": "Architect",
        "Software": "Software",
        "Developer": "Developer",
        "Infrastructure": "Infrastructure",
        "System": "System",
        "Administrator": "Administrator",
        "Site": "Site",
        "Reliability": "Reliability",
        "Java": "Java",
        "C++": "C++",
        "Python": "Python",
        "SQL": "SQL",
        "Linux": "Linux",
        "Good": "Good",
        "resumes": "resumes",
        "Must": "Must",
        "languages": "languages",
        "Scala": "Scala",
        "GO": "GO",
        "Json": "Json",
        "YAML": "YAML",
        "Bachelors": "Bachelors",
        "Degree": "Degree",
        "Computer": "Computer",
        "Science": "Science",
        "Engineering": "Engineering",
        "Mathematics": "Mathematics",
        "Electrical": "Electrical",
        "Statistical": "Statistical",
        "Computing": "Computing",
        "Mathematical": "Mathematical",
        "Statistics": "Statistics",
        "Mechanical": "Mechanical",
        "Information": "Information",
        "Systems": "Systems",
        "Development": "Development",
        "Technology": "Technology",
        "Programming": "Programming",
        "Industrial": "Industrial",
        "Actuarial": "Actuarial",
        "Physics": "Physics",
        "Economics": "Economics",
        "Nice": "Nice",
        "Master": "Master",
        "above": "above",
        "field": "field",
        "Benefits": "Benefits",
        "PerksFull": "PerksFull",
        "benefits": "benefits",
        "Medical/Dental/Vision": "Medical/Dental/Vision",
        "Paid": "Paid",
        "travel": "travel",
        "Atlanta": "Atlanta",
        "HQPaid": "HQPaid",
        "Time": "Time",
        "Off401": "Off401",
        "GA": "GA",
        "projects": "projects",
        "Job": "Job",
        "DetailsJob": "DetailsJob",
        "Typefulltime": "Typefulltime",
        "days": "days"
      },
      "ADJ": {
        "experienced": "experienced",
        "paced": "paced",
        "scalable": "scalable",
        "available": "available",
        "fault-tolerant": "fault-tolerant",
        "reliable": "reliable",
        "tolerant": "tolerant",
        "several": "several",
        "simultaneous": "simultaneous",
        "multiple": "multiple",
        "complex": "complex",
        "multi-component": "multi-component",
        "continuous": "continuous",
        "best": "best",
        "infrastructure": "infrastructure",
        "deployment": "deployment",
        "uptime": "uptime",
        "latest": "latest",
        "high": "high",
        "right": "right",
        "functional": "functional",
        "user": "user",
        "build": "build",
        "previous": "previous",
        "ff": "ff",
        "other": "other",
        "More": "More",
        "plus": "plus",
        "live": "live"
      },
      "PRT": {
        "to": "to"
      },
      "NUM": {
        "one": "one"
      }
    }
  },
  "223332523": {
    "Company": "Cognizant",
    "Job Title": "AWS/Python Developer",
    "Job Details": "DescriptionWe are Cognizant Artificial Intelligence Digital technologies, including analytics and AI, give companies a once-in-a-generation opportunity to perform orders of magnitude better than ever before|||| But clients need new business models built from analyzing customers and business operations at every angle to really understand them|||| With the power to apply artificial intelligence and data science to business decisions via enterprise data management solutions, we help leading companies prototype, refine, validate and scale the most desirable products and delivery models to enterprise scale within weeks *You must be legally authorized to work in the United States without the need for employer sponsorship, now or at any time in the future * Job Title – AWS/Python Developer Location – Atlanta, Georgia (Remote until COVID) Roles/Responsibilities:  You understand various aspects of architecture practices: business, application, data, security, infrastructure and governance|||| You can successfully work with Product Architects to define technical architecture for products||||  You will design, develop, test, deploy, maintain and improve software||||  You will manage individual project priorities, deadlines and work you're doing||||  You have the ability to translate functional and technical requirements into detailed architecture and design||||  You have experience in overall system architecture, scalability, reliability, and performance||||  You have the ability to work within pressurized environments whilst making critical decisions||||  Experience with Cloud Platforms AWS and Deploying and automating infrastructure/applications using Chef, RPM, Docker, AWS (ECS,EKS, ECR), Terraform|||| Manage AWS infrastructure with a drive towards a cloud smart strategy||||  Extend and maintain our CI/CD pipeline||||  Write and update technical documentation||||  Troubleshoot problems and provide support for software and cloud systems||||  Mentor across the organization on devops best practices and techniques||||  Ensure projects follow operating practices for Visible and enhance the processes as needed|||| Ensure the quality of the project meets Quality Assurance (QA) and User Acceptance Testing (UAT) guidelines|||| Demonstrate the ability to adapt and work with team members of various experience level|||| Required Qualifications:   Bachelor's Degree in Computer Science, or similar|||| 5+ years of experience as a Developer|||| Experience in Enterprise Architecture environment||||  Cloud transformation projects||||  Agile methodology||||  Working knowledge of DevOps|||| Experience in big-scale Batch Application Platforms||||  You adore working in a fast paced and agile development environment||||  You have experience in reviewing and selecting Technical and Applications Architectures solutions||||  You have experience of working with Technical and Application Architects||||  You have solid hands-on experience on software development life cycles||||  You have solid experience working with diverse technology platforms||||  You have excellent analytical and problem-solving skills||||  You excel in strategic planning and problem-solving|||| You can successful mentor developers who are looking to become architects||||  Must be proficient in OS security controls, privileges and escalation||||  Good to have experience working with deployment and orchestration technologies (such as Docker, Kubernetes, OpenStack, Chef, Salt, Ansible, Jenkins)||||  Should have consumed/worked with Virtualization Tools and Storage tech||||  Good written/Oral Communication, Presentation, Interactive skills with team across geography||||  Works well under pressure and meets deadline||||  Flexible to work either independently or with team||||  Experience with the linear modeling functions within R|||| Highly collaborative, a fast learner and willing to work wherever needed on the team|||| Experience with Object Oriented Programming|||| Experience with Python and a major relational database|||| Experience with version control and understanding of version control concepts|||| Understanding of RESTful API design||||     Job DetailsJob Typefulltime, employeePosted 5 days ago||||",
    "KeyWords": {
      "NOUN": {
        "Cognizant": "Cognizant",
        "Artificial": "Artificial",
        "Intelligence": "Intelligence",
        "Digital": "Digital",
        "technologies": "technologies",
        "analytics": "analytics",
        "AI": "AI",
        "companies": "companies",
        "opportunity": "opportunity",
        "orders": "orders",
        "magnitude": "magnitude",
        "clients": "clients",
        "business": "business",
        "models": "models",
        "customers": "customers",
        "operations": "operations",
        "angle": "angle",
        "power": "power",
        "intelligence": "intelligence",
        "data": "data",
        "science": "science",
        "decisions": "decisions",
        "enterprise": "enterprise",
        "management": "management",
        "solutions": "solutions",
        "prototype": "prototype",
        "refine": "refine",
        "validate": "validate",
        "products": "products",
        "delivery": "delivery",
        "scale": "scale",
        "weeks": "weeks",
        "United": "United",
        "States": "States",
        "need": "need",
        "employer": "employer",
        "sponsorship": "sponsorship",
        "time": "time",
        "future": "future",
        "Job": "Job",
        "Title": "Title",
        "AWS/Python": "AWS/Python",
        "Developer": "Developer",
        "Location": "Location",
        "Atlanta": "Atlanta",
        "Georgia": "Georgia",
        "Remote": "Remote",
        "COVID": "COVID",
        "Roles/Responsibilities": "Roles/Responsibilities",
        "aspects": "aspects",
        "architecture": "architecture",
        "practices": "practices",
        "application": "application",
        "security": "security",
        "infrastructure": "infrastructure",
        "governance": "governance",
        "Product": "Product",
        "Architects": "Architects",
        "test": "test",
        "deploy": "deploy",
        "maintain": "maintain",
        "software": "software",
        "project": "project",
        "priorities": "priorities",
        "deadlines": "deadlines",
        "work": "work",
        "ability": "ability",
        "requirements": "requirements",
        "design": "design",
        "system": "system",
        "scalability": "scalability",
        "reliability": "reliability",
        "performance": "performance",
        "environments": "environments",
        "Experience": "Experience",
        "Cloud": "Cloud",
        "Platforms": "Platforms",
        "AWS": "AWS",
        "Deploying": "Deploying",
        "infrastructure/applications": "infrastructure/applications",
        "Chef": "Chef",
        "RPM": "RPM",
        "Docker": "Docker",
        "ECS": "ECS",
        "EKS": "EKS",
        "ECR": "ECR",
        "Terraform": "Terraform",
        "Manage": "Manage",
        "drive": "drive",
        "strategy": "strategy",
        "Extend": "Extend",
        "CI/CD": "CI/CD",
        "pipeline": "pipeline",
        "Write": "Write",
        "documentation": "documentation",
        "Troubleshoot": "Troubleshoot",
        "problems": "problems",
        "support": "support",
        "systems": "systems",
        "Mentor": "Mentor",
        "organization": "organization",
        "devops": "devops",
        "techniques": "techniques",
        "Ensure": "Ensure",
        "projects": "projects",
        "operating": "operating",
        "processes": "processes",
        "quality": "quality",
        "Quality": "Quality",
        "Assurance": "Assurance",
        "QA": "QA",
        "User": "User",
        "Acceptance": "Acceptance",
        "Testing": "Testing",
        "UAT": "UAT",
        "guidelines": "guidelines",
        "members": "members",
        "experience": "experience",
        "level": "level",
        "Qualifications": "Qualifications",
        "Bachelor": "Bachelor",
        "Degree": "Degree",
        "Computer": "Computer",
        "Science": "Science",
        "years": "years",
        "Enterprise": "Enterprise",
        "Architecture": "Architecture",
        "environment": "environment",
        "transformation": "transformation",
        "Agile": "Agile",
        "methodology": "methodology",
        "knowledge": "knowledge",
        "DevOps": "DevOps",
        "Batch": "Batch",
        "Application": "Application",
        "fast": "fast",
        "development": "development",
        "reviewing": "reviewing",
        "Technical": "Technical",
        "Applications": "Applications",
        "Architectures": "Architectures",
        "life": "life",
        "cycles": "cycles",
        "technology": "technology",
        "platforms": "platforms",
        "skills": "skills",
        "planning": "planning",
        "problem-solving": "problem-solving",
        "mentor": "mentor",
        "developers": "developers",
        "architects": "architects",
        "Must": "Must",
        "OS": "OS",
        "controls": "controls",
        "privileges": "privileges",
        "escalation": "escalation",
        "deployment": "deployment",
        "orchestration": "orchestration",
        "Kubernetes": "Kubernetes",
        "OpenStack": "OpenStack",
        "Salt": "Salt",
        "Ansible": "Ansible",
        "Jenkins": "Jenkins",
        "Virtualization": "Virtualization",
        "Tools": "Tools",
        "Storage": "Storage",
        "tech": "tech",
        "Communication": "Communication",
        "Presentation": "Presentation",
        "Interactive": "Interactive",
        "team": "team",
        "geography": "geography",
        "pressure": "pressure",
        "meets": "meets",
        "modeling": "modeling",
        "functions": "functions",
        "R.": "R.",
        "Highly": "Highly",
        "learner": "learner",
        "Object": "Object",
        "Oriented": "Oriented",
        "Programming": "Programming",
        "Python": "Python",
        "database": "database",
        "version": "version",
        "control": "control",
        "understanding": "understanding",
        "concepts": "concepts",
        "Understanding": "Understanding",
        "RESTful": "RESTful",
        "API": "API",
        "DetailsJob": "DetailsJob",
        "Typefulltime": "Typefulltime",
        "days": "days"
      },
      "VERB": {
        "including": "including",
        "give": "give",
        "perform": "perform",
        "need": "need",
        "built": "built",
        "analyzing": "analyzing",
        "understand": "understand",
        "apply": "apply",
        "help": "help",
        "leading": "leading",
        "scale": "scale",
        "enterprise": "enterprise",
        "must": "must",
        "be": "be",
        "authorized": "authorized",
        "work": "work",
        "can": "can",
        "define": "define",
        "will": "will",
        "design": "design",
        "develop": "develop",
        "improve": "improve",
        "manage": "manage",
        "'re": "'re",
        "doing": "doing",
        "have": "have",
        "translate": "translate",
        "experience": "experience",
        "whilst": "whilst",
        "making": "making",
        "automating": "automating",
        "using": "using",
        "maintain": "maintain",
        "provide": "provide",
        "follow": "follow",
        "enhance": "enhance",
        "needed": "needed",
        "Ensure": "Ensure",
        "meets": "meets",
        "Demonstrate": "Demonstrate",
        "adapt": "adapt",
        "Required": "Required",
        "Working": "Working",
        "adore": "adore",
        "working": "working",
        "paced": "paced",
        "selecting": "selecting",
        "excel": "excel",
        "are": "are",
        "looking": "looking",
        "become": "become",
        "proficient": "proficient",
        "Should": "Should",
        "consumed/worked": "consumed/worked",
        "skills": "skills",
        "Works": "Works",
        "deadline": "deadline",
        "employeePosted": "employeePosted"
      },
      "ADJ": {
        "new": "new",
        "artificial": "artificial",
        "desirable": "desirable",
        "various": "various",
        "technical": "technical",
        "individual": "individual",
        "functional": "functional",
        "detailed": "detailed",
        "overall": "overall",
        "pressurized": "pressurized",
        "critical": "critical",
        "cloud": "cloud",
        "smart": "smart",
        "update": "update",
        "best": "best",
        "Visible": "Visible",
        "team": "team",
        "similar": "similar",
        "big-scale": "big-scale",
        "agile": "agile",
        "solid": "solid",
        "hands-on": "hands-on",
        "diverse": "diverse",
        "excellent": "excellent",
        "analytical": "analytical",
        "problem-solving": "problem-solving",
        "strategic": "strategic",
        "successful": "successful",
        "Good": "Good",
        "such": "such",
        "written/Oral": "written/Oral",
        "Flexible": "Flexible",
        "linear": "linear",
        "collaborative": "collaborative",
        "fast": "fast",
        "willing": "willing",
        "major": "major",
        "relational": "relational"
      },
      "PRT": {
        "to": "to",
        "'s": "'s"
      },
      "NUM": {}
    }
  },
  "223333515": {
    "Company": "Aclat Inc",
    "Job Title": "Sr. Software Engineer",
    "Job Details": "DescriptionSENIOR SOFTWARE ENGINEERJOB SUMMARY: The Software Engineer designs and develops internal and external business systems/applications, systems interfaces, databases, reporting, or business intelligence systems, as required to deliver new systems functionality supporting corporate business objectives|||| RESPONSIBILITIES: Strategy Owns the technical vision and development of a sub domain or capability||||Technology and System Develops web, mobile and user interface (UI) applications to deliver new systems functionality supporting corporate business objectives|||| Leads moderately complex projects|||| Utilizes development skills to build software and unit test new systems functionality per technical specifications, with deliverables to include builds and releases|||| Ensures Continuous Integration and Build is in place||||Maintains technical skills and expertise through continuing education and training||||Project Management Translates business, and functional requirements into documented technical specifications or User Stories|||| Communicates design, requirements, functionality, and limitations of systems/applications|||| Utilizes development skills to build (code) and unit test new systems functionality per technical specifications, with deliverables to include code builds and documented unit test results|||| Develops or updates support documentation as needed by the DecOps function and lead Peer Review to allow acceptance of systems changes into production|||| Oversees build and unit test production deployment packages|||| Facilitates/leads reviews (walkthroughs) or grooming sessions and demos of technical specifications and program code with other members of the technical team, communicating design, requirements, feature set, functionality and limitations of systems/applications to team and development lead|||| Utilizes product lifecycle methodology as a guide for development activities|||| Provides on-call and after hours support as required for production releases and to respond and provide active resolution support on production outages||||Contribute to and work to meet project schedules||||Relationship and People Management ▪ Performs peer reviews|||| Collaborates with architects and other Software Engineers on design|||| Collaborates with other Business and IT partner teams on successful delivery of product enhancements and support|||| Occassionally supervises contract resources||||MINIMUM REQUIRED:Minimum 5 years’ Application Development Experience|||| Minimum 5 years’ professional experience designing and developing applications on one RDBMS (Oracle or SQL 2000)|||| Minimum 5 years’ professional experience using 3 or more development languages or tools (e||||g||||, C#, ASP||||Net, J2EE Application Framework, Siebel, Oblix, etc||||)|||| Minimum 5 years’ professional experience designing and developing applications on one operating system (Unix or Windows 2000) or designing complex multi-tiered applications|||| Minimum of 5 years’ work experience as a Software Engineer is desirable, preferably in the wireless industry|||| Has had development experience on at least 4 projects with total project team size greater than 3 team members and has acted as lead Software Engineer on at least one project impacting multiple business units and providing technical leadership for at least 3 Software Engineers|||| Has experience mentoring other members of technical/development staff|||| Has experience working with at least 3 business applications/systems and has also provided tier 4 production support||||Specific work experience/skills required for each individual position to be updated by the hiring manager as these will vary depending upon whether the position develops user interfaces, middle tier and/or interfaces, database, business intelligence, or packaged applications like Siebel or Rightpoint||||EDUCATION: Bachelor’s Degree|||| Bachelor’s degree in Computer Science or a related field||||TRAVEL: May require up to 10% of domestic overnight travel within the region, and occasional trips to the Bellevue Headquarters||||Must be able to communicate with others effectively through written communication methods|||| Must be able to communicate (talking, hearing, etc||||) with others effectively through oral communication methods||||This position requires working with a computer (keyboard/mouse), telephone, and/or calculator; or, other repetitive use of hands||||The Rate is 50-55 W2 we pay to candidate|||| Lower the best and need local to Atlanta, GAJob DetailsSalary$50 - $55 Per HourJob Typefulltime, contractPosted 5 days ago||||",
    "KeyWords": {
      "NOUN": {
        "SOFTWARE": "SOFTWARE",
        "ENGINEERJOB": "ENGINEERJOB",
        "SUMMARY": "SUMMARY",
        "Software": "Software",
        "Engineer": "Engineer",
        "designs": "designs",
        "business": "business",
        "systems/applications": "systems/applications",
        "systems": "systems",
        "interfaces": "interfaces",
        "databases": "databases",
        "reporting": "reporting",
        "intelligence": "intelligence",
        "functionality": "functionality",
        "objectives": "objectives",
        "RESPONSIBILITIES": "RESPONSIBILITIES",
        "Strategy": "Strategy",
        "Owns": "Owns",
        "vision": "vision",
        "development": "development",
        "sub": "sub",
        "domain": "domain",
        "capability": "capability",
        "Technology": "Technology",
        "System": "System",
        "Develops": "Develops",
        "web": "web",
        "interface": "interface",
        "UI": "UI",
        "applications": "applications",
        "Leads": "Leads",
        "projects": "projects",
        "Utilizes": "Utilizes",
        "skills": "skills",
        "software": "software",
        "unit": "unit",
        "specifications": "specifications",
        "deliverables": "deliverables",
        "builds": "builds",
        "releases": "releases",
        "Ensures": "Ensures",
        "Integration": "Integration",
        "Build": "Build",
        "place": "place",
        "Maintains": "Maintains",
        "expertise": "expertise",
        "education": "education",
        "training": "training",
        "Project": "Project",
        "Management": "Management",
        "Translates": "Translates",
        "requirements": "requirements",
        "User": "User",
        "Stories": "Stories",
        "Communicates": "Communicates",
        "design": "design",
        "limitations": "limitations",
        "code": "code",
        "test": "test",
        "results": "results",
        "support": "support",
        "documentation": "documentation",
        "DecOps": "DecOps",
        "function": "function",
        "Peer": "Peer",
        "Review": "Review",
        "acceptance": "acceptance",
        "changes": "changes",
        "production": "production",
        "deployment": "deployment",
        "packages": "packages",
        "Facilitates/leads": "Facilitates/leads",
        "walkthroughs": "walkthroughs",
        "sessions": "sessions",
        "demos": "demos",
        "program": "program",
        "members": "members",
        "team": "team",
        "feature": "feature",
        "lead": "lead",
        "product": "product",
        "lifecycle": "lifecycle",
        "methodology": "methodology",
        "guide": "guide",
        "activities": "activities",
        "Provides": "Provides",
        "hours": "hours",
        "resolution": "resolution",
        "outages": "outages",
        "Contribute": "Contribute",
        "schedules": "schedules",
        "Relationship": "Relationship",
        "People": "People",
        "Performs": "Performs",
        "reviews": "reviews",
        "Collaborates": "Collaborates",
        "architects": "architects",
        "Engineers": "Engineers",
        "Business": "Business",
        "IT": "IT",
        "partner": "partner",
        "teams": "teams",
        "delivery": "delivery",
        "enhancements": "enhancements",
        "Occassionally": "Occassionally",
        "contract": "contract",
        "resources": "resources",
        "MINIMUM": "MINIMUM",
        "years": "years",
        "Application": "Application",
        "Development": "Development",
        "Experience": "Experience",
        "Minimum": "Minimum",
        "experience": "experience",
        "designing": "designing",
        "RDBMS": "RDBMS",
        "Oracle": "Oracle",
        "SQL": "SQL",
        "languages": "languages",
        "tools": "tools",
        "g.": "g.",
        "ASP": "ASP",
        "Net": "Net",
        "J2EE": "J2EE",
        "Framework": "Framework",
        "Siebel": "Siebel",
        "Oblix": "Oblix",
        "operating": "operating",
        "system": "system",
        "Unix": "Unix",
        "Windows": "Windows",
        "work": "work",
        "wireless": "wireless",
        "industry": "industry",
        "Has": "Has",
        "project": "project",
        "size": "size",
        "units": "units",
        "leadership": "leadership",
        "staff": "staff",
        "applications/systems": "applications/systems",
        "tier": "tier",
        "experience/skills": "experience/skills",
        "position": "position",
        "hiring": "hiring",
        "manager": "manager",
        "and/or": "and/or",
        "database": "database",
        "Rightpoint": "Rightpoint",
        "EDUCATION": "EDUCATION",
        "Bachelor": "Bachelor",
        "Degree": "Degree",
        "degree": "degree",
        "Computer": "Computer",
        "Science": "Science",
        "field": "field",
        "TRAVEL": "TRAVEL",
        "May": "May",
        "travel": "travel",
        "region": "region",
        "trips": "trips",
        "Bellevue": "Bellevue",
        "Headquarters": "Headquarters",
        "Must": "Must",
        "others": "others",
        "communication": "communication",
        "methods": "methods",
        "hearing": "hearing",
        "computer": "computer",
        "keyboard/mouse": "keyboard/mouse",
        "telephone": "telephone",
        "calculator": "calculator",
        "use": "use",
        "hands": "hands",
        "Rate": "Rate",
        "W2": "W2",
        "Atlanta": "Atlanta",
        "GAJob": "GAJob",
        "DetailsSalary": "DetailsSalary",
        "Per": "Per",
        "HourJob": "HourJob",
        "Typefulltime": "Typefulltime",
        "days": "days"
      },
      "VERB": {
        "required": "required",
        "deliver": "deliver",
        "supporting": "supporting",
        "build": "build",
        "test": "test",
        "include": "include",
        "is": "is",
        "continuing": "continuing",
        "documented": "documented",
        "needed": "needed",
        "allow": "allow",
        "reviews": "reviews",
        "grooming": "grooming",
        "communicating": "communicating",
        "set": "set",
        "team": "team",
        "respond": "respond",
        "provide": "provide",
        "work": "work",
        "meet": "meet",
        "peer": "peer",
        "supervises": "supervises",
        "developing": "developing",
        "using": "using",
        "designing": "designing",
        "had": "had",
        "has": "has",
        "acted": "acted",
        "impacting": "impacting",
        "providing": "providing",
        "mentoring": "mentoring",
        "working": "working",
        "provided": "provided",
        "be": "be",
        "updated": "updated",
        "will": "will",
        "vary": "vary",
        "depending": "depending",
        "develops": "develops",
        "packaged": "packaged",
        "require": "require",
        "communicate": "communicate",
        "written": "written",
        "talking": "talking",
        "requires": "requires",
        "pay": "pay",
        "candidate": "candidate",
        "need": "need",
        "contractPosted": "contractPosted"
      },
      "ADJ": {
        "external": "external",
        "new": "new",
        "corporate": "corporate",
        "technical": "technical",
        "mobile": "mobile",
        "user": "user",
        "complex": "complex",
        "Continuous": "Continuous",
        "functional": "functional",
        "documented": "documented",
        "updates": "updates",
        "lead": "lead",
        "build": "build",
        "other": "other",
        "Utilizes": "Utilizes",
        "on-call": "on-call",
        "active": "active",
        "project": "project",
        "successful": "successful",
        "REQUIRED": "REQUIRED",
        "Minimum": "Minimum",
        "professional": "professional",
        "more": "more",
        "e.": "e.",
        "multi-tiered": "multi-tiered",
        "desirable": "desirable",
        "least": "least",
        "total": "total",
        "greater": "greater",
        "multiple": "multiple",
        "technical/development": "technical/development",
        "Specific": "Specific",
        "individual": "individual",
        "middle": "middle",
        "tier": "tier",
        "related": "related",
        "domestic": "domestic",
        "overnight": "overnight",
        "occasional": "occasional",
        "able": "able",
        "oral": "oral",
        "and/or": "and/or",
        "repetitive": "repetitive",
        "50-55": "50-55",
        "Lower": "Lower",
        "best": "best",
        "local": "local"
      },
      "PRT": {
        "to": "to"
      },
      "NUM": {
        "10": "10",
        "50": "50",
        "55": "55",
        "2000": "2000",
        "one": "one"
      },
      "X": {
        "etc": "etc"
      }
    }
  },
  "223335079": {
    "Company": "Jobot",
    "Job Title": "Senior Software Engineer - Java/Python/AWS",
    "Job Details": "DescriptionRemote!This Jobot Job is hosted by: Madeline LazarusAre you a fit? Easy Apply now by clicking the \"Apply at employer's site\" button and sending us your resume||||Salary: $130,000 - $150,000 per yearA bit about us:We are looking for a Software Engineer/Cloud Engineer to join us in the effort of building our Healthcare financial management AI platform and solutions|||| Location: Seattle, WA, Nashville, TN or Atlanta, GA - remoteSalary: $80,000 - $150,000 (depends on level of experience, we are looking for various levels of experience)Are you passionate about building enterprise-class solutions using the latest cloud technologies and current development best practices? Are you ready to be a leader in implementing technologies such as Amazon Web Services and NoSQL databases in a DevOps organization that insists on 100% fault tolerant code, 100% automation of tests and infrastructure as code in an environment of continuous tests, continuous integration and continuous deployment?ent experienceWhy join us? Cutting Edge Technology company in Healthcare industry Vacation/PTO Medical Dental Vision Bonus 401kJob DetailsWhat you will be doing: Design, test, code and deliver high quality secure production software with completely automated tests suitable for cloud deployment at scale||||  Develop automated tests (TDD including unit, integration, smoke, acceptance tests) to achieve test coverage for continuous deployment and near 100% availability|||| Execute acceptance tests and maintain test artifacts in a shared repository||||  Add new tests when fixing defects||||   Collaborate with Tech Lead (TL) Cloud Engineer and Product Owner (PO) to refine user stories and acceptance criteria|||| Work with PO to confirm that the code and acceptance tests reflect the desired functionality|||| Work in small deliverable batches < 1 week to DOD|||| Participate in planning and in committing to team and individual objectives||||    Conduct research, spikes, design, prototyping and other innovation, exploration and learning activities||||    Trunk based development - commit new or modified code reviewed to the shared source code repository and master trunk daily||||    Pair with another Cloud Engineer when appropriate to develop code and associated automatic tests||||  Participate in continuous improvement of the software itself, team’s process, CI/CD and development environments, including infrastructure as code||||   Eliminate distractions, impediments and wasteful work to optimize flow and velocity||||   Use feature toggles, multi-versioning, short lived branches and other techniques to keep the trunk working and always deployable||||What you need in order to succeed: Professional experience with at least two modern programming languages such as C#, Java, Go, Python, etc||||   Experience with indexed data persistence such as Relational Databases (SQL) or NoSQL Data Stores||||   Ability to execute moderate complexity software engineering assignments when provided high level business requirements and technical design guidelines from an architect or senior engineer with minimal supervision||||   Ability to breakdown requirements into stories and provide estimates, perform code reviews, raise technical risk and create documentation||||    Experience providing low-level design using established enterprise standards and technology; strong debugging skills||||  Cloud application development, including serverless and containerized in AWS   Proficiency in developing objected-oriented software, with deep experience in one or more relevant languages   Experience building complex software systems that have been successfully delivered to customers, using microservices, loosely coupled architecture   Experience with agile program management methodologies||||    Willingness to own all stages of development process: requirements, design, implementation, testing, and operational supportInterested in hearing more? Easy Apply now by clicking the \"Apply at employer's site\" button||||Job DetailsSalary$130000 - $150000 Per YearJob Typefulltime, employeePosted 5 days ago||||",
    "KeyWords": {
      "NOUN": {
        "Jobot": "Jobot",
        "Job": "Job",
        "Madeline": "Madeline",
        "LazarusAre": "LazarusAre",
        "fit": "fit",
        "Easy": "Easy",
        "Apply": "Apply",
        "employer": "employer",
        "site": "site",
        "button": "button",
        "resume": "resume",
        "yearA": "yearA",
        "bit": "bit",
        "Software": "Software",
        "Engineer/Cloud": "Engineer/Cloud",
        "Engineer": "Engineer",
        "effort": "effort",
        "Healthcare": "Healthcare",
        "management": "management",
        "AI": "AI",
        "platform": "platform",
        "solutions": "solutions",
        "Location": "Location",
        "Seattle": "Seattle",
        "WA": "WA",
        "Nashville": "Nashville",
        "TN": "TN",
        "Atlanta": "Atlanta",
        "GA": "GA",
        "remoteSalary": "remoteSalary",
        "depends": "depends",
        "level": "level",
        "experience": "experience",
        "levels": "levels",
        "cloud": "cloud",
        "technologies": "technologies",
        "development": "development",
        "practices": "practices",
        "leader": "leader",
        "Amazon": "Amazon",
        "Web": "Web",
        "Services": "Services",
        "NoSQL": "NoSQL",
        "DevOps": "DevOps",
        "organization": "organization",
        "fault": "fault",
        "code": "code",
        "automation": "automation",
        "tests": "tests",
        "infrastructure": "infrastructure",
        "environment": "environment",
        "integration": "integration",
        "deployment": "deployment",
        "experienceWhy": "experienceWhy",
        "Edge": "Edge",
        "Technology": "Technology",
        "company": "company",
        "industry": "industry",
        "Vacation/PTO": "Vacation/PTO",
        "Medical": "Medical",
        "Dental": "Dental",
        "Vision": "Vision",
        "Bonus": "Bonus",
        "DetailsWhat": "DetailsWhat",
        "Design": "Design",
        "test": "test",
        "quality": "quality",
        "secure": "secure",
        "production": "production",
        "software": "software",
        "scale": "scale",
        "Develop": "Develop",
        "TDD": "TDD",
        "unit": "unit",
        "smoke": "smoke",
        "acceptance": "acceptance",
        "coverage": "coverage",
        "availability": "availability",
        "artifacts": "artifacts",
        "repository": "repository",
        "Add": "Add",
        "defects": "defects",
        "Collaborate": "Collaborate",
        "Tech": "Tech",
        "Lead": "Lead",
        "TL": "TL",
        "Cloud": "Cloud",
        "Product": "Product",
        "Owner": "Owner",
        "PO": "PO",
        "stories": "stories",
        "criteria": "criteria",
        "Work": "Work",
        "functionality": "functionality",
        "batches": "batches",
        "week": "week",
        "DOD": "DOD",
        "Participate": "Participate",
        "planning": "planning",
        "team": "team",
        "objectives": "objectives",
        "Conduct": "Conduct",
        "research": "research",
        "spikes": "spikes",
        "design": "design",
        "prototyping": "prototyping",
        "innovation": "innovation",
        "exploration": "exploration",
        "learning": "learning",
        "activities": "activities",
        "Trunk": "Trunk",
        "commit": "commit",
        "source": "source",
        "master": "master",
        "trunk": "trunk",
        "Pair": "Pair",
        "appropriate": "appropriate",
        "improvement": "improvement",
        "process": "process",
        "CI/CD": "CI/CD",
        "environments": "environments",
        "Eliminate": "Eliminate",
        "distractions": "distractions",
        "impediments": "impediments",
        "work": "work",
        "flow": "flow",
        "velocity": "velocity",
        "Use": "Use",
        "feature": "feature",
        "toggles": "toggles",
        "multi-versioning": "multi-versioning",
        "branches": "branches",
        "techniques": "techniques",
        "order": "order",
        "languages": "languages",
        "Java": "Java",
        "Go": "Go",
        "Python": "Python",
        "Experience": "Experience",
        "data": "data",
        "persistence": "persistence",
        "Databases": "Databases",
        "SQL": "SQL",
        "Data": "Data",
        "Stores": "Stores",
        "Ability": "Ability",
        "complexity": "complexity",
        "engineering": "engineering",
        "assignments": "assignments",
        "business": "business",
        "requirements": "requirements",
        "guidelines": "guidelines",
        "architect": "architect",
        "engineer": "engineer",
        "supervision": "supervision",
        "estimates": "estimates",
        "perform": "perform",
        "reviews": "reviews",
        "risk": "risk",
        "documentation": "documentation",
        "enterprise": "enterprise",
        "standards": "standards",
        "technology": "technology",
        "debugging": "debugging",
        "skills": "skills",
        "application": "application",
        "serverless": "serverless",
        "AWS": "AWS",
        "Proficiency": "Proficiency",
        "building": "building",
        "complex": "complex",
        "systems": "systems",
        "customers": "customers",
        "microservices": "microservices",
        "architecture": "architecture",
        "program": "program",
        "methodologies": "methodologies",
        "Willingness": "Willingness",
        "stages": "stages",
        "implementation": "implementation",
        "DetailsSalary": "DetailsSalary",
        "Per": "Per",
        "YearJob": "YearJob",
        "Typefulltime": "Typefulltime",
        "days": "days"
      },
      "VERB": {
        "hosted": "hosted",
        "clicking": "clicking",
        "sending": "sending",
        "are": "are",
        "looking": "looking",
        "join": "join",
        "building": "building",
        "Are": "Are",
        "passionate": "passionate",
        "using": "using",
        "be": "be",
        "implementing": "implementing",
        "databases": "databases",
        "insists": "insists",
        "Cutting": "Cutting",
        "will": "will",
        "doing": "doing",
        "deliver": "deliver",
        "automated": "automated",
        "including": "including",
        "achieve": "achieve",
        "maintain": "maintain",
        "fixing": "fixing",
        "refine": "refine",
        "confirm": "confirm",
        "reflect": "reflect",
        "committing": "committing",
        "based": "based",
        "modified": "modified",
        "reviewed": "reviewed",
        "shared": "shared",
        "develop": "develop",
        "associated": "associated",
        "Participate": "Participate",
        "optimize": "optimize",
        "lived": "lived",
        "keep": "keep",
        "working": "working",
        "need": "need",
        "succeed": "succeed",
        "programming": "programming",
        "execute": "execute",
        "provided": "provided",
        "breakdown": "breakdown",
        "provide": "provide",
        "raise": "raise",
        "create": "create",
        "providing": "providing",
        "established": "established",
        "containerized": "containerized",
        "developing": "developing",
        "have": "have",
        "been": "been",
        "delivered": "delivered",
        "own": "own",
        "testing": "testing",
        "supportInterested": "supportInterested",
        "hearing": "hearing",
        "employeePosted": "employeePosted"
      },
      ".": {
        "''": "''",
        "``": "``"
      },
      "PRT": {
        "to": "to",
        "'s": "'s"
      },
      "ADJ": {
        "financial": "financial",
        "various": "various",
        "enterprise-class": "enterprise-class",
        "latest": "latest",
        "current": "current",
        "best": "best",
        "ready": "ready",
        "such": "such",
        "tolerant": "tolerant",
        "continuous": "continuous",
        "ent": "ent",
        "high": "high",
        "suitable": "suitable",
        "cloud": "cloud",
        "Execute": "Execute",
        "shared": "shared",
        "new": "new",
        "user": "user",
        "desired": "desired",
        "small": "small",
        "deliverable": "deliverable",
        "individual": "individual",
        "other": "other",
        "automatic": "automatic",
        "wasteful": "wasteful",
        "short": "short",
        "deployable": "deployable",
        "Professional": "Professional",
        "least": "least",
        "modern": "modern",
        "indexed": "indexed",
        "Relational": "Relational",
        "moderate": "moderate",
        "technical": "technical",
        "senior": "senior",
        "minimal": "minimal",
        "low-level": "low-level",
        "strong": "strong",
        "objected-oriented": "objected-oriented",
        "deep": "deep",
        "more": "more",
        "relevant": "relevant",
        "coupled": "coupled",
        "agile": "agile",
        "operational": "operational"
      },
      "NUM": {
        "100": "100",
        "130000": "130000",
        "150000": "150000",
        "150,000": "150,000",
        "80,000": "80,000",
        "401kJob": "401kJob",
        "two": "two",
        "one": "one"
      },
      "X": {}
    }
  },
  "223339190": {
    "Company": "NTT DATA Services",
    "Job Title": "Senior Device Driver Software Engineer",
    "Job Details": "DescriptionSenior Device Driver Software Engineer Location: Remote/ GA post COVID RestrictionsDuration: 6+ month Contract, potential for extensions Overview: The Senior Device Driver Software Engineer will be responsible for developing new and update existing device drivers for DYMO label printers across multiple platforms||||This position will: Provide the opportunity to learn the latest Windows and Mac OS X technologies Provide the opportunity to learn and work in a variety of platforms including iOS and Android Be part of a small focused team that will influence the future direction of DYMO SoftwareQualifications Bachelor's degree in Computer Science or related degree required 4+ years of Software Development experience in C and C++ required Knowledge of Windows printer device drivers required Knowledge of CUPS drivers required Strong debugging skills, especially regarding threads and memory management required Knowledge of USB, Bluetooth and TCP/IP required  Knowledge of the Microsoft Windows HLK process required Demonstrates expert knowledge of Software Design, Development, and best practices Demonstrates strong communication skills (verbal and written) Demonstrates strong critical thinking and problem-solving skills Demonstrates fluency in English Acts as a highly self-motivated and detail oriented player Acts as a strong team player Fast learner|||| Willing and able to quickly get up to speed with new technologies and skills Knowledge of printing systems, fonts or graphics a plus Knowledge of Agile/Scrum development methodologies a plus Knowledge of Bitbucket/Git and TeamCity a plus Experience in development in a cross-platform environment is a plusThe Company is an equal opportunity employer and makes employment decisions on the basis of merit and business needs|||| The Company will consider all qualified applicants for employment without regard to race, color, religious creed, citizenship, national origin, ancestry, age, sex, sexual orientation, genetic information, physical or mental disability, veteran or marital status, or any other class protected by law|||| To comply with applicable laws ensuring equal employment opportunities to qualified individuals with a disability, the Company will make reasonable accommodations for the known physical or mental limitations of an otherwise qualified individual with a disability who is an applicant or an employee unless undue hardship to the Company would result||||Job DetailsJob Typefulltime, employeePosted 5 days ago||||",
    "KeyWords": {
      "NOUN": {
        "Device": "Device",
        "Driver": "Driver",
        "Software": "Software",
        "Engineer": "Engineer",
        "Location": "Location",
        "Remote/": "Remote/",
        "GA": "GA",
        "post": "post",
        "COVID": "COVID",
        "RestrictionsDuration": "RestrictionsDuration",
        "month": "month",
        "Contract": "Contract",
        "potential": "potential",
        "extensions": "extensions",
        "Overview": "Overview",
        "Senior": "Senior",
        "device": "device",
        "drivers": "drivers",
        "DYMO": "DYMO",
        "label": "label",
        "printers": "printers",
        "platforms": "platforms",
        "position": "position",
        "opportunity": "opportunity",
        "Windows": "Windows",
        "Mac": "Mac",
        "OS": "OS",
        "technologies": "technologies",
        "variety": "variety",
        "iOS": "iOS",
        "Android": "Android",
        "Be": "Be",
        "part": "part",
        "team": "team",
        "direction": "direction",
        "SoftwareQualifications": "SoftwareQualifications",
        "Bachelor": "Bachelor",
        "degree": "degree",
        "Computer": "Computer",
        "Science": "Science",
        "years": "years",
        "Development": "Development",
        "experience": "experience",
        "C++": "C++",
        "Knowledge": "Knowledge",
        "printer": "printer",
        "CUPS": "CUPS",
        "Strong": "Strong",
        "skills": "skills",
        "threads": "threads",
        "memory": "memory",
        "management": "management",
        "USB": "USB",
        "Bluetooth": "Bluetooth",
        "TCP/IP": "TCP/IP",
        "Microsoft": "Microsoft",
        "HLK": "HLK",
        "process": "process",
        "Demonstrates": "Demonstrates",
        "knowledge": "knowledge",
        "Design": "Design",
        "practices": "practices",
        "communication": "communication",
        "thinking": "thinking",
        "fluency": "fluency",
        "Acts": "Acts",
        "detail": "detail",
        "player": "player",
        "Fast": "Fast",
        "learner": "learner",
        "Willing": "Willing",
        "systems": "systems",
        "fonts": "fonts",
        "graphics": "graphics",
        "Agile/Scrum": "Agile/Scrum",
        "development": "development",
        "Bitbucket/Git": "Bitbucket/Git",
        "TeamCity": "TeamCity",
        "Experience": "Experience",
        "environment": "environment",
        "Company": "Company",
        "employer": "employer",
        "employment": "employment",
        "decisions": "decisions",
        "basis": "basis",
        "merit": "merit",
        "business": "business",
        "needs": "needs",
        "applicants": "applicants",
        "regard": "regard",
        "race": "race",
        "color": "color",
        "creed": "creed",
        "citizenship": "citizenship",
        "origin": "origin",
        "ancestry": "ancestry",
        "age": "age",
        "sex": "sex",
        "orientation": "orientation",
        "information": "information",
        "disability": "disability",
        "veteran": "veteran",
        "status": "status",
        "class": "class",
        "law": "law",
        "laws": "laws",
        "opportunities": "opportunities",
        "individuals": "individuals",
        "accommodations": "accommodations",
        "limitations": "limitations",
        "otherwise": "otherwise",
        "applicant": "applicant",
        "employee": "employee",
        "hardship": "hardship",
        "Job": "Job",
        "DetailsJob": "DetailsJob",
        "Typefulltime": "Typefulltime",
        "days": "days"
      },
      "NUM": {
        "4+": "4+"
      },
      "VERB": {
        "be": "be",
        "developing": "developing",
        "existing": "existing",
        "will": "will",
        "Provide": "Provide",
        "learn": "learn",
        "work": "work",
        "including": "including",
        "influence": "influence",
        "related": "related",
        "required": "required",
        "debugging": "debugging",
        "regarding": "regarding",
        "Demonstrates": "Demonstrates",
        "written": "written",
        "oriented": "oriented",
        "Acts": "Acts",
        "get": "get",
        "speed": "speed",
        "printing": "printing",
        "methodologies": "methodologies",
        "is": "is",
        "makes": "makes",
        "consider": "consider",
        "protected": "protected",
        "comply": "comply",
        "ensuring": "ensuring",
        "make": "make",
        "qualified": "qualified",
        "would": "would",
        "result": "result",
        "employeePosted": "employeePosted"
      },
      "ADJ": {
        "new": "new",
        "update": "update",
        "multiple": "multiple",
        "latest": "latest",
        "small": "small",
        "focused": "focused",
        "future": "future",
        "expert": "expert",
        "best": "best",
        "strong": "strong",
        "verbal": "verbal",
        "critical": "critical",
        "problem-solving": "problem-solving",
        "English": "English",
        "self-motivated": "self-motivated",
        "able": "able",
        "plus": "plus",
        "cross-platform": "cross-platform",
        "plusThe": "plusThe",
        "equal": "equal",
        "qualified": "qualified",
        "religious": "religious",
        "national": "national",
        "sexual": "sexual",
        "genetic": "genetic",
        "physical": "physical",
        "mental": "mental",
        "marital": "marital",
        "other": "other",
        "applicable": "applicable",
        "reasonable": "reasonable",
        "known": "known",
        "individual": "individual",
        "undue": "undue"
      },
      "PRT": {
        "to": "to",
        "'s": "'s",
        "up": "up",
        "To": "To"
      }
    }
  },
  "223348697": {
    "Company": "CyberCoders",
    "Job Title": "REMOTE - Senior C#/.NET Engineer - SaaS",
    "Job Details": "DescriptionIf you are a Senior C#/||||NET Engineer with experience, please read on!Top Reasons to Work with UsWe provide user-friendly software that  simplifies the process of claims and attachment management, facilitates secure communications, speeds up payments, and helps dental practices thrive||||\nOur mission is to empower our clients to achieve improved performance and cost-savings through a robust portfolio of electronic healthcare communication and secure information exchange solutions||||What You Will Be DoingYour primary responsibility will be developing software services/programs in both on-premises and SaaS solutions|||| Our team is full stack  dealing with database design to API development to front end UI in the healthcare industry|||| \n\nResponsibilities:\n- New and existing feature enhancement\n- Maintaining on-premises suite and back-end applications (||||NET 4||||8)\n- Designing and developing solutions in Amazon Web Services\n- Database optimization\n- Developing new services that provide capabilities our products\n- Building custom solutions for specific customer integrationsWhat You Need for this PositionMUST HAVE:- BS in related field OR equivalent professional experience\n- 5+ years of ASP||||NET/C# development experience\n- 3+ years of AWS experience: Cognito, Lambdas, Dynamo, RDS\n- Javascript - preferably Angular||||js\n- Web API development\n- SQL\n\nNICE TO HAVE:\n- SaaS industry experience\n- Healthcare industry experience\n- SaaS\n- PlasticWhat's In It for You- Competitive Salary DOE- Comprehensive Benefits Package\n- 401k with match\n- Generous PTO\n- Referral Program\n- Remote workSo, if you are a Senior C#/||||NET Engineer with experience, please apply today!Job DetailsSalary$130000 - $150000 Per YearJob Typefulltime, employeePosted 4 days ago||||",
    "KeyWords": {
      "NOUN": {
        "Senior": "Senior",
        "NET": "NET",
        "Engineer": "Engineer",
        "experience": "experience",
        "please": "please",
        "Reasons": "Reasons",
        "UsWe": "UsWe",
        "software": "software",
        "process": "process",
        "claims": "claims",
        "management": "management",
        "communications": "communications",
        "payments": "payments",
        "practices": "practices",
        "mission": "mission",
        "clients": "clients",
        "performance": "performance",
        "cost-savings": "cost-savings",
        "portfolio": "portfolio",
        "healthcare": "healthcare",
        "communication": "communication",
        "information": "information",
        "exchange": "exchange",
        "solutions": "solutions",
        "DoingYour": "DoingYour",
        "responsibility": "responsibility",
        "services/programs": "services/programs",
        "on-premises": "on-premises",
        "SaaS": "SaaS",
        "team": "team",
        "stack": "stack",
        "database": "database",
        "design": "design",
        "API": "API",
        "development": "development",
        "end": "end",
        "UI": "UI",
        "industry": "industry",
        "Responsibilities": "Responsibilities",
        "New": "New",
        "feature": "feature",
        "applications": "applications",
        "Amazon": "Amazon",
        "Web": "Web",
        "Services": "Services",
        "Database": "Database",
        "optimization": "optimization",
        "services": "services",
        "products": "products",
        "Building": "Building",
        "custom": "custom",
        "customer": "customer",
        "PositionMUST": "PositionMUST",
        "HAVE": "HAVE",
        "BS": "BS",
        "field": "field",
        "OR": "OR",
        "years": "years",
        "ASP": "ASP",
        "NET/C": "NET/C",
        "AWS": "AWS",
        "Cognito": "Cognito",
        "Lambdas": "Lambdas",
        "Dynamo": "Dynamo",
        "RDS": "RDS",
        "Javascript": "Javascript",
        "Angular": "Angular",
        "js": "js",
        "SQL": "SQL",
        "NICE": "NICE",
        "TO": "TO",
        "Healthcare": "Healthcare",
        "You-": "You-",
        "Competitive": "Competitive",
        "Salary": "Salary",
        "DOE-": "DOE-",
        "Comprehensive": "Comprehensive",
        "Benefits": "Benefits",
        "Package": "Package",
        "match": "match",
        "PTO": "PTO",
        "Program": "Program",
        "Remote": "Remote",
        "workSo": "workSo",
        "today": "today",
        "Job": "Job",
        "DetailsSalary": "DetailsSalary",
        "Per": "Per",
        "YearJob": "YearJob",
        "Typefulltime": "Typefulltime",
        "days": "days"
      },
      "VERB": {
        "read": "read",
        "Work": "Work",
        "provide": "provide",
        "simplifies": "simplifies",
        "facilitates": "facilitates",
        "speeds": "speeds",
        "helps": "helps",
        "thrive": "thrive",
        "is": "is",
        "empower": "empower",
        "achieve": "achieve",
        "improved": "improved",
        "secure": "secure",
        "Will": "Will",
        "Be": "Be",
        "will": "will",
        "be": "be",
        "developing": "developing",
        "dealing": "dealing",
        "existing": "existing",
        "Maintaining": "Maintaining",
        "Designing": "Designing",
        "Developing": "Developing",
        "capabilities": "capabilities",
        "Need": "Need",
        "'s": "'s",
        "are": "are",
        "please": "please",
        "apply": "apply",
        "employeePosted": "employeePosted"
      },
      "ADJ": {
        "user-friendly": "user-friendly",
        "attachment": "attachment",
        "secure": "secure",
        "dental": "dental",
        "robust": "robust",
        "electronic": "electronic",
        "primary": "primary",
        "full": "full",
        "front": "front",
        "enhancement": "enhancement",
        "suite": "suite",
        "back-end": "back-end",
        "new": "new",
        "specific": "specific",
        "related": "related",
        "equivalent": "equivalent",
        "professional": "professional",
        "Generous": "Generous",
        "Referral": "Referral"
      },
      "PRT": {
        "up": "up",
        "to": "to"
      },
      ".": {},
      "NUM": {
        "130000": "130000",
        "150000": "150000",
        "3+": "3+",
        "401k": "401k"
      }
    }
  },
  "223351271": {
    "Company": "Resolution Technologies",
    "Job Title": "Mulesoft Developer",
    "Job Details": "DescriptionMulesoft Developer\nMulesoft Developer\n\nWe are looking for a Mulesoft Developer to drive forward API development and refactoring as we modernize and transition our legacy APIs to Mulesoft platform|||| The Mulesoft Developer will be part of our North American IT organization and will work across multiple engineering teams and core systems||||\n\nNow’s a great time to join a team embarking on transformation||||\nMulesoft Developer ResponsibilitiesAlways make security the top priorityAutomate what should be automatedDevelop integration flows in MuleSoft with integrations to APIs, databases, messaging, & files||||Develop automated tests in MuleSoft and partner with the Cloud Engineering team for integration into CI/CD processesTroubleshoot and fix issuesCollaborate and pair with multiple teams to share knowledge and improve everyone’s skillsDevelop a deep understanding of KPI’s that affect each line of businessDefine and document processes and analyses\nMulesoft Developer Required Skills5+ years’ hands-on experience in software engineering3+ years’ iPaaS and API Development experience using MuleSoftExperience building high volume interfacesExperience building composable APIsGood understanding of integration design patterns & best practicesKnowledge of SOAP, REST, and GraphQLKnowledge of industry trends and relevant application technologiesAdept at mastering new technology, processes and software applicationsDedicated to quality and customer satisfaction, persistent about achieving project goalsInterpersonal skills that demonstrate collaboration, facilitation, influencing and negotiatingIn depth experience using Agile, Scrum and iterative development practices\nMulesoft Developer Desired SkillsExperience with MuleSoft Anypoint Platform, 4||||xMuleSoft certificationProficiency in Python or JavaB||||S|||| in Computer Science, Engineering, or equivalent experience\nPayments or Financial Services experienceJob DetailsSalary135000 Per HourPosted 4 days ago||||",
    "KeyWords": {
      "NOUN": {
        "Developer": "Developer",
        "Mulesoft": "Mulesoft",
        "API": "API",
        "development": "development",
        "refactoring": "refactoring",
        "legacy": "legacy",
        "APIs": "APIs",
        "platform": "platform",
        "part": "part",
        "IT": "IT",
        "organization": "organization",
        "engineering": "engineering",
        "teams": "teams",
        "core": "core",
        "systems": "systems",
        "time": "time",
        "team": "team",
        "transformation": "transformation",
        "ResponsibilitiesAlways": "ResponsibilitiesAlways",
        "security": "security",
        "priorityAutomate": "priorityAutomate",
        "integration": "integration",
        "MuleSoft": "MuleSoft",
        "integrations": "integrations",
        "files": "files",
        "Develop": "Develop",
        "tests": "tests",
        "partner": "partner",
        "Cloud": "Cloud",
        "Engineering": "Engineering",
        "CI/CD": "CI/CD",
        "processesTroubleshoot": "processesTroubleshoot",
        "issuesCollaborate": "issuesCollaborate",
        "pair": "pair",
        "share": "share",
        "knowledge": "knowledge",
        "everyone": "everyone",
        "understanding": "understanding",
        "KPI": "KPI",
        "line": "line",
        "businessDefine": "businessDefine",
        "document": "document",
        "processes": "processes",
        "analyses": "analyses",
        "Required": "Required",
        "Skills5+": "Skills5+",
        "years": "years",
        "experience": "experience",
        "software": "software",
        "iPaaS": "iPaaS",
        "Development": "Development",
        "MuleSoftExperience": "MuleSoftExperience",
        "building": "building",
        "volume": "volume",
        "interfacesExperience": "interfacesExperience",
        "APIsGood": "APIsGood",
        "design": "design",
        "practicesKnowledge": "practicesKnowledge",
        "SOAP": "SOAP",
        "REST": "REST",
        "GraphQLKnowledge": "GraphQLKnowledge",
        "industry": "industry",
        "trends": "trends",
        "application": "application",
        "technologiesAdept": "technologiesAdept",
        "technology": "technology",
        "quality": "quality",
        "customer": "customer",
        "satisfaction": "satisfaction",
        "persistent": "persistent",
        "project": "project",
        "skills": "skills",
        "collaboration": "collaboration",
        "facilitation": "facilitation",
        "depth": "depth",
        "Agile": "Agile",
        "Scrum": "Scrum",
        "practices": "practices",
        "Desired": "Desired",
        "SkillsExperience": "SkillsExperience",
        "Anypoint": "Anypoint",
        "Platform": "Platform",
        "certificationProficiency": "certificationProficiency",
        "Python": "Python",
        "JavaB": "JavaB",
        "S.": "S.",
        "Computer": "Computer",
        "Science": "Science",
        "Payments": "Payments",
        "Financial": "Financial",
        "Services": "Services",
        "experienceJob": "experienceJob",
        "DetailsSalary135000": "DetailsSalary135000",
        "Per": "Per",
        "days": "days"
      },
      "VERB": {
        "looking": "looking",
        "drive": "drive",
        "modernize": "modernize",
        "transition": "transition",
        "will": "will",
        "be": "be",
        "work": "work",
        "join": "join",
        "embarking": "embarking",
        "make": "make",
        "should": "should",
        "flows": "flows",
        "databases": "databases",
        "messaging": "messaging",
        "automated": "automated",
        "improve": "improve",
        "skillsDevelop": "skillsDevelop",
        "using": "using",
        "patterns": "patterns",
        "mastering": "mastering",
        "applicationsDedicated": "applicationsDedicated",
        "achieving": "achieving",
        "demonstrate": "demonstrate",
        "influencing": "influencing",
        "HourPosted": "HourPosted"
      },
      "PRT": {
        "to": "to"
      },
      "ADJ": {
        "American": "American",
        "multiple": "multiple",
        "great": "great",
        "top": "top",
        "automatedDevelop": "automatedDevelop",
        "fix": "fix",
        "deep": "deep",
        "affect": "affect",
        "hands-on": "hands-on",
        "engineering3+": "engineering3+",
        "high": "high",
        "composable": "composable",
        "best": "best",
        "relevant": "relevant",
        "new": "new",
        "goalsInterpersonal": "goalsInterpersonal",
        "negotiatingIn": "negotiatingIn",
        "iterative": "iterative",
        "xMuleSoft": "xMuleSoft",
        "equivalent": "equivalent"
      },
      "NUM": {}
    }
  },
  "223364242": {
    "Company": "Elgebra",
    "Job Title": "Full Stack Java Developer with AWS (Direct hire)",
    "Job Details": "DescriptionHighly energetic candidate with 8 years of work experience in IT industry||||· Must have programming experience with Core Java / J2EE application, XML and Web Services||||· Strong knowledge of Spring Framework & Spring Boot Application, Micro services, Spring Boot, Web services based on SOAP/REST· Familiarity with JavaScript frameworks such as Angular JS and React|||| Experience on Tomcat||||· Strong experience in writing complex SQL queries and Unix scripting||||· Strong AWS Experience including AWS CodeBuild, AWS CodeCommit, AWS CodePipeline , AWS Lambda, API Gateway, CloudFormation, Serverless Deployment· Must have work experience on AgileJob DetailsJob Typefulltime, employeePosted 4 days ago||||",
    "KeyWords": {
      "NOUN": {
        "candidate": "candidate",
        "years": "years",
        "work": "work",
        "experience": "experience",
        "IT": "IT",
        "industry": "industry",
        "Must": "Must",
        "Core": "Core",
        "Java": "Java",
        "J2EE": "J2EE",
        "application": "application",
        "XML": "XML",
        "Web": "Web",
        "Services": "Services",
        "Strong": "Strong",
        "knowledge": "knowledge",
        "Spring": "Spring",
        "Framework": "Framework",
        "Boot": "Boot",
        "Application": "Application",
        "Micro": "Micro",
        "services": "services",
        "SOAP/REST·": "SOAP/REST·",
        "Familiarity": "Familiarity",
        "JavaScript": "JavaScript",
        "frameworks": "frameworks",
        "Angular": "Angular",
        "JS": "JS",
        "React": "React",
        "Experience": "Experience",
        "Tomcat": "Tomcat",
        "SQL": "SQL",
        "queries": "queries",
        "Unix": "Unix",
        "AWS": "AWS",
        "CodeBuild": "CodeBuild",
        "CodeCommit": "CodeCommit",
        "CodePipeline": "CodePipeline",
        "Lambda": "Lambda",
        "API": "API",
        "Gateway": "Gateway",
        "CloudFormation": "CloudFormation",
        "Serverless": "Serverless",
        "Deployment·": "Deployment·",
        "AgileJob": "AgileJob",
        "DetailsJob": "DetailsJob",
        "Typefulltime": "Typefulltime",
        "days": "days"
      },
      "ADJ": {
        "such": "such",
        "Strong": "Strong",
        "complex": "complex"
      },
      "VERB": {
        "programming": "programming",
        "based": "based",
        "writing": "writing",
        "scripting": "scripting",
        "including": "including",
        "have": "have",
        "employeePosted": "employeePosted"
      }
    }
  },
  "223365198": {
    "Company": "Caresoft Inc.",
    "Job Title": "Java Web Developer",
    "Job Details": "DescriptionTitle/Role -   Java DeveloperLocation  -   Atlanta, GA 30303Duration  –   6- 12 monthsJob DescriptionOur client is seeking a qualified candidate for the position of Java Developer based in Atlanta, Georgia to work as a part of the Shines Applications Team||||The Java Developer responsibilities include the integration and design of new application systems and/or life-cycle enhancement to existing complex multi-platform (Java)our client is Responsible for determining the scope of the assigned project(s) by assessing requirements from business and technical/network personnel||||Responsible for evaluation and selection of the appropriate technical platform for the system||||Work will include integration planning, integration analysis across multiple technical platforms, integration analysis across client to include both global system design anddetailed program design for complex processes or interfaces, review of database design of new data structures, and suggested modifications to existing data structures||||Effectively documents and teaches the structure and function of the new application and/or enhancements resulting from the assigned project(s)to other Web Application Managers and senior technical personnel to insure that the new systems or enhancements operate smooth within environment||||Qualifications:Bachelor’s degree in Computer Science or equivalent||||years of experience web development experience which includes the programming/ development of web applications||||years of Team lead experience is desirable to apply for the jobyears of experience with Java/J2EE, Spring MVC, Hibernate, EJB, Spring||||years of experience of web development experience which includes the programming/ development of web applicationsyears of experience with Java/J2EE, Spring MVC, Hibernate, EJB, Spring||||Experience leading large and small application development teamsExperience integrating applications and designing and developing web services and frameworks; extensive front and back end experience required||||Required / Desired SkillsBachelor's Degree in computer science or equivalentWeb development experience which includes the programming/ development of webapplicationsExperience working with the Java programming languageSuccessful track record in designing and implementing web applications using J2EE, Spring, Spring MVC, Flex, Hibernate, EJB 3||||0, Struts, Oracle 10g, ADesign, code, test, and deploy J2EE based applications into industry-leading container/application server environments such as Websphere/Weblogic/JBos||||Job DetailsJob Typefulltime, employeePosted 4 days ago||||",
    "KeyWords": {
      "NOUN": {
        "Java": "Java",
        "DeveloperLocation": "DeveloperLocation",
        "Atlanta": "Atlanta",
        "GA": "GA",
        "DescriptionOur": "DescriptionOur",
        "client": "client",
        "candidate": "candidate",
        "position": "position",
        "Developer": "Developer",
        "Georgia": "Georgia",
        "part": "part",
        "Shines": "Shines",
        "Applications": "Applications",
        "Team": "Team",
        "responsibilities": "responsibilities",
        "integration": "integration",
        "design": "design",
        "application": "application",
        "systems": "systems",
        "enhancement": "enhancement",
        "multi-platform": "multi-platform",
        "scope": "scope",
        "project": "project",
        "requirements": "requirements",
        "business": "business",
        "technical/network": "technical/network",
        "personnel": "personnel",
        "evaluation": "evaluation",
        "selection": "selection",
        "platform": "platform",
        "system": "system",
        "Work": "Work",
        "planning": "planning",
        "analysis": "analysis",
        "platforms": "platforms",
        "program": "program",
        "processes": "processes",
        "interfaces": "interfaces",
        "review": "review",
        "database": "database",
        "data": "data",
        "structures": "structures",
        "modifications": "modifications",
        "documents": "documents",
        "structure": "structure",
        "function": "function",
        "and/or": "and/or",
        "enhancements": "enhancements",
        "Web": "Web",
        "Application": "Application",
        "Managers": "Managers",
        "smooth": "smooth",
        "environment": "environment",
        "Qualifications": "Qualifications",
        "Bachelor": "Bachelor",
        "degree": "degree",
        "Computer": "Computer",
        "Science": "Science",
        "years": "years",
        "experience": "experience",
        "web": "web",
        "development": "development",
        "programming/": "programming/",
        "applications": "applications",
        "lead": "lead",
        "jobyears": "jobyears",
        "Java/J2EE": "Java/J2EE",
        "Spring": "Spring",
        "MVC": "MVC",
        "Hibernate": "Hibernate",
        "EJB": "EJB",
        "applicationsyears": "applicationsyears",
        "Experience": "Experience",
        "teamsExperience": "teamsExperience",
        "integrating": "integrating",
        "services": "services",
        "frameworks": "frameworks",
        "front": "front",
        "end": "end",
        "Desired": "Desired",
        "SkillsBachelor": "SkillsBachelor",
        "Degree": "Degree",
        "computer": "computer",
        "science": "science",
        "webapplicationsExperience": "webapplicationsExperience",
        "programming": "programming",
        "track": "track",
        "record": "record",
        "J2EE": "J2EE",
        "Flex": "Flex",
        "Struts": "Struts",
        "Oracle": "Oracle",
        "ADesign": "ADesign",
        "code": "code",
        "test": "test",
        "deploy": "deploy",
        "container/application": "container/application",
        "server": "server",
        "environments": "environments",
        "Websphere/Weblogic/JBos": "Websphere/Weblogic/JBos",
        "Job": "Job",
        "DetailsJob": "DetailsJob",
        "Typefulltime": "Typefulltime",
        "days": "days"
      },
      "NUM": {
        "12": "12",
        "10g": "10g"
      },
      "ADJ": {
        "qualified": "qualified",
        "new": "new",
        "life-cycle": "life-cycle",
        "complex": "complex",
        "Responsible": "Responsible",
        "appropriate": "appropriate",
        "technical": "technical",
        "multiple": "multiple",
        "global": "global",
        "other": "other",
        "senior": "senior",
        "equivalent": "equivalent",
        "desirable": "desirable",
        "web": "web",
        "large": "large",
        "small": "small",
        "extensive": "extensive",
        "back": "back",
        "languageSuccessful": "languageSuccessful",
        "industry-leading": "industry-leading",
        "such": "such"
      },
      "X": {},
      "VERB": {
        "seeking": "seeking",
        "based": "based",
        "work": "work",
        "include": "include",
        "existing": "existing",
        "is": "is",
        "determining": "determining",
        "assigned": "assigned",
        "assessing": "assessing",
        "will": "will",
        "anddetailed": "anddetailed",
        "suggested": "suggested",
        "teaches": "teaches",
        "resulting": "resulting",
        "insure": "insure",
        "operate": "operate",
        "includes": "includes",
        "apply": "apply",
        "leading": "leading",
        "designing": "designing",
        "developing": "developing",
        "required": "required",
        "Required": "Required",
        "equivalentWeb": "equivalentWeb",
        "working": "working",
        "implementing": "implementing",
        "using": "using",
        "employeePosted": "employeePosted"
      },
      "PRT": {
        "to": "to",
        "'s": "'s"
      }
    }
  },
  "223385438": {
    "Company": "Nesco Resource, LLC",
    "Job Title": "Software Engineer",
    "Job Details": "DescriptionJob Description\nWe are currently seeking a Software Engineer|||| This position will be located in Atlanta, GA||||\n\nThe Health Analytics Division specializes in developing advanced Information Technology and Data Management solutions for our government and commercial clients|||| As a mid level software developer, you will assist entry level staff as you solve mid level technical problems!\n\nMajor Responsibilities:\n• Solving technical problems using computer science and systems development approaches in areas that require mathematical and/or statistical methods and knowledge\n• Interacting and communicating with clients\n• Interacting with teams of scientists including, but not limited to epidemiologists, mathematicians, computer scientists, statisticians, and engineers\n• Proactively managing expectations and meeting deadlines in a fast moving, agile software development environment\n• Conducting and participating in assigned projects with minimum of supervision and within time and budget constraints\n• Interacting with on-site client team members as well as geographically diverse team members daily\n• Maintaining excellent communication with team members and developing and maintaining a strong working relationship with the client\n• Continued job performance improvement through on-the-job training and outside study\n• Thrive in a multi-disciplinary environment solving problems in a variety of application areas\n• Minimal domestic travel\n\nThe Following Requirements Must be Met to be Considered for this Position:\n• Bachelor's Degree in Computer Science, Computer Information Science, or Computer Engineering with at least 5 years of demonstrated work experience; OR equivalent combination of education and experience||||\n• Demonstrated competency in object-oriented programming with languages such as Java/JavaEE or C#\n• Demonstrated experience with SQL and relational database engines such as SQL Server, MySQL, PostgreSQL, or Oracle\n• Demonstrated experience with web development technologies such as HTML, XML, JSON, CSS, and JavaScript and accompanying frameworks and libraries (e||||g||||, jQuery, Bootstrap, etc||||) and Experience with additional JavaScript frameworks (e||||g||||, React, Angular, Vue)\n• Demonstrated competency with development tools (e||||g||||, NetBeans, Eclipse, Visual Studio Code, etc||||)\n• Demonstrated experience with Agile development\n• Demonstrated ability to develop, test, document, and maintain computer code for deadline driven projects\n• Demonstrated ability to participate in requirements gathering process, provide user documentation, and write clear, concise comments within programs\n• Excellent written and oral communication skills\n• Must be a US Person with the ability to obtain and maintain a government clearance\n\nThe Following is Desired, but not Required, to be Considered for this Position:\n• Experience with team collaboration software (e||||g||||, Confluence, JIRA, Eventum, Bugzilla, etc||||)\n• Experience with version control software (e||||g||||, GIT, SVN, Azure DevOps, etc||||)\n• Experience with user interface and user experience design and implementation\n• Experience with Python, SAS, S+, R, C, C#, C++\n• Experience with web server software (e||||g||||, WebLogic, Apache, IIS, Tomcat)\n• Experience with automated code quality tools (e||||g||||, SonarQube)\n• Experience with continuous integration tools (e||||g||||, Hudson, Jenkins, xUnit, Team Foundation Server, etc||||)\n• Experience with automated testing tools and frameworks (e||||g||||, Katalon, Selenium, Cucumber, etc||||)\n• Experience with cloud computing technologies as well as associated service providers such as Amazon Web Services (AWS) and Microsoft Azure\n\nNesco Resource and affiliates (Lehigh G||||I||||T Inc, and Callos Resource, LLC) is an equal employment opportunity employer and does not discriminate on the basis of race, color, religion, sex, sexual orientation, gender identity, national origin, disability, age, or veteran status, or any other legally protected characteristics with respect to employment opportunities||||Job DetailsSalary$71 Per HourJob Typefulltime, contractPosted 3 days ago||||",
    "KeyWords": {
      "NOUN": {
        "Description": "Description",
        "Software": "Software",
        "Engineer": "Engineer",
        "position": "position",
        "Atlanta": "Atlanta",
        "GA": "GA",
        "Health": "Health",
        "Analytics": "Analytics",
        "Division": "Division",
        "Information": "Information",
        "Technology": "Technology",
        "Data": "Data",
        "Management": "Management",
        "solutions": "solutions",
        "government": "government",
        "clients": "clients",
        "level": "level",
        "software": "software",
        "developer": "developer",
        "entry": "entry",
        "staff": "staff",
        "problems": "problems",
        "Responsibilities": "Responsibilities",
        "computer": "computer",
        "science": "science",
        "systems": "systems",
        "development": "development",
        "approaches": "approaches",
        "areas": "areas",
        "methods": "methods",
        "knowledge": "knowledge",
        "Interacting": "Interacting",
        "teams": "teams",
        "scientists": "scientists",
        "epidemiologists": "epidemiologists",
        "mathematicians": "mathematicians",
        "statisticians": "statisticians",
        "engineers": "engineers",
        "expectations": "expectations",
        "deadlines": "deadlines",
        "moving": "moving",
        "environment": "environment",
        "Conducting": "Conducting",
        "projects": "projects",
        "minimum": "minimum",
        "supervision": "supervision",
        "time": "time",
        "budget": "budget",
        "constraints": "constraints",
        "client": "client",
        "team": "team",
        "members": "members",
        "communication": "communication",
        "working": "working",
        "relationship": "relationship",
        "Continued": "Continued",
        "job": "job",
        "performance": "performance",
        "improvement": "improvement",
        "training": "training",
        "study": "study",
        "Thrive": "Thrive",
        "variety": "variety",
        "application": "application",
        "Minimal": "Minimal",
        "Requirements": "Requirements",
        "Must": "Must",
        "Position": "Position",
        "Bachelor": "Bachelor",
        "Degree": "Degree",
        "Computer": "Computer",
        "Science": "Science",
        "Engineering": "Engineering",
        "years": "years",
        "work": "work",
        "experience": "experience",
        "combination": "combination",
        "education": "education",
        "competency": "competency",
        "programming": "programming",
        "languages": "languages",
        "Java/JavaEE": "Java/JavaEE",
        "SQL": "SQL",
        "database": "database",
        "engines": "engines",
        "Server": "Server",
        "MySQL": "MySQL",
        "PostgreSQL": "PostgreSQL",
        "Oracle": "Oracle",
        "web": "web",
        "technologies": "technologies",
        "HTML": "HTML",
        "XML": "XML",
        "JSON": "JSON",
        "CSS": "CSS",
        "JavaScript": "JavaScript",
        "frameworks": "frameworks",
        "libraries": "libraries",
        "g.": "g.",
        "jQuery": "jQuery",
        "Bootstrap": "Bootstrap",
        "Experience": "Experience",
        "React": "React",
        "Angular": "Angular",
        "Vue": "Vue",
        "tools": "tools",
        "NetBeans": "NetBeans",
        "Eclipse": "Eclipse",
        "Visual": "Visual",
        "Studio": "Studio",
        "Code": "Code",
        "Agile": "Agile",
        "Demonstrated": "Demonstrated",
        "ability": "ability",
        "test": "test",
        "document": "document",
        "code": "code",
        "deadline": "deadline",
        "requirements": "requirements",
        "process": "process",
        "documentation": "documentation",
        "comments": "comments",
        "programs": "programs",
        "Excellent": "Excellent",
        "skills": "skills",
        "US": "US",
        "Person": "Person",
        "clearance": "clearance",
        "Following": "Following",
        "Desired": "Desired",
        "Required": "Required",
        "collaboration": "collaboration",
        "Confluence": "Confluence",
        "JIRA": "JIRA",
        "Eventum": "Eventum",
        "Bugzilla": "Bugzilla",
        "version": "version",
        "control": "control",
        "GIT": "GIT",
        "SVN": "SVN",
        "Azure": "Azure",
        "DevOps": "DevOps",
        "interface": "interface",
        "design": "design",
        "implementation": "implementation",
        "Python": "Python",
        "SAS": "SAS",
        "S+": "S+",
        "C++": "C++",
        "server": "server",
        "WebLogic": "WebLogic",
        "Apache": "Apache",
        "IIS": "IIS",
        "Tomcat": "Tomcat",
        "quality": "quality",
        "SonarQube": "SonarQube",
        "integration": "integration",
        "Hudson": "Hudson",
        "Jenkins": "Jenkins",
        "xUnit": "xUnit",
        "Team": "Team",
        "Foundation": "Foundation",
        "testing": "testing",
        "Katalon": "Katalon",
        "Selenium": "Selenium",
        "Cucumber": "Cucumber",
        "cloud": "cloud",
        "service": "service",
        "providers": "providers",
        "Amazon": "Amazon",
        "Web": "Web",
        "Services": "Services",
        "AWS": "AWS",
        "Microsoft": "Microsoft",
        "Nesco": "Nesco",
        "Resource": "Resource",
        "affiliates": "affiliates",
        "Lehigh": "Lehigh",
        "G.": "G.",
        "I.": "I.",
        "Inc": "Inc",
        "Callos": "Callos",
        "LLC": "LLC",
        "employment": "employment",
        "opportunity": "opportunity",
        "employer": "employer",
        "basis": "basis",
        "race": "race",
        "color": "color",
        "religion": "religion",
        "sex": "sex",
        "orientation": "orientation",
        "gender": "gender",
        "identity": "identity",
        "origin": "origin",
        "disability": "disability",
        "age": "age",
        "veteran": "veteran",
        "status": "status",
        "characteristics": "characteristics",
        "respect": "respect",
        "opportunities": "opportunities",
        "Job": "Job",
        "DetailsSalary": "DetailsSalary",
        "Per": "Per",
        "HourJob": "HourJob",
        "Typefulltime": "Typefulltime",
        "days": "days"
      },
      "VERB": {
        "seeking": "seeking",
        "will": "will",
        "be": "be",
        "located": "located",
        "specializes": "specializes",
        "developing": "developing",
        "assist": "assist",
        "solve": "solve",
        "Solving": "Solving",
        "using": "using",
        "require": "require",
        "communicating": "communicating",
        "Interacting": "Interacting",
        "including": "including",
        "managing": "managing",
        "meeting": "meeting",
        "participating": "participating",
        "Maintaining": "Maintaining",
        "maintaining": "maintaining",
        "solving": "solving",
        "travel": "travel",
        "Met": "Met",
        "Considered": "Considered",
        "Demonstrated": "Demonstrated",
        "accompanying": "accompanying",
        "develop": "develop",
        "maintain": "maintain",
        "driven": "driven",
        "participate": "participate",
        "gathering": "gathering",
        "provide": "provide",
        "written": "written",
        "obtain": "obtain",
        "is": "is",
        "computing": "computing",
        "associated": "associated",
        "does": "does",
        "discriminate": "discriminate",
        "protected": "protected",
        "contractPosted": "contractPosted"
      },
      "ADJ": {
        "commercial": "commercial",
        "mid": "mid",
        "level": "level",
        "technical": "technical",
        "Major": "Major",
        "mathematical": "mathematical",
        "and/or": "and/or",
        "statistical": "statistical",
        "limited": "limited",
        "fast": "fast",
        "assigned": "assigned",
        "on-site": "on-site",
        "diverse": "diverse",
        "excellent": "excellent",
        "strong": "strong",
        "on-the-job": "on-the-job",
        "outside": "outside",
        "multi-disciplinary": "multi-disciplinary",
        "domestic": "domestic",
        "Following": "Following",
        "least": "least",
        "demonstrated": "demonstrated",
        "equivalent": "equivalent",
        "object-oriented": "object-oriented",
        "such": "such",
        "relational": "relational",
        "e.": "e.",
        "additional": "additional",
        "user": "user",
        "write": "write",
        "clear": "clear",
        "concise": "concise",
        "oral": "oral",
        "automated": "automated",
        "continuous": "continuous",
        "equal": "equal",
        "sexual": "sexual",
        "national": "national",
        "other": "other"
      },
      "PRT": {
        "to": "to",
        "'s": "'s"
      },
      "X": {
        "etc": "etc"
      },
      "NUM": {}
    }
  },
  "223405736": {
    "Company": "CyberCoders",
    "Job Title": "100% Remote Software Engineer",
    "Job Details": "DescriptionIf you are a Front End Developer with experience, please read on!\nWe are a leading SaaS company that allows our clients to dive deeper into the data surrounding their customer! We have been in business for 20 years and continue to grow our operations and are currently looking for a front-end developer who has experience shipping web applications in react/node||||Top Reasons to Work with UsWe have a strong leadership team that promotes from withinAwesome company culture!\nChance to grow your career professionally and personally|||| \nChance to ship meaningful web applications!\n100% Remote/WFH opportunity! Enjoy more time with family as you work from home!What You Will Be DoingWrite clean and testable React JSX||||Build detailed applications\nDevelop and shop web applications||||What You Need for this Position- JavaScript- REACT\n- NODESo, if you are a Front End Developer with experience, please apply today or send your resume to keith||||ellis@cybercoders||||comJob DetailsSalary$80000 - $120000 Per YearJob Typefulltime, employeePosted 1 Day ago||||",
    "KeyWords": {
      "NOUN": {
        "Front": "Front",
        "End": "End",
        "Developer": "Developer",
        "experience": "experience",
        "please": "please",
        "SaaS": "SaaS",
        "company": "company",
        "clients": "clients",
        "deeper": "deeper",
        "data": "data",
        "customer": "customer",
        "business": "business",
        "years": "years",
        "operations": "operations",
        "developer": "developer",
        "web": "web",
        "applications": "applications",
        "react/node": "react/node",
        "Reasons": "Reasons",
        "UsWe": "UsWe",
        "leadership": "leadership",
        "team": "team",
        "culture": "culture",
        "Chance": "Chance",
        "career": "career",
        "Remote/WFH": "Remote/WFH",
        "opportunity": "opportunity",
        "Enjoy": "Enjoy",
        "time": "time",
        "family": "family",
        "home": "home",
        "React": "React",
        "JSX": "JSX",
        "Build": "Build",
        "Develop": "Develop",
        "shop": "shop",
        "JavaScript-": "JavaScript-",
        "REACT": "REACT",
        "NODESo": "NODESo",
        "today": "today",
        "resume": "resume",
        "cybercoders": "cybercoders",
        "comJob": "comJob",
        "DetailsSalary": "DetailsSalary",
        "Per": "Per",
        "YearJob": "YearJob",
        "Typefulltime": "Typefulltime",
        "Day": "Day"
      },
      "VERB": {
        "read": "read",
        "are": "are",
        "leading": "leading",
        "allows": "allows",
        "dive": "dive",
        "surrounding": "surrounding",
        "have": "have",
        "been": "been",
        "continue": "continue",
        "grow": "grow",
        "looking": "looking",
        "has": "has",
        "shipping": "shipping",
        "Work": "Work",
        "promotes": "promotes",
        "ship": "ship",
        "work": "work",
        "Will": "Will",
        "Be": "Be",
        "detailed": "detailed",
        "Need": "Need",
        "please": "please",
        "apply": "apply",
        "send": "send",
        "keith": "keith",
        "ellis": "ellis",
        "employeePosted": "employeePosted"
      },
      "PRT": {
        "to": "to"
      },
      "NUM": {
        "100": "100",
        "80000": "80000",
        "120000": "120000"
      },
      "ADJ": {
        "Top": "Top",
        "strong": "strong",
        "withinAwesome": "withinAwesome",
        "meaningful": "meaningful",
        "more": "more",
        "DoingWrite": "DoingWrite",
        "clean": "clean",
        "testable": "testable",
        "Position-": "Position-"
      }
    }
  },
  "223461909": {
    "Company": "Smart IMS",
    "Job Title": "Cognos BI Developer - W2",
    "Job Details": "Description*** Contract to Hire role ****** W2-Contract ****** Local Candidates preferred ***Required Skills:2+ years of Cognos Report development experience1 year with the latest version Cognos Analytics 11||||x2-3 years of experience with Framework Manager||||Proficient with writing Oracle sqls||||Troubleshooting of report issues and performance issues||||Experience with building Dashboards and familiar with other BI tools like Tableau, Power BI||||3 years experience w/ C++3 years experience w/JavaJob DetailsJob Typefulltime, contractPostedToday||||",
    "KeyWords": {
      "NOUN": {
        "Contract": "Contract",
        "Hire": "Hire",
        "role": "role",
        "W2-Contract": "W2-Contract",
        "Local": "Local",
        "Candidates": "Candidates",
        "Required": "Required",
        "Skills:2+": "Skills:2+",
        "years": "years",
        "Cognos": "Cognos",
        "Report": "Report",
        "development": "development",
        "year": "year",
        "version": "version",
        "Analytics": "Analytics",
        "experience": "experience",
        "Framework": "Framework",
        "Manager": "Manager",
        "Proficient": "Proficient",
        "Oracle": "Oracle",
        "sqls": "sqls",
        "Troubleshooting": "Troubleshooting",
        "report": "report",
        "issues": "issues",
        "performance": "performance",
        "Experience": "Experience",
        "building": "building",
        "Dashboards": "Dashboards",
        "BI": "BI",
        "tools": "tools",
        "Tableau": "Tableau",
        "Power": "Power",
        "C++3": "C++3",
        "DetailsJob": "DetailsJob",
        "Typefulltime": "Typefulltime",
        "contractPostedToday": "contractPostedToday"
      },
      "PRT": {},
      "VERB": {
        "writing": "writing",
        "w/": "w/",
        "w/JavaJob": "w/JavaJob"
      },
      "ADJ": {
        "latest": "latest",
        "x2-3": "x2-3",
        "familiar": "familiar",
        "other": "other"
      },
      "NUM": {}
    }
  },
  "31c5f857-3638-4f74-a8b7-b101215be91d": {
    "Company": "Pyramid Consulting, Inc",
    "Job Title": "Software Developer",
    "Job Details": "DescriptionJob DescriptionImmediate need for a talented Software Developer with experience in the Telecom Industry|||| This is a 12+ Months Contract opportunity with long-term potential and is located in Atlanta, GA|||| Please review the job description below|||| Job ID: 21-00578Key Responsibilities and Requirements:Design and develop software for remote access services for the Global Network Client for Windows||||Develop applications for mobile handsets and tablets to complement television/cable IPTV service||||Writes code and completes programming and documentation using programming language and technology||||Performs testing and debugging of applications||||Analyzes, designs, programs, debugs and modifies software enhancements and/or new products used in local, networked, or Internet-related computer programs||||Review/approve proposed tech system designs in collaboration with team||||Our client is a leading Telecom Industry and we are currently interviewing to fill this and other similar contract positions|||| If you are interested in this position, please apply online for immediate consideration|||| J2W:CB3Job DetailsPostedToday||||",
    "KeyWords": {
      "NOUN": {
        "DescriptionImmediate": "DescriptionImmediate",
        "need": "need",
        "Software": "Software",
        "Developer": "Developer",
        "experience": "experience",
        "Telecom": "Telecom",
        "Industry": "Industry",
        "Months": "Months",
        "Contract": "Contract",
        "opportunity": "opportunity",
        "potential": "potential",
        "Atlanta": "Atlanta",
        "GA": "GA",
        "Please": "Please",
        "job": "job",
        "description": "description",
        "Job": "Job",
        "ID": "ID",
        "Responsibilities": "Responsibilities",
        "Requirements": "Requirements",
        "Design": "Design",
        "software": "software",
        "access": "access",
        "services": "services",
        "Global": "Global",
        "Network": "Network",
        "Client": "Client",
        "Windows": "Windows",
        "Develop": "Develop",
        "applications": "applications",
        "handsets": "handsets",
        "tablets": "tablets",
        "IPTV": "IPTV",
        "service": "service",
        "code": "code",
        "documentation": "documentation",
        "language": "language",
        "technology": "technology",
        "Performs": "Performs",
        "Analyzes": "Analyzes",
        "programs": "programs",
        "debugs": "debugs",
        "modifies": "modifies",
        "enhancements": "enhancements",
        "products": "products",
        "computer": "computer",
        "Review/approve": "Review/approve",
        "tech": "tech",
        "system": "system",
        "collaboration": "collaboration",
        "team": "team",
        "client": "client",
        "contract": "contract",
        "positions": "positions",
        "position": "position",
        "online": "online",
        "consideration": "consideration",
        "J2W": "J2W",
        "CB3Job": "CB3Job",
        "DetailsPostedToday": "DetailsPostedToday"
      },
      "ADJ": {
        "12+": "12+",
        "long-term": "long-term",
        "21-00578Key": "21-00578Key",
        "remote": "remote",
        "mobile": "mobile",
        "television/cable": "television/cable",
        "programming": "programming",
        "new": "new",
        "local": "local",
        "networked": "networked",
        "Internet-related": "Internet-related",
        "other": "other",
        "similar": "similar",
        "interested": "interested",
        "immediate": "immediate"
      },
      "VERB": {
        "is": "is",
        "located": "located",
        "review": "review",
        "develop": "develop",
        "complement": "complement",
        "Writes": "Writes",
        "completes": "completes",
        "programming": "programming",
        "using": "using",
        "testing": "testing",
        "debugging": "debugging",
        "designs": "designs",
        "and/or": "and/or",
        "used": "used",
        "proposed": "proposed",
        "leading": "leading",
        "are": "are",
        "interviewing": "interviewing",
        "fill": "fill",
        "please": "please",
        "apply": "apply"
      },
      "PRT": {
        "to": "to"
      }
    }
  },
  "9992e54e-e062-4666-91d9-dbce749c65ec": {
    "Company": "The Magnet Group",
    "Job Title": "Senior PHP Developer /Magento 2 Administrator",
    "Job Details": "DescriptionDescription:\nSummaryThe Magento Administrator will be responsible for working within the Magento platform, using their skills and adaptability to focus on multiple projects simultaneously and adapt to new technologies quickly|||| Duties will include making site configuration updates, monitor site performance, handling data imports/integrations, run Magento 2 CLI commands and resolving helpdesk support tickets||||Essential Duties and Responsibilities include the following|||| Other duties may be assigned||||• Implement deployment of website bug fixes and feature enhancements• Serve as a liaison and primary point of contact for 4Magento framework development and maintenance within the organization and external vendor relationships• Act as a project manager to evaluate, prioritize, develop, manage, implement and test web improvement initiatives• Manage key Soap API integration touchpoints between ERP and Magento (e||||g||||, Inventory, Freight, products, etc||||)• Critical thinking and decision-making skills with the ability to prioritize necessary projects and improvements• Additional duties as deemed necessary by the Supervisor/Manager||||• Maintain integrity of product catalog and make updates• Manage product types, categories, names, SKUs, attributes, advanced pricing, product images, and descriptions• Handle CMS/content updates• Install/Deploy custom modules and third-party module install and upgrades• Manage Magento updates||||\n\nRequirements:\n• Demonstrated understanding of web technologies, browsers, analytics, reporting and content management systems and processes• Proficient in Magento 2, HTML, CSS, JavaScript, MS Office, MYSQL, Google Analytics• Experience in managing vendor relationships, and cross-functional projects• Detail-oriented, capable of handling multiple tasks at once, adept in navigating ambiguity and rapidly changing or competing priorities||||• Proactive, confident self-starter with positive energy, customer-oriented attitude and excellent multitasking ability• Experience collaborating with multiple levels of stakeholders• Passion for digital & eCommerce space• Strong communication and presentation skills with the ability to translate complex plans into concise and clear recommendations||||• Highly creative and out of the box strategic thinker who is comfortable sharing ideas and cheerleading new strategies that impact business metrics• Ability to review current practices and bring a fresh perspective on ways to approach existing problems• Stay Up to date with latest trends and marketing best practices• Demonstrates strong business and commercial acumen• Self-motivated and direct, with the ability to effectively prioritize and execute tasks in a high-pressure environment||||• Excellent organizational skills and knowledge of Agile development methodologies||||• Extensive experience in PHP development and MVC concepts||||• Deep knowledge of Magento 2 CE Core functionality (EE is a plus)|||| • Experienced in Magento frontend Theme development• Experience in the creation & integration of external APIs and SOAP/ REST web services||||• Good knowledge of the current UX/UI and best practices• Knowledge of SEO optimization/integration techniques|||| • Strong knowledge of MySQL Database management and queries|||| • Knowledge of JS and CSS frameworks such as jQuery, Bootstrap, Knockout, CSS3 (SASS/LESS), HTML5, etc|||| • Version control experience with tools such as GIT, BitBucket or SVN||||Education And/or Experience• 4+ years PHP experience• 2+ years of Magento 2 Administration• 4+ HTML, CSS, JavaScript experience • 2+ years MySQL and database experiencePM19 PI128093222Job DetailsPosted 10 days ago||||",
    "KeyWords": {
      "NOUN": {
        "SummaryThe": "SummaryThe",
        "Magento": "Magento",
        "Administrator": "Administrator",
        "platform": "platform",
        "skills": "skills",
        "adaptability": "adaptability",
        "projects": "projects",
        "technologies": "technologies",
        "Duties": "Duties",
        "site": "site",
        "configuration": "configuration",
        "updates": "updates",
        "monitor": "monitor",
        "performance": "performance",
        "data": "data",
        "imports/integrations": "imports/integrations",
        "CLI": "CLI",
        "commands": "commands",
        "support": "support",
        "tickets": "tickets",
        "Responsibilities": "Responsibilities",
        "duties": "duties",
        "Implement": "Implement",
        "deployment": "deployment",
        "bug": "bug",
        "fixes": "fixes",
        "feature": "feature",
        "Serve": "Serve",
        "liaison": "liaison",
        "point": "point",
        "contact": "contact",
        "framework": "framework",
        "development": "development",
        "maintenance": "maintenance",
        "organization": "organization",
        "vendor": "vendor",
        "relationships•": "relationships•",
        "Act": "Act",
        "project": "project",
        "manager": "manager",
        "manage": "manage",
        "implement": "implement",
        "test": "test",
        "web": "web",
        "improvement": "improvement",
        "initiatives•": "initiatives•",
        "Manage": "Manage",
        "Soap": "Soap",
        "API": "API",
        "integration": "integration",
        "touchpoints": "touchpoints",
        "ERP": "ERP",
        "g.": "g.",
        "Inventory": "Inventory",
        "Freight": "Freight",
        "products": "products",
        "Critical": "Critical",
        "thinking": "thinking",
        "ability": "ability",
        "Additional": "Additional",
        "Supervisor/Manager": "Supervisor/Manager",
        "Maintain": "Maintain",
        "integrity": "integrity",
        "product": "product",
        "catalog": "catalog",
        "types": "types",
        "categories": "categories",
        "names": "names",
        "SKUs": "SKUs",
        "pricing": "pricing",
        "images": "images",
        "Handle": "Handle",
        "CMS/content": "CMS/content",
        "Install/Deploy": "Install/Deploy",
        "custom": "custom",
        "modules": "modules",
        "module": "module",
        "install": "install",
        "Requirements": "Requirements",
        "understanding": "understanding",
        "browsers": "browsers",
        "analytics": "analytics",
        "reporting": "reporting",
        "management": "management",
        "systems": "systems",
        "Proficient": "Proficient",
        "HTML": "HTML",
        "CSS": "CSS",
        "JavaScript": "JavaScript",
        "MS": "MS",
        "Office": "Office",
        "MYSQL": "MYSQL",
        "Google": "Google",
        "Analytics•": "Analytics•",
        "Experience": "Experience",
        "relationships": "relationships",
        "projects•": "projects•",
        "Detail-oriented": "Detail-oriented",
        "tasks": "tasks",
        "ambiguity": "ambiguity",
        "priorities": "priorities",
        "Proactive": "Proactive",
        "self-starter": "self-starter",
        "energy": "energy",
        "attitude": "attitude",
        "collaborating": "collaborating",
        "levels": "levels",
        "Passion": "Passion",
        "eCommerce": "eCommerce",
        "space•": "space•",
        "Strong": "Strong",
        "communication": "communication",
        "presentation": "presentation",
        "plans": "plans",
        "concise": "concise",
        "recommendations": "recommendations",
        "Highly": "Highly",
        "box": "box",
        "thinker": "thinker",
        "ideas": "ideas",
        "strategies": "strategies",
        "business": "business",
        "metrics•": "metrics•",
        "Ability": "Ability",
        "practices": "practices",
        "perspective": "perspective",
        "ways": "ways",
        "problems•": "problems•",
        "Stay": "Stay",
        "date": "date",
        "trends": "trends",
        "marketing": "marketing",
        "practices•": "practices•",
        "acumen•": "acumen•",
        "environment": "environment",
        "knowledge": "knowledge",
        "Agile": "Agile",
        "methodologies": "methodologies",
        "experience": "experience",
        "PHP": "PHP",
        "MVC": "MVC",
        "concepts": "concepts",
        "Deep": "Deep",
        "CE": "CE",
        "Core": "Core",
        "functionality": "functionality",
        "EE": "EE",
        "plus": "plus",
        "Experienced": "Experienced",
        "Theme": "Theme",
        "development•": "development•",
        "creation": "creation",
        "APIs": "APIs",
        "SOAP/": "SOAP/",
        "REST": "REST",
        "services": "services",
        "UX/UI": "UX/UI",
        "Knowledge": "Knowledge",
        "SEO": "SEO",
        "optimization/integration": "optimization/integration",
        "techniques": "techniques",
        "MySQL": "MySQL",
        "Database": "Database",
        "queries": "queries",
        "JS": "JS",
        "frameworks": "frameworks",
        "jQuery": "jQuery",
        "Bootstrap": "Bootstrap",
        "Knockout": "Knockout",
        "CSS3": "CSS3",
        "SASS/LESS": "SASS/LESS",
        "HTML5": "HTML5",
        "Version": "Version",
        "control": "control",
        "tools": "tools",
        "GIT": "GIT",
        "BitBucket": "BitBucket",
        "SVN": "SVN",
        "Education": "Education",
        "And/or": "And/or",
        "Experience•": "Experience•",
        "years": "years",
        "Administration•": "Administration•",
        "PI128093222Job": "PI128093222Job",
        "days": "days"
      },
      "VERB": {
        "be": "be",
        "working": "working",
        "using": "using",
        "focus": "focus",
        "adapt": "adapt",
        "will": "will",
        "include": "include",
        "making": "making",
        "handling": "handling",
        "run": "run",
        "resolving": "resolving",
        "may": "may",
        "assigned": "assigned",
        "enhancements•": "enhancements•",
        "evaluate": "evaluate",
        "prioritize": "prioritize",
        "develop": "develop",
        "deemed": "deemed",
        "make": "make",
        "attributes": "attributes",
        "advanced": "advanced",
        "descriptions•": "descriptions•",
        "updates": "updates",
        "Demonstrated": "Demonstrated",
        "managing": "managing",
        "navigating": "navigating",
        "changing": "changing",
        "competing": "competing",
        "multitasking": "multitasking",
        "translate": "translate",
        "is": "is",
        "sharing": "sharing",
        "cheerleading": "cheerleading",
        "impact": "impact",
        "review": "review",
        "bring": "bring",
        "approach": "approach",
        "existing": "existing",
        "Demonstrates": "Demonstrates",
        "execute": "execute",
        "frontend": "frontend",
        "experience•": "experience•",
        "database": "database",
        "DetailsPosted": "DetailsPosted"
      },
      "ADJ": {
        "multiple": "multiple",
        "new": "new",
        "helpdesk": "helpdesk",
        "Essential": "Essential",
        "following": "following",
        "Other": "Other",
        "website": "website",
        "primary": "primary",
        "external": "external",
        "key": "key",
        "e.": "e.",
        "decision-making": "decision-making",
        "necessary": "necessary",
        "improvements•": "improvements•",
        "updates•": "updates•",
        "third-party": "third-party",
        "upgrades•": "upgrades•",
        "content": "content",
        "processes•": "processes•",
        "vendor": "vendor",
        "cross-functional": "cross-functional",
        "capable": "capable",
        "confident": "confident",
        "positive": "positive",
        "customer-oriented": "customer-oriented",
        "excellent": "excellent",
        "ability•": "ability•",
        "stakeholders•": "stakeholders•",
        "digital": "digital",
        "complex": "complex",
        "clear": "clear",
        "creative": "creative",
        "strategic": "strategic",
        "comfortable": "comfortable",
        "current": "current",
        "fresh": "fresh",
        "latest": "latest",
        "strong": "strong",
        "commercial": "commercial",
        "Self-motivated": "Self-motivated",
        "direct": "direct",
        "high-pressure": "high-pressure",
        "Excellent": "Excellent",
        "organizational": "organizational",
        "Extensive": "Extensive",
        "Good": "Good",
        "best": "best",
        "such": "such",
        "experiencePM19": "experiencePM19"
      },
      "PRT": {
        "to": "to"
      },
      "NUM": {
        "10": "10",
        "4+": "4+",
        "2+": "2+"
      },
      "X": {
        "etc": "etc"
      }
    }
  },
  "24825a6a-16e0-41d6-b36f-6085e17c1a07": {
    "Company": "Cox Automotive",
    "Job Title": "Principal Cloud Architect",
    "Job Details": "DescriptionPrimary Location: 7000 Central Pkwy, Atlanta, GA, USADivision: Cox AutomotiveJob Level: Individual ContributorTravel: NoSchedule: Full-timeShift: Day JobRequisition Number: 202000821Cox Automotive is currently looking for a Cloud Technical Architect for its Financial Platforms Team to join our team in Atlanta, GA||||The Cloud Technical Architect is responsible for overseeing the configuration and infrastructure-as-code across the Oracle Cloud Infrastructure (OCI) which supports the Cox Automotive Oracle financial platforms||||  The platforms running on OCI include 2 large Oracle E-Business (EBS) implementations, Revenue Management & Billing (RMB), OBIEE, and a reporting replica||||  The position is accountable for:  defining the OCI infrastructure direction and overseeing the infrastructure development||||  The Cloud Technical Architect works in concert with the application delivery teams and production operations team to ensure that application and infrastructure decisions and projects are aligned||||  This role requires thorough understanding of infrastructure and development processes and an in-depth understanding of the organization’s technology portfolio and capabilities, as well as external options||||  The Cloud Technical Architect ensures the reliability, scalability, and consistency of the overall suite of financial platforms by leading technical staff, both employees and consultants, in the design, development and delivery of technical solutions|||| Technology We Use:Oracle Cloud Infrastructure, Oracle E-Business Suite, Oracle RMB, Oracle Business Intelligence (OBIEE)WebLogic, Oracle SOA, Github, Jenkins, Ansible, FlexDeployYour Role:Drive the strategic roadmap for the Oracle Cloud Infrastructure including driving the decisions on architectural components and setting the overall direction and priorities for the OCI team in partnership with Financial Platform Application delivery teamsLead the development of OCI solutions to meet the complex demands of the Oracle delivery teams while ensuring the highest levels of system reliability Understand and provide input and guidance on OCI Budget and team resourcesEnsure that the OCI delivery teams operates according to the CAFÉ (i||||e||||, scaled agile) principles Break OCI features into stories to be consumed by the OCI delivery teamsDefine and promote technology policies, practices and decisions which recognize the current and evolving needs of all stakeholdersDrive consistency and automation through the implementation of SDLC tools (e||||g||||, Ansible, FlexDeploy)Drive best practice decisions on coding, performance tuning and integrationDrive best practice decisions on architecture and automation with the mindset to improve operational efficiencies of the solution and the team||||Partner with the other financial platform delivery teams to manage rollout schedules and technology releases ensuring business needs are supported in all phases throughout the processReviews, coordinates, and provides leadership to the work of senior professionalsTranslates the department’s objectives into cloud goals and activitiesDisplays strong teamwork and interpersonal skills with the ability to communicate to all levels of management  Qualifications:Required Experience (minimum): BA/BS Degree in related field and 10 years of related experience or MS Degree with 8 years of related experience or a Ph||||D|||| with 5 years of related experience or 14 years of related experience10+ years of information technology experience required 5+ years working in cloud-based infrastructure5+ years of software delivery experience (Agile methods preferred) 3+ years in implementing large scale transformational projects (ERP programs preferred)What We Look For (preferred): Excellent Communication Skills||||The proven ability to collaborate to deliver quality solutions|||| Proven track record of achieving success in a dynamic, fast-paced software development environment|||| Ability to adapt to rapidly changing priorities, make appropriate solution decisions quickly and be co-located with their team to ensure accessibility by the team||||Ability to rapidly learn new technologies Oracle EBS experience preferredSo, are you ready to challenge today and transform tomorrow? Apply now||||Who We AreAbout Cox AutomotiveThere’s nothing ordinary about Cox Automotive|||| We are people of every background driven by our passion for mobility, innovation, client success and community outreach|||| We make buying, selling and owning (or simply using) cars easier for everyone|||| Touching more than 40,000 clients across five continents, we bring together the best brands and the best teams to propel the automotive industry forward|||| Some of those team members work for our iconic consumer brands like Autotrader and Kelley Blue Book, while others are creating the future of automotive at industry-facing brands like Dealer||||com, Manheim and vAuto|||| About Cox  We are the Cox family of businesses|||| We’ve been making our mark since 1898 by building and evolving world-class businesses, staying true to our values, and encouraging top talent to always look for growth and impact while building a career with us||||  Our primary divisions – Cox Communications and Cox Automotive – are driving a new wave of innovation, powering smart cities with powerhouse broadband communications and pioneering greener, more progressive transportation alternatives for individuals and fleet operators||||  We’re also expanding into new spaces like cleantech and healthcare to rev up our momentum toward building a better future for the next generation||||  We’re looking for the talent today who will be our leaders tomorrow|||| Sound intriguing? Learn more about where we are today, where we hope you’ll be going with us, and the common purpose that unites us at coxenterprises||||com||||    Cox is an Equal Employment Opportunity employer - All qualified applicants/employees will receive consideration for employment without regard to that individual’s age, race, color, religion or creed, national origin or ancestry, sex (including pregnancy), sexual orientation, gender, gender identity, physical or mental disability, veteran status, genetic information, ethnicity, citizenship, or any other characteristic protected by law||||Statement to ALL Third-Party Agencies and Similar Organizations:  Cox accepts resumes only from agencies with which we formally engage their services||||   Please do not forward resumes to our applicant tracking system, Cox employees, Cox hiring manager, or send to any Cox facility|||| Cox is not responsible for any fees or charges associated with unsolicited resumes||||Job DetailsPosted 4 days ago||||",
    "KeyWords": {
      "ADJ": {
        "Individual": "Individual",
        "Full-timeShift": "Full-timeShift",
        "responsible": "responsible",
        "infrastructure-as-code": "infrastructure-as-code",
        "financial": "financial",
        "large": "large",
        "accountable": "accountable",
        "in-depth": "in-depth",
        "external": "external",
        "overall": "overall",
        "technical": "technical",
        "strategic": "strategic",
        "architectural": "architectural",
        "complex": "complex",
        "highest": "highest",
        "current": "current",
        "stakeholdersDrive": "stakeholdersDrive",
        "e.": "e.",
        "best": "best",
        "integrationDrive": "integrationDrive",
        "operational": "operational",
        "other": "other",
        "senior": "senior",
        "cloud": "cloud",
        "strong": "strong",
        "interpersonal": "interpersonal",
        "related": "related",
        "experience10+": "experience10+",
        "cloud-based": "cloud-based",
        "infrastructure5+": "infrastructure5+",
        "scale": "scale",
        "transformational": "transformational",
        "Excellent": "Excellent",
        "proven": "proven",
        "quality": "quality",
        "dynamic": "dynamic",
        "fast-paced": "fast-paced",
        "appropriate": "appropriate",
        "co-located": "co-located",
        "new": "new",
        "ready": "ready",
        "ordinary": "ordinary",
        "easier": "easier",
        "more": "more",
        "automotive": "automotive",
        "team": "team",
        "iconic": "iconic",
        "industry-facing": "industry-facing",
        "ve": "ve",
        "true": "true",
        "top": "top",
        "primary": "primary",
        "smart": "smart",
        "progressive": "progressive",
        "better": "better",
        "next": "next",
        "re": "re",
        "ll": "ll",
        "common": "common",
        "Equal": "Equal",
        "qualified": "qualified",
        "individual": "individual",
        "national": "national",
        "sexual": "sexual",
        "physical": "physical",
        "mental": "mental",
        "genetic": "genetic",
        "characteristic": "characteristic",
        "Similar": "Similar",
        "applicant": "applicant",
        "unsolicited": "unsolicited"
      },
      "NOUN": {
        "Central": "Central",
        "Pkwy": "Pkwy",
        "Atlanta": "Atlanta",
        "GA": "GA",
        "USADivision": "USADivision",
        "Cox": "Cox",
        "AutomotiveJob": "AutomotiveJob",
        "Level": "Level",
        "ContributorTravel": "ContributorTravel",
        "NoSchedule": "NoSchedule",
        "Day": "Day",
        "JobRequisition": "JobRequisition",
        "Number": "Number",
        "Automotive": "Automotive",
        "Cloud": "Cloud",
        "Technical": "Technical",
        "Architect": "Architect",
        "Financial": "Financial",
        "Platforms": "Platforms",
        "Team": "Team",
        "team": "team",
        "configuration": "configuration",
        "Oracle": "Oracle",
        "Infrastructure": "Infrastructure",
        "OCI": "OCI",
        "platforms": "platforms",
        "E-Business": "E-Business",
        "EBS": "EBS",
        "implementations": "implementations",
        "Revenue": "Revenue",
        "Management": "Management",
        "Billing": "Billing",
        "RMB": "RMB",
        "OBIEE": "OBIEE",
        "reporting": "reporting",
        "replica": "replica",
        "position": "position",
        "infrastructure": "infrastructure",
        "direction": "direction",
        "development": "development",
        "concert": "concert",
        "application": "application",
        "delivery": "delivery",
        "teams": "teams",
        "production": "production",
        "operations": "operations",
        "decisions": "decisions",
        "projects": "projects",
        "role": "role",
        "understanding": "understanding",
        "processes": "processes",
        "organization": "organization",
        "technology": "technology",
        "portfolio": "portfolio",
        "capabilities": "capabilities",
        "options": "options",
        "reliability": "reliability",
        "scalability": "scalability",
        "consistency": "consistency",
        "suite": "suite",
        "staff": "staff",
        "employees": "employees",
        "consultants": "consultants",
        "design": "design",
        "solutions": "solutions",
        "Technology": "Technology",
        "Suite": "Suite",
        "Business": "Business",
        "Intelligence": "Intelligence",
        "WebLogic": "WebLogic",
        "SOA": "SOA",
        "Github": "Github",
        "Jenkins": "Jenkins",
        "Ansible": "Ansible",
        "FlexDeployYour": "FlexDeployYour",
        "Role": "Role",
        "roadmap": "roadmap",
        "components": "components",
        "priorities": "priorities",
        "partnership": "partnership",
        "Platform": "Platform",
        "Application": "Application",
        "demands": "demands",
        "levels": "levels",
        "system": "system",
        "Understand": "Understand",
        "input": "input",
        "guidance": "guidance",
        "Budget": "Budget",
        "resourcesEnsure": "resourcesEnsure",
        "CAFÉ": "CAFÉ",
        "i.": "i.",
        "e.": "e.",
        "agile": "agile",
        "Break": "Break",
        "stories": "stories",
        "teamsDefine": "teamsDefine",
        "promote": "promote",
        "policies": "policies",
        "practices": "practices",
        "needs": "needs",
        "automation": "automation",
        "implementation": "implementation",
        "SDLC": "SDLC",
        "tools": "tools",
        "g.": "g.",
        "FlexDeploy": "FlexDeploy",
        "Drive": "Drive",
        "practice": "practice",
        "coding": "coding",
        "performance": "performance",
        "tuning": "tuning",
        "architecture": "architecture",
        "mindset": "mindset",
        "efficiencies": "efficiencies",
        "solution": "solution",
        "Partner": "Partner",
        "platform": "platform",
        "rollout": "rollout",
        "schedules": "schedules",
        "releases": "releases",
        "business": "business",
        "phases": "phases",
        "processReviews": "processReviews",
        "coordinates": "coordinates",
        "leadership": "leadership",
        "work": "work",
        "professionalsTranslates": "professionalsTranslates",
        "department": "department",
        "objectives": "objectives",
        "goals": "goals",
        "activitiesDisplays": "activitiesDisplays",
        "teamwork": "teamwork",
        "skills": "skills",
        "ability": "ability",
        "management": "management",
        "Qualifications": "Qualifications",
        "Experience": "Experience",
        "minimum": "minimum",
        "BA/BS": "BA/BS",
        "Degree": "Degree",
        "field": "field",
        "years": "years",
        "experience": "experience",
        "MS": "MS",
        "Ph": "Ph",
        "D.": "D.",
        "information": "information",
        "software": "software",
        "Agile": "Agile",
        "methods": "methods",
        "ERP": "ERP",
        "programs": "programs",
        "Communication": "Communication",
        "Skills": "Skills",
        "Proven": "Proven",
        "track": "track",
        "record": "record",
        "success": "success",
        "environment": "environment",
        "Ability": "Ability",
        "accessibility": "accessibility",
        "technologies": "technologies",
        "preferredSo": "preferredSo",
        "today": "today",
        "transform": "transform",
        "tomorrow": "tomorrow",
        "AutomotiveThere": "AutomotiveThere",
        "nothing": "nothing",
        "people": "people",
        "background": "background",
        "passion": "passion",
        "mobility": "mobility",
        "innovation": "innovation",
        "client": "client",
        "community": "community",
        "cars": "cars",
        "everyone": "everyone",
        "clients": "clients",
        "continents": "continents",
        "brands": "brands",
        "industry": "industry",
        "forward": "forward",
        "members": "members",
        "consumer": "consumer",
        "Autotrader": "Autotrader",
        "Kelley": "Kelley",
        "Blue": "Blue",
        "Book": "Book",
        "others": "others",
        "future": "future",
        "Dealer": "Dealer",
        "com": "com",
        "Manheim": "Manheim",
        "vAuto": "vAuto",
        "family": "family",
        "businesses": "businesses",
        "mark": "mark",
        "world-class": "world-class",
        "values": "values",
        "talent": "talent",
        "growth": "growth",
        "impact": "impact",
        "career": "career",
        "divisions": "divisions",
        "Communications": "Communications",
        "wave": "wave",
        "cities": "cities",
        "powerhouse": "powerhouse",
        "broadband": "broadband",
        "communications": "communications",
        "greener": "greener",
        "transportation": "transportation",
        "alternatives": "alternatives",
        "individuals": "individuals",
        "fleet": "fleet",
        "operators": "operators",
        "re": "re",
        "spaces": "spaces",
        "cleantech": "cleantech",
        "healthcare": "healthcare",
        "momentum": "momentum",
        "generation": "generation",
        "leaders": "leaders",
        "Learn": "Learn",
        "purpose": "purpose",
        "coxenterprises": "coxenterprises",
        "Employment": "Employment",
        "Opportunity": "Opportunity",
        "applicants/employees": "applicants/employees",
        "consideration": "consideration",
        "employment": "employment",
        "regard": "regard",
        "age": "age",
        "race": "race",
        "color": "color",
        "religion": "religion",
        "creed": "creed",
        "origin": "origin",
        "ancestry": "ancestry",
        "sex": "sex",
        "pregnancy": "pregnancy",
        "orientation": "orientation",
        "gender": "gender",
        "identity": "identity",
        "disability": "disability",
        "veteran": "veteran",
        "status": "status",
        "ethnicity": "ethnicity",
        "citizenship": "citizenship",
        "law": "law",
        "Statement": "Statement",
        "Third-Party": "Third-Party",
        "Agencies": "Agencies",
        "Organizations": "Organizations",
        "agencies": "agencies",
        "services": "services",
        "Please": "Please",
        "tracking": "tracking",
        "hiring": "hiring",
        "manager": "manager",
        "facility": "facility",
        "fees": "fees",
        "charges": "charges",
        "resumes": "resumes",
        "Job": "Job",
        "days": "days"
      },
      "NUM": {
        "10": "10",
        "14": "14",
        "1898": "1898",
        "202000821Cox": "202000821Cox",
        "5+": "5+",
        "3+": "3+",
        "40,000": "40,000",
        "five": "five"
      },
      "VERB": {
        "looking": "looking",
        "join": "join",
        "is": "is",
        "overseeing": "overseeing",
        "supports": "supports",
        "running": "running",
        "include": "include",
        "defining": "defining",
        "works": "works",
        "ensure": "ensure",
        "are": "are",
        "aligned": "aligned",
        "requires": "requires",
        "ensures": "ensures",
        "leading": "leading",
        "Use": "Use",
        "Drive": "Drive",
        "including": "including",
        "driving": "driving",
        "setting": "setting",
        "teamsLead": "teamsLead",
        "meet": "meet",
        "ensuring": "ensuring",
        "provide": "provide",
        "operates": "operates",
        "according": "according",
        "scaled": "scaled",
        "principles": "principles",
        "features": "features",
        "be": "be",
        "consumed": "consumed",
        "recognize": "recognize",
        "evolving": "evolving",
        "improve": "improve",
        "manage": "manage",
        "supported": "supported",
        "provides": "provides",
        "communicate": "communicate",
        "Required": "Required",
        "required": "required",
        "working": "working",
        "preferred": "preferred",
        "implementing": "implementing",
        "Look": "Look",
        "collaborate": "collaborate",
        "deliver": "deliver",
        "achieving": "achieving",
        "adapt": "adapt",
        "changing": "changing",
        "make": "make",
        "learn": "learn",
        "challenge": "challenge",
        "AreAbout": "AreAbout",
        "driven": "driven",
        "outreach": "outreach",
        "buying": "buying",
        "selling": "selling",
        "owning": "owning",
        "using": "using",
        "Touching": "Touching",
        "bring": "bring",
        "propel": "propel",
        "work": "work",
        "creating": "creating",
        "been": "been",
        "making": "making",
        "building": "building",
        "staying": "staying",
        "encouraging": "encouraging",
        "look": "look",
        "powering": "powering",
        "pioneering": "pioneering",
        "expanding": "expanding",
        "rev": "rev",
        "will": "will",
        "Sound": "Sound",
        "intriguing": "intriguing",
        "hope": "hope",
        "going": "going",
        "unites": "unites",
        "receive": "receive",
        "protected": "protected",
        "accepts": "accepts",
        "resumes": "resumes",
        "engage": "engage",
        "do": "do",
        "send": "send",
        "associated": "associated",
        "DetailsPosted": "DetailsPosted"
      },
      "PRT": {
        "to": "to",
        "up": "up"
      },
      "X": {}
    }
  },
  "e6611ed3-f0ef-45f8-8f92-6b935f8f80fe": {
    "Company": "Revature",
    "Job Title": "Software Developer (No Prior Experience Required)",
    "Job Details": "DescriptionRevature will hire over 300 new Software Developers in the next 4 weeks|||| As the largest employer of emerging tech talent, we are looking for candidates all around the U||||S||||One day someone is going to ask you where you got your start…This is IT!With a wide range of Fortune 500 enterprises, government organizations and top systems integrators as our clients, we not only provide you with the skills needed to succeed through an employer-paid training program  but will also give you the opportunity to put those skills to use, on projects that matter||||What We Are Looking ForCollege degree (Associates or Bachelors)Must be authorized to work in the USStrong desire to learn to code – No prior professional experience required|||| A natural problem solverStrong communication and interpersonal skillsWilling to relocate anywhere in the US – Relocation assistance providedWhat We OfferCompetitive salaryRelocation & housing assistanceHealth, vision & dental insurancePaid time offIndustry CertificationsLife Insurance Policy401kMentoring program and ongoing support throughout your entire Revature careerExperience with the largest and most reputable companies in the USApply Today|||| Interviews are going on now||||#SoftwareEngineering Equal Employment OpportunityThe Company is an equal opportunity employer|||| We will extend equal opportunity to all individuals without regard to race, religion, color, sex, pregnancy, childbirth or related medical conditions, sexual orientation, gender identity, national origin, disability, age, genetic information, marital status, veteran status, or any other status protected under applicable federal, state, or local laws|||| This policy applies to all terms and conditions of employment, including but not limited to, hiring, placement, promotion, termination, layoff, recall, transfer, leaves of absence, benefits, compensation and training|||| If you require an accommodation to work based on any of these protected factors, please notify the Human Resources Department, and the Company will evaluate the request and provide an accommodation in accordance with applicable law||||We seek to comply with all applicable federal, state and local laws related to discrimination and will not tolerate the interference with the ability of any of the Company’s employees to perform their job duties|||| Our policy reflects and affirms the Company’s commitment to the principles of fair employment and the elimination of all discriminatory practices||||Job DetailsPosted 6 days ago||||",
    "KeyWords": {
      "NOUN": {
        "Software": "Software",
        "Developers": "Developers",
        "weeks": "weeks",
        "employer": "employer",
        "talent": "talent",
        "candidates": "candidates",
        "U.": "U.",
        "S.": "S.",
        "One": "One",
        "day": "day",
        "someone": "someone",
        "start…This": "start…This",
        "IT": "IT",
        "range": "range",
        "Fortune": "Fortune",
        "enterprises": "enterprises",
        "government": "government",
        "organizations": "organizations",
        "systems": "systems",
        "integrators": "integrators",
        "clients": "clients",
        "skills": "skills",
        "training": "training",
        "program": "program",
        "opportunity": "opportunity",
        "projects": "projects",
        "matter": "matter",
        "ForCollege": "ForCollege",
        "degree": "degree",
        "Associates": "Associates",
        "Bachelors": "Bachelors",
        "Must": "Must",
        "USStrong": "USStrong",
        "desire": "desire",
        "No": "No",
        "experience": "experience",
        "problem": "problem",
        "solverStrong": "solverStrong",
        "communication": "communication",
        "skillsWilling": "skillsWilling",
        "US": "US",
        "Relocation": "Relocation",
        "assistance": "assistance",
        "OfferCompetitive": "OfferCompetitive",
        "salaryRelocation": "salaryRelocation",
        "housing": "housing",
        "assistanceHealth": "assistanceHealth",
        "vision": "vision",
        "dental": "dental",
        "insurancePaid": "insurancePaid",
        "time": "time",
        "offIndustry": "offIndustry",
        "CertificationsLife": "CertificationsLife",
        "Insurance": "Insurance",
        "Policy401kMentoring": "Policy401kMentoring",
        "support": "support",
        "Revature": "Revature",
        "careerExperience": "careerExperience",
        "companies": "companies",
        "USApply": "USApply",
        "Today": "Today",
        "Interviews": "Interviews",
        "Employment": "Employment",
        "OpportunityThe": "OpportunityThe",
        "Company": "Company",
        "individuals": "individuals",
        "regard": "regard",
        "race": "race",
        "religion": "religion",
        "color": "color",
        "sex": "sex",
        "pregnancy": "pregnancy",
        "childbirth": "childbirth",
        "conditions": "conditions",
        "orientation": "orientation",
        "gender": "gender",
        "identity": "identity",
        "origin": "origin",
        "disability": "disability",
        "age": "age",
        "information": "information",
        "status": "status",
        "veteran": "veteran",
        "state": "state",
        "laws": "laws",
        "policy": "policy",
        "terms": "terms",
        "employment": "employment",
        "placement": "placement",
        "promotion": "promotion",
        "termination": "termination",
        "layoff": "layoff",
        "recall": "recall",
        "transfer": "transfer",
        "absence": "absence",
        "benefits": "benefits",
        "compensation": "compensation",
        "accommodation": "accommodation",
        "factors": "factors",
        "Human": "Human",
        "Resources": "Resources",
        "Department": "Department",
        "request": "request",
        "accordance": "accordance",
        "law": "law",
        "discrimination": "discrimination",
        "interference": "interference",
        "ability": "ability",
        "employees": "employees",
        "job": "job",
        "duties": "duties",
        "commitment": "commitment",
        "principles": "principles",
        "elimination": "elimination",
        "practices": "practices",
        "Job": "Job",
        "days": "days"
      },
      "VERB": {
        "hire": "hire",
        "emerging": "emerging",
        "are": "are",
        "looking": "looking",
        "is": "is",
        "going": "going",
        "ask": "ask",
        "got": "got",
        "provide": "provide",
        "needed": "needed",
        "succeed": "succeed",
        "will": "will",
        "give": "give",
        "put": "put",
        "use": "use",
        "Are": "Are",
        "Looking": "Looking",
        "be": "be",
        "authorized": "authorized",
        "work": "work",
        "learn": "learn",
        "code": "code",
        "required": "required",
        "relocate": "relocate",
        "ongoing": "ongoing",
        "SoftwareEngineering": "SoftwareEngineering",
        "extend": "extend",
        "protected": "protected",
        "applies": "applies",
        "including": "including",
        "hiring": "hiring",
        "leaves": "leaves",
        "require": "require",
        "based": "based",
        "please": "please",
        "notify": "notify",
        "evaluate": "evaluate",
        "seek": "seek",
        "comply": "comply",
        "related": "related",
        "tolerate": "tolerate",
        "perform": "perform",
        "reflects": "reflects",
        "affirms": "affirms",
        "DetailsPosted": "DetailsPosted"
      },
      "NUM": {
        "500": "500"
      },
      "ADJ": {
        "next": "next",
        "largest": "largest",
        "tech": "tech",
        "wide": "wide",
        "top": "top",
        "employer-paid": "employer-paid",
        "prior": "prior",
        "professional": "professional",
        "natural": "natural",
        "interpersonal": "interpersonal",
        "entire": "entire",
        "reputable": "reputable",
        "Equal": "Equal",
        "equal": "equal",
        "related": "related",
        "medical": "medical",
        "sexual": "sexual",
        "national": "national",
        "genetic": "genetic",
        "marital": "marital",
        "other": "other",
        "applicable": "applicable",
        "federal": "federal",
        "local": "local",
        "limited": "limited",
        "protected": "protected",
        "fair": "fair",
        "discriminatory": "discriminatory"
      },
      "PRT": {
        "to": "to"
      }
    }
  },
  "8d2c63cc-39fd-45e0-846c-84843beefe05": {
    "Company": "Covance",
    "Job Title": "Software Engineer - DB/C or PL/B",
    "Job Details": "DescriptionJob Overview:Note: This role is with our parent company, LabCorp (NYSE: LH), an S&P 500 company|||| LH is a leading global life sciences company that is deeply integrated in guiding patient care, providing comprehensive clinical laboratory and end-to-end drug development services|||| With a mission to improve health and improve lives, LabCorp delivers world-class diagnostic solutions, brings innovative medicines to patients faster and uses technology to improve the delivery of care|||| LabCorp reported net revenues of over $11 billion in 2018|||| Description Technical Skills:At least 5 years' experience in the DB/C or PL/B (DATABUS) programming languages||||Be proficient in a typical DB/C Linux development environment||||C#/||||NET experience a plus||||SQL Server Database Development experience a plus||||Previous experience working in a lab/healthcare environment a major plus||||General Software Engineering Skills:General Functional and OOP programming experience||||Ability to learn new technologies||||Ability to employ software development best practices and patterns||||Proficiency with modern source control systems (specifically TFVC)||||Good understanding of HL7, FHIR, XML, JSON, XSLT data models||||Knowledge in Test Driven Development and Continuous Integration is a plus||||  Education/Qualifications:RequirementsUS Citizenship is mandatory (DOD requirement)||||Preferred location is San Antonio, TX||||Remote working will be considered if candidate is open to some travel (post-Covid) to the CDD lab in San Antonio, TX||||Experience:At least 5 years' experience in the DB/C or PL/B (DATABUS) programming languages||||Job DetailsPosted 6 days ago||||",
    "KeyWords": {
      "NOUN": {
        "Overview": "Overview",
        "Note": "Note",
        "role": "role",
        "parent": "parent",
        "company": "company",
        "LabCorp": "LabCorp",
        "NYSE": "NYSE",
        "LH": "LH",
        "life": "life",
        "sciences": "sciences",
        "patient": "patient",
        "care": "care",
        "laboratory": "laboratory",
        "drug": "drug",
        "development": "development",
        "services": "services",
        "mission": "mission",
        "health": "health",
        "lives": "lives",
        "solutions": "solutions",
        "medicines": "medicines",
        "patients": "patients",
        "technology": "technology",
        "delivery": "delivery",
        "revenues": "revenues",
        "Description": "Description",
        "Technical": "Technical",
        "Skills": "Skills",
        "years": "years",
        "experience": "experience",
        "DB/C": "DB/C",
        "PL/B": "PL/B",
        "DATABUS": "DATABUS",
        "programming": "programming",
        "languages": "languages",
        "Linux": "Linux",
        "environment": "environment",
        "NET": "NET",
        "plus": "plus",
        "SQL": "SQL",
        "Server": "Server",
        "Database": "Database",
        "Development": "Development",
        "lab/healthcare": "lab/healthcare",
        "General": "General",
        "Software": "Software",
        "Engineering": "Engineering",
        "Functional": "Functional",
        "OOP": "OOP",
        "Ability": "Ability",
        "technologies": "technologies",
        "software": "software",
        "practices": "practices",
        "patterns": "patterns",
        "Proficiency": "Proficiency",
        "source": "source",
        "control": "control",
        "systems": "systems",
        "TFVC": "TFVC",
        "understanding": "understanding",
        "HL7": "HL7",
        "FHIR": "FHIR",
        "XML": "XML",
        "JSON": "JSON",
        "XSLT": "XSLT",
        "data": "data",
        "models": "models",
        "Knowledge": "Knowledge",
        "Test": "Test",
        "Driven": "Driven",
        "Continuous": "Continuous",
        "Integration": "Integration",
        "Education/Qualifications": "Education/Qualifications",
        "RequirementsUS": "RequirementsUS",
        "Citizenship": "Citizenship",
        "DOD": "DOD",
        "requirement": "requirement",
        "location": "location",
        "San": "San",
        "Antonio": "Antonio",
        "TX": "TX",
        "Remote": "Remote",
        "candidate": "candidate",
        "travel": "travel",
        "CDD": "CDD",
        "lab": "lab",
        "Experience": "Experience",
        "Job": "Job",
        "days": "days"
      },
      "VERB": {
        "is": "is",
        "leading": "leading",
        "integrated": "integrated",
        "guiding": "guiding",
        "providing": "providing",
        "improve": "improve",
        "delivers": "delivers",
        "brings": "brings",
        "uses": "uses",
        "reported": "reported",
        "Be": "Be",
        "working": "working",
        "programming": "programming",
        "learn": "learn",
        "employ": "employ",
        "Preferred": "Preferred",
        "will": "will",
        "be": "be",
        "considered": "considered",
        "DetailsPosted": "DetailsPosted"
      },
      "NUM": {
        "11": "11",
        "2018": "2018",
        "billion": "billion"
      },
      "ADJ": {
        "comprehensive": "comprehensive",
        "clinical": "clinical",
        "end-to-end": "end-to-end",
        "world-class": "world-class",
        "diagnostic": "diagnostic",
        "innovative": "innovative",
        "net": "net",
        "least": "least",
        "proficient": "proficient",
        "typical": "typical",
        "Previous": "Previous",
        "major": "major",
        "new": "new",
        "modern": "modern",
        "Good": "Good",
        "plus": "plus",
        "mandatory": "mandatory",
        "open": "open",
        "post-Covid": "post-Covid"
      },
      "PRT": {
        "to": "to"
      }
    }
  },
  "cb858f69-19f9-4bb2-9dc3-d58073113bef": {
    "Company": "InComm",
    "Job Title": "Lead Software Test Engineer",
    "Job Details": "DescriptionAs a Lead QA Engineer, you will lead and provide direction to a team of testing professionals on automation and manual testing efforts|||| Provide training and mentorship to junior engineers while fostering strong relationships with clients and stakeholders||||ResponsibilitiesLead QA initiatives including leading a team of test professionals and contributing to the testing effort in a hands-on roleLead efforts to automate testing where possibleWork closely with cross-functional organizations, project teams and clients to develop project schedules, execute test plans and cases and deliver high quality productsSupport analysts and engineers by ensuring that test scripts are well documented and that all requirements are metEnsure that test team follows standardized testing processes and reporting proceduresRespond to scope changes from business stakeholdersReview product/project requirement documents for completenessCoordinates activities with Project Manager and Core project teamEscalate concerns, issues and risks to the appropriate stakeholders in order to meet project deadlinesMust be able to work under pressure and meet deadlines, while maintaining a positive attitudeWork closely with the QA Manager to evaluate and enhance QA standards, technologies and approachesAssist in creating the QA project documentation (e||||g|||| templates for requirements traceability, test plans, cycles, cases, scripts and standardized reports, such as a root-cause bug report and a test execution progress report), and trainingUse functional specifications to plan, create, or sign-off on test plans, test cases, and automated test cases||||Defines and tracks quality assurance metrics such as defects, defect counts, test results and test status||||Participate in training and mentoring other members of the QA staffAct as a strong advocate for quality in the product/project development process for softwareImplement ongoing quality improvement processes and tools working with interdepartmental teamsMust have strong relationship building skills and able to establish and maintain positive work relationships with peers, management, key stakeholders and clientsStrong verbal and written communications skills, with an ability to present complex concepts and make them understood at all levels of the organization, both to technical and non-technical team members and stakeholders, etc||||QualificationsBasic programming skills to create automated test scripts|||| Strong organizational skills, ability to establish priorities, multi-task, handle competing priorities and follow through on all open items/tasks||||Strong knowledge of QA tools including Test Automation (Robot Framework preferred) and Load Testing||||Solid understanding of the software development lifecycle Knowledge of database technologies Experience in navigating across cross-functional teamsStrong verbal and written communications are critical||||Education A Bachelors degree in CIS or MIS or equivalent experience5 - 10 years relevant experience overall QA experience Youre a Superstar if you have:Knowledge of Robot Framework and Python experience||||Job DetailsPosted 2 days ago||||",
    "KeyWords": {
      "VERB": {
        "will": "will",
        "lead": "lead",
        "provide": "provide",
        "testing": "testing",
        "Provide": "Provide",
        "fostering": "fostering",
        "initiatives": "initiatives",
        "including": "including",
        "leading": "leading",
        "contributing": "contributing",
        "automate": "automate",
        "develop": "develop",
        "execute": "execute",
        "deliver": "deliver",
        "ensuring": "ensuring",
        "are": "are",
        "documented": "documented",
        "follows": "follows",
        "standardized": "standardized",
        "reporting": "reporting",
        "scope": "scope",
        "product/project": "product/project",
        "meet": "meet",
        "be": "be",
        "work": "work",
        "maintaining": "maintaining",
        "evaluate": "evaluate",
        "enhance": "enhance",
        "creating": "creating",
        "plan": "plan",
        "create": "create",
        "automated": "automated",
        "Participate": "Participate",
        "mentoring": "mentoring",
        "working": "working",
        "have": "have",
        "establish": "establish",
        "maintain": "maintain",
        "written": "written",
        "present": "present",
        "make": "make",
        "understood": "understood",
        "programming": "programming",
        "handle": "handle",
        "competing": "competing",
        "follow": "follow",
        "preferred": "preferred",
        "navigating": "navigating",
        "DetailsPosted": "DetailsPosted"
      },
      "NOUN": {
        "QA": "QA",
        "Engineer": "Engineer",
        "direction": "direction",
        "team": "team",
        "professionals": "professionals",
        "automation": "automation",
        "testing": "testing",
        "efforts": "efforts",
        "training": "training",
        "mentorship": "mentorship",
        "engineers": "engineers",
        "relationships": "relationships",
        "clients": "clients",
        "stakeholders": "stakeholders",
        "ResponsibilitiesLead": "ResponsibilitiesLead",
        "test": "test",
        "effort": "effort",
        "roleLead": "roleLead",
        "possibleWork": "possibleWork",
        "organizations": "organizations",
        "project": "project",
        "teams": "teams",
        "schedules": "schedules",
        "plans": "plans",
        "cases": "cases",
        "quality": "quality",
        "productsSupport": "productsSupport",
        "analysts": "analysts",
        "scripts": "scripts",
        "requirements": "requirements",
        "metEnsure": "metEnsure",
        "processes": "processes",
        "proceduresRespond": "proceduresRespond",
        "changes": "changes",
        "business": "business",
        "stakeholdersReview": "stakeholdersReview",
        "requirement": "requirement",
        "documents": "documents",
        "completenessCoordinates": "completenessCoordinates",
        "activities": "activities",
        "Project": "Project",
        "Manager": "Manager",
        "Core": "Core",
        "teamEscalate": "teamEscalate",
        "concerns": "concerns",
        "issues": "issues",
        "risks": "risks",
        "order": "order",
        "pressure": "pressure",
        "meet": "meet",
        "deadlines": "deadlines",
        "attitudeWork": "attitudeWork",
        "standards": "standards",
        "technologies": "technologies",
        "approachesAssist": "approachesAssist",
        "documentation": "documentation",
        "g.": "g.",
        "templates": "templates",
        "traceability": "traceability",
        "cycles": "cycles",
        "reports": "reports",
        "bug": "bug",
        "report": "report",
        "execution": "execution",
        "progress": "progress",
        "specifications": "specifications",
        "sign-off": "sign-off",
        "Defines": "Defines",
        "tracks": "tracks",
        "assurance": "assurance",
        "metrics": "metrics",
        "defects": "defects",
        "counts": "counts",
        "results": "results",
        "status": "status",
        "members": "members",
        "staffAct": "staffAct",
        "advocate": "advocate",
        "product/project": "product/project",
        "development": "development",
        "process": "process",
        "softwareImplement": "softwareImplement",
        "improvement": "improvement",
        "tools": "tools",
        "teamsMust": "teamsMust",
        "relationship": "relationship",
        "building": "building",
        "skills": "skills",
        "work": "work",
        "peers": "peers",
        "management": "management",
        "communications": "communications",
        "ability": "ability",
        "concepts": "concepts",
        "levels": "levels",
        "organization": "organization",
        "Strong": "Strong",
        "priorities": "priorities",
        "multi-task": "multi-task",
        "items/tasks": "items/tasks",
        "knowledge": "knowledge",
        "Test": "Test",
        "Automation": "Automation",
        "Robot": "Robot",
        "Framework": "Framework",
        "Load": "Load",
        "Testing": "Testing",
        "Solid": "Solid",
        "understanding": "understanding",
        "software": "software",
        "lifecycle": "lifecycle",
        "Knowledge": "Knowledge",
        "database": "database",
        "Experience": "Experience",
        "teamsStrong": "teamsStrong",
        "Education": "Education",
        "Bachelors": "Bachelors",
        "degree": "degree",
        "CIS": "CIS",
        "MIS": "MIS",
        "years": "years",
        "experience": "experience",
        "Youre": "Youre",
        "Superstar": "Superstar",
        "Python": "Python",
        "Job": "Job",
        "days": "days"
      },
      "PRT": {
        "to": "to"
      },
      "ADJ": {
        "junior": "junior",
        "strong": "strong",
        "hands-on": "hands-on",
        "cross-functional": "cross-functional",
        "high": "high",
        "appropriate": "appropriate",
        "able": "able",
        "positive": "positive",
        "e.": "e.",
        "standardized": "standardized",
        "such": "such",
        "root-cause": "root-cause",
        "trainingUse": "trainingUse",
        "functional": "functional",
        "defect": "defect",
        "other": "other",
        "ongoing": "ongoing",
        "interdepartmental": "interdepartmental",
        "key": "key",
        "clientsStrong": "clientsStrong",
        "verbal": "verbal",
        "complex": "complex",
        "technical": "technical",
        "non-technical": "non-technical",
        "QualificationsBasic": "QualificationsBasic",
        "automated": "automated",
        "organizational": "organizational",
        "open": "open",
        "critical": "critical",
        "equivalent": "equivalent",
        "relevant": "relevant",
        "overall": "overall"
      },
      "X": {
        "experience5": "experience5"
      },
      "NUM": {}
    }
  },
  "11fc5069-93ed-4dee-b5d1-aea3deed25b3": {
    "Company": "Beech Valley Solutions",
    "Job Title": "Senior Cloud Accountant",
    "Job Details": "DescriptionSenior Accountant (Cloud Accounting)\nLocation: RemoteType: Contract / ConsultingRate: $25 - $30 / hourDuration: Long-term ; IndefiniteWe are searching for the top Cloud Accountants in the world|||| Do you fit the bill?\nAs a Senior Cloud Accountant with Beech Valley 360, you will be working remotely as an advisor to cutting edge companies in the United States||||\nYour responsibilities will include day-to-day bookkeeping and reporting for businesses who use our bookkeeping services|||| Your daily tasks will involve classifying transactions, reconciling bank activity, and recording adjustments|||| You also will likely be involved with overseeing and working with other cloud accountants|||| You must be a Xero Certified Advisor or a Quickbooks ProAdvisor to be considered||||\nThe right person has a detailed understanding of accounting and bookkeeping and must understand the differences between cash and accrual accounting|||| Day-to-day accounting and financial reporting come naturally|||| The role will involve preparing monthly reporting packages that our clients’ management teams can rely upon for decision-making||||\nResponsibilities:\n\nCommunicate with clients on a regular basis to ensure all day-to-day accounting is being performed timely and accurately\nPrepare daily, weekly, monthly financial reporting for management\nReview bookkeeping work and provide feedback to bookkeeping team\nAbility to recommend best practices to management\n\nJob requirements:\n\nDegree in Accounting/Finance/Business or equivalent work experience\n5+ years of hands-on Finance or Accounting experience\nEnglish-speaking skills - must be fluent in English with strong reading, writing, and speaking skills\nProficiency in Quickbooks Online and Xero accounting platforms\nProficient in MS Office and GSuite / Google Apps\n\nAbout Beech Valley 360:Beech Valley 360 provides organizations with top-tier cloud accountants on demand||||\nFounded by ex-Big 4 CPAs, we are the leading talent solution for top accounting talent ready to embrace the gig economy||||\nTo ensure that we’re connecting clients with top-quality professionals, our vetting process includes interviews with ex-public accounting professionals on staff, as well as a proprietary pre-hire testing methodology powered by data science that’s been proven to correlate with project success||||\nWith extensive public accounting and industry experience, we understand the unique contract and full-time accounting and finance needs of our clients|||| We work with organizations of all sizes and can connect firms with hand-picked professionals able to work immediately, without the burden of having to attract and retain these individuals ‘in house’ year-round||||\nLearn more about Beech Valley by visiting our website||||Job DetailsPosted 3 days ago||||",
    "KeyWords": {
      "NOUN": {
        "Accountant": "Accountant",
        "Cloud": "Cloud",
        "Accounting": "Accounting",
        "Location": "Location",
        "RemoteType": "RemoteType",
        "Contract": "Contract",
        "ConsultingRate": "ConsultingRate",
        "hourDuration": "hourDuration",
        "IndefiniteWe": "IndefiniteWe",
        "Accountants": "Accountants",
        "world": "world",
        "bill": "bill",
        "Senior": "Senior",
        "Beech": "Beech",
        "Valley": "Valley",
        "advisor": "advisor",
        "edge": "edge",
        "companies": "companies",
        "United": "United",
        "States": "States",
        "responsibilities": "responsibilities",
        "bookkeeping": "bookkeeping",
        "reporting": "reporting",
        "businesses": "businesses",
        "services": "services",
        "tasks": "tasks",
        "transactions": "transactions",
        "bank": "bank",
        "activity": "activity",
        "adjustments": "adjustments",
        "accountants": "accountants",
        "Xero": "Xero",
        "Certified": "Certified",
        "Advisor": "Advisor",
        "Quickbooks": "Quickbooks",
        "ProAdvisor": "ProAdvisor",
        "person": "person",
        "understanding": "understanding",
        "accounting": "accounting",
        "differences": "differences",
        "cash": "cash",
        "role": "role",
        "packages": "packages",
        "clients": "clients",
        "management": "management",
        "teams": "teams",
        "decision-making": "decision-making",
        "Responsibilities": "Responsibilities",
        "Communicate": "Communicate",
        "basis": "basis",
        "Prepare": "Prepare",
        "Review": "Review",
        "work": "work",
        "feedback": "feedback",
        "team": "team",
        "Ability": "Ability",
        "practices": "practices",
        "Job": "Job",
        "requirements": "requirements",
        "Degree": "Degree",
        "Accounting/Finance/Business": "Accounting/Finance/Business",
        "experience": "experience",
        "years": "years",
        "Finance": "Finance",
        "English-speaking": "English-speaking",
        "English": "English",
        "reading": "reading",
        "writing": "writing",
        "skills": "skills",
        "Proficiency": "Proficiency",
        "Online": "Online",
        "platforms": "platforms",
        "Proficient": "Proficient",
        "MS": "MS",
        "Office": "Office",
        "GSuite": "GSuite",
        "Google": "Google",
        "Apps": "Apps",
        "organizations": "organizations",
        "cloud": "cloud",
        "demand": "demand",
        "CPAs": "CPAs",
        "solution": "solution",
        "talent": "talent",
        "economy": "economy",
        "top-quality": "top-quality",
        "professionals": "professionals",
        "process": "process",
        "interviews": "interviews",
        "staff": "staff",
        "pre-hire": "pre-hire",
        "methodology": "methodology",
        "data": "data",
        "science": "science",
        "project": "project",
        "success": "success",
        "industry": "industry",
        "unique": "unique",
        "contract": "contract",
        "finance": "finance",
        "needs": "needs",
        "sizes": "sizes",
        "firms": "firms",
        "burden": "burden",
        "individuals": "individuals",
        "house": "house",
        "year-round": "year-round",
        "website": "website",
        "days": "days"
      },
      "NUM": {
        "30": "30",
        "360": "360",
        "5+": "5+"
      },
      "ADJ": {
        "top": "top",
        "day-to-day": "day-to-day",
        "daily": "daily",
        "other": "other",
        "cloud": "cloud",
        "right": "right",
        "detailed": "detailed",
        "accrual": "accrual",
        "Day-to-day": "Day-to-day",
        "financial": "financial",
        "monthly": "monthly",
        "regular": "regular",
        "weekly": "weekly",
        "best": "best",
        "equivalent": "equivalent",
        "hands-on": "hands-on",
        "strong": "strong",
        "top-tier": "top-tier",
        "ex-Big": "ex-Big",
        "talent": "talent",
        "ready": "ready",
        "gig": "gig",
        "re": "re",
        "ex-public": "ex-public",
        "proprietary": "proprietary",
        "extensive": "extensive",
        "public": "public",
        "full-time": "full-time",
        "hand-picked": "hand-picked",
        "able": "able",
        "more": "more"
      },
      "VERB": {
        "searching": "searching",
        "Do": "Do",
        "fit": "fit",
        "will": "will",
        "be": "be",
        "working": "working",
        "cutting": "cutting",
        "include": "include",
        "use": "use",
        "involve": "involve",
        "classifying": "classifying",
        "reconciling": "reconciling",
        "recording": "recording",
        "involved": "involved",
        "overseeing": "overseeing",
        "must": "must",
        "considered": "considered",
        "has": "has",
        "understand": "understand",
        "come": "come",
        "preparing": "preparing",
        "can": "can",
        "rely": "rely",
        "ensure": "ensure",
        "is": "is",
        "being": "being",
        "performed": "performed",
        "provide": "provide",
        "bookkeeping": "bookkeeping",
        "recommend": "recommend",
        "skills": "skills",
        "fluent": "fluent",
        "speaking": "speaking",
        "provides": "provides",
        "Founded": "Founded",
        "are": "are",
        "leading": "leading",
        "embrace": "embrace",
        "connecting": "connecting",
        "vetting": "vetting",
        "includes": "includes",
        "testing": "testing",
        "powered": "powered",
        "been": "been",
        "correlate": "correlate",
        "work": "work",
        "connect": "connect",
        "having": "having",
        "attract": "attract",
        "retain": "retain",
        "Learn": "Learn",
        "visiting": "visiting",
        "DetailsPosted": "DetailsPosted"
      },
      "PRT": {
        "to": "to",
        "To": "To"
      }
    }
  },
  "0acbeb16-a9bc-46e1-bf06-76611c3b064c": {
    "Company": "Pyramid Consulting, Inc",
    "Job Title": "Software Developer",
    "Job Details": "DescriptionJob DescriptionImmediate need for a talented Software Developer with experience in the Telecom Industry|||| This is a 06+ Months Contract opportunity with long-term potential and is located in Atlanta, GA|||| Please review the job description below|||| Job ID: 21-00386Key Responsibilities:B||||E/B Tech in Computer Engineering, Electronics or BSc in Computer Science/IT5+ years of software development experience3+ years programming experience in core Java , Android Java , KotlinExperience in developing Embedded/Infotainment Systems (C, C++, or Java) ||||2+ years of Android Java/Kotlin application development experience in Android Studio and Gradle/MavenGood communication skillsKey Requirements and Technology Experience:Familiar with best practices in Android application development and preferably Android AutomotiveExperience with IPC methods such as Binder, AIDL/HIDL, Message QueuesExperience with software development for the automotive and/or off highway vehicle industryUnderstanding of Automotive networking protocols such as J1939, CAN, LINExperience with Git and Gerrit in a team environmentExperience with established Software Development Processes such as V-Model or AgileExperience with unit test toolsMajor Responsibilities:Design and implement Android applications for Operator Interface Displays , Infotainment systems(Android Automotive)||||Interact with customer and gather requirements, requirement analysis and clarificationHelp define requirements and evaluate technical feasibility of implementationEstimate effort for software deliverablesAnalyze and root cause software issuesParticipate in code reviewsDesign and execute unit testsInterface with co-located internal and external development teamOur client is a leading Telecom Industry and we are currently interviewing to fill this and other similar contract positions|||| If you are interested in this position, please apply online for immediate consideration|||| J2W:CB3Job DetailsPostedToday||||",
    "KeyWords": {
      "NOUN": {
        "DescriptionImmediate": "DescriptionImmediate",
        "need": "need",
        "Software": "Software",
        "Developer": "Developer",
        "experience": "experience",
        "Telecom": "Telecom",
        "Industry": "Industry",
        "Months": "Months",
        "Contract": "Contract",
        "opportunity": "opportunity",
        "potential": "potential",
        "Atlanta": "Atlanta",
        "GA": "GA",
        "Please": "Please",
        "job": "job",
        "description": "description",
        "Job": "Job",
        "ID": "ID",
        "Responsibilities": "Responsibilities",
        "B.": "B.",
        "E/B": "E/B",
        "Tech": "Tech",
        "Computer": "Computer",
        "Engineering": "Engineering",
        "Electronics": "Electronics",
        "BSc": "BSc",
        "Science/IT5+": "Science/IT5+",
        "years": "years",
        "software": "software",
        "development": "development",
        "core": "core",
        "Java": "Java",
        "Android": "Android",
        "KotlinExperience": "KotlinExperience",
        "Systems": "Systems",
        "C++": "C++",
        "Java/Kotlin": "Java/Kotlin",
        "application": "application",
        "Studio": "Studio",
        "Gradle/MavenGood": "Gradle/MavenGood",
        "communication": "communication",
        "skillsKey": "skillsKey",
        "Requirements": "Requirements",
        "Technology": "Technology",
        "Experience": "Experience",
        "Familiar": "Familiar",
        "practices": "practices",
        "AutomotiveExperience": "AutomotiveExperience",
        "IPC": "IPC",
        "methods": "methods",
        "Binder": "Binder",
        "AIDL/HIDL": "AIDL/HIDL",
        "Message": "Message",
        "QueuesExperience": "QueuesExperience",
        "and/or": "and/or",
        "highway": "highway",
        "vehicle": "vehicle",
        "industryUnderstanding": "industryUnderstanding",
        "Automotive": "Automotive",
        "protocols": "protocols",
        "J1939": "J1939",
        "CAN": "CAN",
        "LINExperience": "LINExperience",
        "Git": "Git",
        "Gerrit": "Gerrit",
        "team": "team",
        "environmentExperience": "environmentExperience",
        "Development": "Development",
        "V-Model": "V-Model",
        "AgileExperience": "AgileExperience",
        "unit": "unit",
        "test": "test",
        "Design": "Design",
        "implement": "implement",
        "applications": "applications",
        "Operator": "Operator",
        "Interface": "Interface",
        "Displays": "Displays",
        "Infotainment": "Infotainment",
        "systems": "systems",
        "Interact": "Interact",
        "customer": "customer",
        "gather": "gather",
        "requirements": "requirements",
        "analysis": "analysis",
        "clarificationHelp": "clarificationHelp",
        "define": "define",
        "feasibility": "feasibility",
        "implementationEstimate": "implementationEstimate",
        "effort": "effort",
        "deliverablesAnalyze": "deliverablesAnalyze",
        "root": "root",
        "cause": "cause",
        "issuesParticipate": "issuesParticipate",
        "code": "code",
        "reviewsDesign": "reviewsDesign",
        "testsInterface": "testsInterface",
        "teamOur": "teamOur",
        "client": "client",
        "contract": "contract",
        "positions": "positions",
        "position": "position",
        "online": "online",
        "consideration": "consideration",
        "J2W": "J2W",
        "CB3Job": "CB3Job",
        "DetailsPostedToday": "DetailsPostedToday"
      },
      "ADJ": {
        "06+": "06+",
        "long-term": "long-term",
        "21-00386Key": "21-00386Key",
        "Embedded/Infotainment": "Embedded/Infotainment",
        "best": "best",
        "such": "such",
        "automotive": "automotive",
        "toolsMajor": "toolsMajor",
        "requirement": "requirement",
        "technical": "technical",
        "co-located": "co-located",
        "internal": "internal",
        "external": "external",
        "other": "other",
        "similar": "similar",
        "interested": "interested",
        "immediate": "immediate"
      },
      "VERB": {
        "is": "is",
        "located": "located",
        "review": "review",
        "programming": "programming",
        "developing": "developing",
        "networking": "networking",
        "established": "established",
        "Processes": "Processes",
        "evaluate": "evaluate",
        "execute": "execute",
        "leading": "leading",
        "are": "are",
        "interviewing": "interviewing",
        "fill": "fill",
        "please": "please",
        "apply": "apply"
      },
      "NUM": {
        "2+": "2+"
      },
      "PRT": {}
    }
  }
}